{"features": [{"geometry": {"coordinates": [37.0674, 54.50503], "type": "Point"}, "properties": {"UPDATE_SCRIPT": "python add_town_by_geoname_id.py 11_\u0410\u043b\u0435\u043a\u0441\u0438\u043d.geojson 582750", "adminCode1": "76", "adminName1": "Tula", "countryCode": "RU", "countryId": "2017370", "countryName": "Russia", "fcl": "P", "fclName": "city, village,...", "fcode": "PPL", "fcodeName": "populated place", "geonameId": 582750, "hgr_SOURCE": "http://babel.hathitrust.org/cgi/pt?id=uc1.b4583201;view=1up;seq=10", "hgr_admin1_partofID": "35", "hgr_admin2_partofID": 82.0, "hgr_admin_hierarchy": "\u0442\u0443\u043b\u044c\u0441\u043a|\u0430\u043b\u0435\u043a\u0441\u0438\u043d", "hgr_alt_name_new_orth": null, "hgr_alt_name_old_orth": null, "hgr_description": "\u0410\u041b\u0415\u041a\u0421\u0418\u041d\u042a, \u0433\u043e\u0440\u043e\u0434\u044a \u0422\u0443\u043b\u044c\u0441\u043a\u0430\u0433\u043e \u041d\u0430\u043c\u0463\u0441\u0442\u043d\u0438\u0447\u0435\u0441\u0442\u0432\u0430. \u0417\u0434\u0463\u0441\u044c \u0431\u044b\u0432\u0430\u044e\u0442\u044a \u0434\u0432\u0463 \u0432\u044a \u0433\u043e\u0434\u0443 \u044f\u0440\u043c\u0430\u0440\u043a\u0438: \u043f\u0435\u0440\u0432\u0430\u044f \u0406\u044e\u043b\u044f 1, \u0432\u0442\u043e\u0440\u0430\u044f \u0410\u0432\u0433\u0443\u0441\u0442\u0430 29 \u0434\u043d\u044f. \u041d\u0430 \u043e\u043d\u044b\u044f \u043f\u0440\u0456\u0463\u0437\u0436\u0430\u044e\u0442\u044a \u0441\u044a \u0440\u0430\u0437\u043d\u044b\u043c\u0438 \u043c\u043e\u0441\u043a\u043e\u0442\u0438\u043b\u044c\u043d\u044b\u043c\u0438 \u0442\u043e\u0432\u0430\u0440\u0430\u043c\u0438.", "hgr_html_text": "\u0410\u041b\u0415\u041a\u0421\u0418\u041d\u042a, </span><span class=\"font0\" style=\"font-style:italic;\">\u0433\u043e\u0440\u043e\u0434\u044a</span><span class=\"font0\"> \u0422\u0443\u043b\u044c\u0441\u043a\u0430\u0433\u043e \u041d\u0430\u043c\u0463\u0441\u0442\u043d\u0438\u0447\u0435\u0441\u0442\u0432\u0430. \u0417\u0434\u0463\u0441\u044c \u0431\u044b\u0432\u0430\u044e\u0442\u044a \u0434\u0432\u0463 \u0432\u044a \u0433\u043e\u0434\u0443 \u044f\u0440\u043c\u0430\u0440\u043a\u0438: \u043f\u0435\u0440\u0432\u0430\u044f \u0406\u044e\u043b\u044f 1, \u0432\u0442\u043e\u0440\u0430\u044f \u0410\u0432\u0433\u0443\u0441\u0442\u0430 29 \u0434\u043d\u044f. \u041d\u0430 \u043e\u043d\u044b\u044f \u043f\u0440\u0456\u0463\u0437\u0436\u0430\u044e\u0442\u044a \u0441\u044a \u0440\u0430\u0437\u043d\u044b\u043c\u0438 \u043c\u043e\u0441\u043a\u043e\u0442\u0438\u043b\u044c\u043d\u044b\u043c\u0438 \u0442\u043e\u0432\u0430\u0440\u0430\u043c\u0438.</span>", "hgr_page": 11, "hgr_partof_id": "82.0", "hgr_prov_modern_sp": "\u0422\u0443\u043b\u044c\u0441\u043a\u043e\u0433\u043e \u041d\u0430\u043c\u0435\u0441\u0442\u043d\u0438\u0447\u0435\u0441\u0442\u0432\u0430", "hgr_prov_stem": "\u0442\u0443\u043b\u044c\u0441\u043a", "hgr_ru_new_orth": "\u0410\u043b\u0435\u043a\u0441\u0438\u043d", "hgr_ru_old_featuretype": "\u0433\u043e\u0440\u043e\u0434\u044a", "hgr_ru_old_orth": "\u0410\u043b\u0435\u043a\u0441\u0438\u043d\u044a", "hgr_ru_prov": "\u0422\u0443\u043b\u044c\u0441\u043a\u0430\u0433\u043e \u041d\u0430\u043c\u0463\u0441\u0442\u043d\u0438\u0447\u0435\u0441\u0442\u0432\u0430", "hgr_ru_uezd": null, "hgr_txt_id": 11, "hgr_uezd_modern_sp": null, "hgr_uezd_stem": "\u0430\u043b\u0435\u043a\u0441\u0438\u043d", "lat": "54.50503", "lng": "37.0674", "name": "Aleksin", "population": 66885, "toponymName": "Aleksin"}, "type": "Feature"}], "type": "FeatureCollection"}