{"type": "FeatureCollection", "features": [{"type": "Feature", "geometry": {"type": "Point", "coordinates": [37.11667, 54.25]}, "properties": {"countryId": "2017370", "adminName1": "Tula", "lat": "54.25", "toponymName": "Pavshino", "countryCode": "RU", "name": "Pavshino", "lng": "37.11667", "population": 0, "adminCode1": "76", "fclName": "city, village,...", "fcode": "PPL", "countryName": "Russia", "fcodeName": "populated place", "geonameId": 511981, "fcl": "P"}}, {"type": "Feature", "geometry": {"type": "Point", "coordinates": [37.13164, 54.25519]}, "properties": {"countryId": "2017370", "adminName1": "Tula", "lat": "54.25519", "toponymName": "Novoye Pavshino", "countryCode": "RU", "name": "Novoye Pavshino", "lng": "37.13164", "population": 0, "adminCode1": "76", "fclName": "city, village,...", "fcode": "PPL", "countryName": "Russia", "fcodeName": "populated place", "geonameId": 517465, "fcl": "P"}}, {"type": "Feature", "geometry": {"type": "Point", "coordinates": [37.15, 54.25]}, "properties": {"countryId": "2017370", "adminName1": "Tula", "lat": "54.25", "toponymName": "Staroye Pavshino", "countryCode": "RU", "name": "Staroye Pavshino", "lng": "37.15", "population": 0, "adminCode1": "76", "fclName": "city, village,...", "fcode": "PPLX", "countryName": "Russia", "fcodeName": "section of populated place", "geonameId": 488361, "fcl": "P"}}]}