{"features": [{"geometry": {"coordinates": [27.18335, 56.65231], "type": "Point"}, "properties": {"UPDATE_SCRIPT": "python add_town_by_geoname_id.py 198_\u0414\u0440\u0438\u0446\u0430\u043d\u044b_f0.8.geojson 460257", "adminCode1": "24", "adminName1": "R\u0113zeknes Rajons", "countryCode": "LV", "countryId": "458258", "countryName": "Latvia", "fcl": "P", "fclName": "city, village,...", "fcode": "PPL", "fcodeName": "populated place", "geonameId": 460257, "hgr_SOURCE": "http://babel.hathitrust.org/cgi/pt?id=uc1.b4583201;view=1up;seq=39", "hgr_admin1_partofID": "24", "hgr_admin2_partofID": 99.0, "hgr_admin_hierarchy": "\u043f\u043e\u043b\u043e\u0442\u0441\u043a|\u0434\u0438\u043d\u0430\u0431\u0443\u0440\u0433\u0441\u043a", "hgr_alt_name_old_orth": null, "hgr_description": "\u0414\u0420\u0418\u0426\u0410\u041d\u042b, \u043c\u0463\u0441\u0442\u0435\u0447\u043a\u043e \u041f\u043e\u043b\u043e\u0442\u0441\u043a\u0430\u0433\u043e \u041d\u0430\u043c\u0463\u0441\u0442\u043d\u0438\u0447\u0435\u0441\u0442\u0432\u0430 \u0432\u044a \u0414\u0438\u043d\u0430\u0431\u0443\u0440\u0433\u0441\u043a\u043e\u043c\u044a \u0443\u0463\u0437\u0434\u0463. \u0417\u0434\u0463\u0441\u044c \u0431\u044b\u0432\u0430\u044e\u0442\u044a \u0432\u044a \u0433\u043e\u0434\u0443 \u0434\u0432\u0463 \u044f\u0440\u043c\u0430\u0440\u043a\u0438; \u0442\u043e\u0440\u0433\u0443\u044e\u0442\u044a \u0420\u0438\u0436\u0441\u043a\u0430\u0433\u043e \u0414\u0432\u043e\u0440\u0446\u0430 \u043a\u0440\u0435\u0441\u0442\u044c\u044f\u043d\u0435 \u0440\u0430\u0437\u043d\u044b\u043c\u0438 \u043c\u0463\u043b\u043e\u0447\u043d\u044b\u043c\u0438 \u0442\u043e\u0432\u0430\u0440\u0430\u043c\u0438 , \u0432\u0438\u043d\u043e\u043c\u044a \u0438 \u043f\u0438\u0432\u043e\u043c\u044a.", "hgr_html_text": "\u0414\u0420\u0418\u0426\u0410\u041d\u042b, </span><span class=\"font0\" style=\"font-style:italic;\">\u043c\u0463\u0441\u0442\u0435\u0447\u043a\u043e</span><span class=\"font0\"> \u041f\u043e\u043b\u043e\u0442\u0441\u043a\u0430\u0433\u043e \u041d\u0430\u043c\u0463\u0441\u0442\u043d\u0438\u0447\u0435\u0441\u0442\u0432\u0430 \u0432\u044a \u0414\u0438\u043d\u0430\u0431\u0443\u0440\u0433\u0441\u043a\u043e\u043c\u044a \u0443\u0463\u0437\u0434\u0463. \u0417\u0434\u0463\u0441\u044c \u0431\u044b\u0432\u0430\u044e\u0442\u044a \u0432\u044a \u0433\u043e\u0434\u0443 \u0434\u0432\u0463 \u044f\u0440\u043c\u0430\u0440\u043a\u0438; \u0442\u043e\u0440\u0433\u0443\u044e\u0442\u044a \u0420\u0438\u0436\u0441\u043a\u0430\u0433\u043e \u0414\u0432\u043e\u0440\u0446\u0430 \u043a\u0440\u0435\u0441\u0442\u044c\u044f\u043d\u0435 \u0440\u0430\u0437\u043d\u044b\u043c\u0438 \u043c\u0463\u043b\u043e\u0447\u043d\u044b\u043c\u0438 \u0442\u043e\u0432\u0430\u0440\u0430\u043c\u0438 , \u0432\u0438\u043d\u043e\u043c\u044a \u0438</span><span class=\"font0\" style=\"font-weight:bold;\"> </span><span class=\"font0\">\u043f\u0438\u0432\u043e\u043c\u044a.</span>", "hgr_page": 40, "hgr_partof_id": "99.0", "hgr_prov_modern_sp": "\u041f\u043e\u043b\u043e\u0442\u0441\u043a\u043e\u0433\u043e \u041d\u0430\u043c\u0435\u0441\u0442\u043d\u0438\u0447\u0435\u0441\u0442\u0432\u0430", "hgr_prov_stem": "\u043f\u043e\u043b\u043e\u0442\u0441\u043a", "hgr_ru_new_orth": "\u0414\u0440\u0438\u0446\u0430\u043d\u044b", "hgr_ru_old_featuretype": "\u043c\u0463\u0441\u0442\u0435\u0447\u043a\u043e", "hgr_ru_old_orth": "\u0414\u0440\u0438\u0446\u0430\u043d\u044b", "hgr_ru_prov": "\u041f\u043e\u043b\u043e\u0442\u0441\u043a\u0430\u0433\u043e \u041d\u0430\u043c\u0463\u0441\u0442\u043d\u0438\u0447\u0435\u0441\u0442\u0432\u0430", "hgr_ru_uezd": "\u0414\u0438\u043d\u0430\u0431\u0443\u0440\u0433\u0441\u043a\u043e\u043c\u044a \u0443\u0463\u0437\u0434\u0463", "hgr_txt_id": 198, "hgr_uezd_modern_sp": "\u0414\u0438\u043d\u0430\u0431\u0443\u0440\u0433\u0441\u043a\u043e\u043c \u0443\u0435\u0437\u0434\u0435", "hgr_uezd_stem": "\u0434\u0438\u043d\u0430\u0431\u0443\u0440\u0433\u0441\u043a", "lat": "56.65231", "lng": "27.18335", "name": "Dric\u0113ni", "population": 0, "toponymName": "Dric\u0113ni"}, "type": "Feature"}], "type": "FeatureCollection"}