{"features": [{"geometry": {"coordinates": [36.37746, 57.93588], "type": "Point"}, "properties": {"UPDATE_SCRIPT": "python add_town_by_geoname_id.py 223_\u0415\u0441\u043a\u0435_f0.7.geojson 467013", "adminCode1": "77", "adminName1": "Tverskaya", "countryCode": "RU", "countryId": "2017370", "countryName": "Russia", "fcl": "P", "fclName": "city, village,...", "fcode": "PPL", "fcodeName": "populated place", "geonameId": 467013, "hgr_SOURCE": "http://babel.hathitrust.org/cgi/pt?id=uc1.b4583201;view=1up;seq=43", "hgr_admin1_partofID": "33", "hgr_admin2_partofID": 86.0, "hgr_admin_hierarchy": "\u0442\u0432\u0435\u0440\u0441\u043a|\u0431\u0435\u0436\u0435\u0446\u043a", "hgr_alt_name_new_orth": null, "hgr_alt_name_old_orth": null, "hgr_description": "\u0415\u0421\u041a\u0415, \u0441\u0435\u043b\u043e \u0422\u0432\u0435\u0440\u0441\u043a\u0430\u0433\u043e \u041d\u0430\u043c\u0463\u0441\u0442\u043d\u0438\u0447\u0435\u0441\u0442\u0432\u0430 \u0432\u044a \u0411\u0463\u0436\u0435\u0446\u043a\u043e\u043c\u044a \u0443\u0463\u0437\u0434\u0463. \u0417\u0434\u0463\u0441\u044c \u0431\u044b\u0432\u0430\u0435\u0442\u044a \u0433\u043e\u0434\u043e\u0432\u0430\u044f \u044f\u0440\u043c\u0430\u0440\u043a\u0430; \u0441\u044a\u0463\u0437\u0436\u0430\u044e\u0442\u0441\u044f \u043d\u0430 \u043e\u043d\u0443\u044e \u043a\u0443\u043f\u0446\u044b \u0441\u044a \u043c\u0463\u043b\u043e\u0447\u043d\u044b\u043c\u044a \u043b\u0430\u0432\u043e\u0447\u043d\u044b\u043c\u044a \u0442\u043e\u0432\u0430\u0440\u043e\u043c\u044a.", "hgr_html_text": "\u0415\u0421\u041a\u0415, </span><span class=\"font0\" style=\"font-style:italic;\">\u0441\u0435\u043b\u043e</span><span class=\"font0\"> \u0422\u0432\u0435\u0440\u0441\u043a\u0430\u0433\u043e \u041d\u0430\u043c\u0463\u0441\u0442\u043d\u0438\u0447\u0435\u0441\u0442\u0432\u0430 \u0432\u044a \u0411\u0463\u0436\u0435\u0446\u043a\u043e\u043c\u044a \u0443\u0463\u0437\u0434\u0463. \u0417\u0434\u0463\u0441\u044c \u0431\u044b\u0432\u0430\u0435\u0442\u044a \u0433\u043e\u0434\u043e\u0432\u0430\u044f \u044f\u0440\u043c\u0430\u0440\u043a\u0430; \u0441\u044a\u0463\u0437\u0436\u0430\u044e\u0442\u0441\u044f \u043d\u0430 \u043e\u043d\u0443\u044e \u043a\u0443\u043f\u0446\u044b \u0441\u044a \u043c\u0463\u043b\u043e\u0447\u043d\u044b\u043c\u044a \u043b\u0430\u0432\u043e\u0447\u043d\u044b\u043c\u044a \u0442\u043e\u0432\u0430\u0440\u043e\u043c\u044a.</span>", "hgr_page": 44, "hgr_partof_id": "86.0", "hgr_prov_modern_sp": "\u0422\u0432\u0435\u0440\u0441\u043a\u043e\u0433\u043e \u041d\u0430\u043c\u0435\u0441\u0442\u043d\u0438\u0447\u0435\u0441\u0442\u0432\u0430", "hgr_prov_stem": "\u0442\u0432\u0435\u0440\u0441\u043a", "hgr_ru_new_orth": "\u0415\u0441\u043a\u0435", "hgr_ru_old_featuretype": "\u0441\u0435\u043b\u043e", "hgr_ru_old_orth": "\u0415\u0441\u043a\u0435", "hgr_ru_prov": "\u0422\u0432\u0435\u0440\u0441\u043a\u0430\u0433\u043e \u041d\u0430\u043c\u0463\u0441\u0442\u043d\u0438\u0447\u0435\u0441\u0442\u0432\u0430", "hgr_ru_uezd": "\u0411\u0463\u0436\u0435\u0446\u043a\u043e\u043c\u044a \u0443\u0463\u0437\u0434\u0463", "hgr_txt_id": 223, "hgr_uezd_modern_sp": "\u0411\u0435\u0436\u0435\u0446\u043a\u043e\u043c \u0443\u0435\u0437\u0434\u0435", "hgr_uezd_stem": "\u0431\u0435\u0436\u0435\u0446\u043a", "lat": "57.93588", "lng": "36.37746", "name": "Yes'ki", "population": 0, "toponymName": "Yes\u2019ki"}, "type": "Feature"}], "type": "FeatureCollection"}