{"features": [{"geometry": {"coordinates": [42.49369, 52.31847], "type": "Point"}, "properties": {"UPDATE_SCRIPT": "python add_town_by_geoname_id.py 257_\u0418\u043d\u0436\u0430\u0432\u0435\u043d\u044c\u0435_f0.6.geojson 556275", "adminCode1": "72", "adminName1": "Tambov", "countryCode": "RU", "countryId": "2017370", "countryName": "Russia", "fcl": "P", "fclName": "city, village,...", "fcode": "PPL", "fcodeName": "populated place", "geonameId": 556275, "hgr_SOURCE": "http://babel.hathitrust.org/cgi/pt?id=uc1.b4583201;view=1up;seq=48", "hgr_admin1_partofID": "32", "hgr_admin2_partofID": 156.0, "hgr_admin_hierarchy": "\u0442\u0430\u043c\u0431\u043e\u0432\u0441\u043a|\u0448\u0430\u0442\u0441\u043a", "hgr_alt_name_new_orth": null, "hgr_alt_name_old_orth": null, "hgr_description": "\u0418\u041d\u0416\u0410\u0412\u0415\u041d\u042c\u0415, \u0441\u0435\u043b\u043e \u0440\u0430\u0437\u043d\u044b\u0445\u044a \u041f\u043e\u043c\u0463\u0449\u0438\u043a\u043e\u0432\u044a \u0422\u0430\u043c\u0431\u043e\u0432\u0441\u043a\u0430\u0433\u043e \u041d\u0430\u043c\u0463\u0441\u0442\u043d\u0438\u0447\u0435\u0441\u0442\u0432\u0430 \u0432\u044a \u0428\u0430\u0442\u0441\u043a\u043e\u043c\u044a \u0443\u0463\u0437\u0434\u0463. \u0417\u0434\u0463\u0441\u044c \u0431\u044b\u0432\u0430\u044e\u0442\u044a \u044f\u0440\u043c\u0430\u0440\u043a\u0438 \u0432\u044a \u0434\u0435\u0432\u044f\u0442\u0443\u044e , \u0434\u0435\u0441\u044f\u0442\u0443\u044e \u0438 \u043e\u0434\u0438\u043d\u0430\u0434\u0446\u0430\u0442\u0443\u044e \u043f\u044f\u0442\u043d\u0438\u0446\u044b \u043f\u043e \u041f\u0430\u0441\u0445\u0463; \u043d\u0430 \u043e\u043d\u044b\u0445\u044a \u0442\u043e\u0440\u0433\u0443\u044e\u0442\u044a \u043a\u0443\u043f\u0446\u044b \u0445\u043e\u043b\u0441\u0442\u043e\u043c\u044a, \u043f\u0435\u043d\u044c\u043a\u043e\u044e \u0438 \u043f\u0440\u043e\u0447\u0438\u043c\u044a.", "hgr_html_text": "\u0418\u041d\u0416\u0410\u0412\u0415\u041d\u042c\u0415, </span><span class=\"font0\" style=\"font-style:italic;\">\u0441\u0435\u043b\u043e</span><span class=\"font0\"> \u0440\u0430\u0437\u043d\u044b\u0445\u044a \u041f\u043e\u043c\u0463\u0449\u0438\u043a\u043e\u0432\u044a \u0422\u0430\u043c\u0431\u043e\u0432\u0441\u043a\u0430\u0433\u043e \u041d\u0430\u043c\u0463\u0441\u0442\u043d\u0438\u0447\u0435\u0441\u0442\u0432\u0430 \u0432\u044a \u0428\u0430\u0442\u0441\u043a\u043e\u043c\u044a \u0443\u0463\u0437\u0434\u0463. \u0417\u0434\u0463\u0441\u044c \u0431\u044b\u0432\u0430\u044e\u0442\u044a \u044f\u0440\u043c\u0430\u0440\u043a\u0438 \u0432\u044a \u0434\u0435\u0432\u044f\u0442\u0443\u044e , \u0434\u0435\u0441\u044f\u0442\u0443\u044e \u0438 \u043e\u0434\u0438\u043d\u0430\u0434\u0446\u0430\u0442\u0443\u044e \u043f\u044f\u0442\u043d\u0438\u0446\u044b \u043f\u043e \u041f\u0430\u0441\u0445\u0463; \u043d\u0430 \u043e\u043d\u044b\u0445\u044a \u0442\u043e\u0440\u0433\u0443\u044e\u0442\u044a \u043a\u0443\u043f\u0446\u044b \u0445\u043e\u043b\u0441\u0442\u043e\u043c\u044a, \u043f\u0435\u043d\u044c\u043a\u043e\u044e \u0438 \u043f\u0440\u043e\u0447\u0438\u043c\u044a.</span>", "hgr_page": 49, "hgr_partof_id": "156.0", "hgr_prov_modern_sp": "\u0422\u0430\u043c\u0431\u043e\u0432\u0441\u043a\u043e\u0433\u043e \u041d\u0430\u043c\u0435\u0441\u0442\u043d\u0438\u0447\u0435\u0441\u0442\u0432\u0430", "hgr_prov_stem": "\u0442\u0430\u043c\u0431\u043e\u0432\u0441\u043a", "hgr_ru_new_orth": "\u0418\u043d\u0436\u0430\u0432\u0435\u043d\u044c\u0435", "hgr_ru_old_featuretype": "\u0441\u0435\u043b\u043e", "hgr_ru_old_orth": "\u0418\u043d\u0436\u0430\u0432\u0435\u043d\u044c\u0435", "hgr_ru_prov": "\u0422\u0430\u043c\u0431\u043e\u0432\u0441\u043a\u0430\u0433\u043e \u041d\u0430\u043c\u0463\u0441\u0442\u043d\u0438\u0447\u0435\u0441\u0442\u0432\u0430", "hgr_ru_uezd": "\u0428\u0430\u0442\u0441\u043a\u043e\u043c\u044a \u0443\u0463\u0437\u0434\u0463", "hgr_txt_id": 257, "hgr_uezd_modern_sp": "\u0428\u0430\u0442\u0441\u043a\u043e\u043c \u0443\u0435\u0437\u0434\u0435", "hgr_uezd_stem": "\u0448\u0430\u0442\u0441\u043a", "lat": "52.31847", "lng": "42.49369", "name": "Inzhavino", "population": 10278, "toponymName": "Inzhavino"}, "type": "Feature"}], "type": "FeatureCollection"}