{"features": [{"geometry": {"coordinates": [32.34731, 50.15553], "type": "Point"}, "properties": {"UPDATE_SCRIPT": "python add_town_by_geoname_id.py 325_\u041a\u043e\u0440\u043e\u0432\u0430\u0439_f0.8.geojson 704879", "adminCode1": "18", "adminName1": "Poltava", "countryCode": "UA", "countryId": "690791", "countryName": "Ukraine", "fcl": "P", "fclName": "city, village,...", "fcode": "PPL", "fcodeName": "populated place", "geonameId": 704879, "hgr_SOURCE": "http://babel.hathitrust.org/cgi/pt?id=uc1.b4583201;view=1up;seq=58", "hgr_admin1_partofID": "13", "hgr_admin2_partofID": 122.0, "hgr_admin_hierarchy": "\u043a\u0438\u0435\u0432\u0441\u043a|\u043b\u0443\u0431\u0435\u043d\u0441\u043a", "hgr_alt_name_old_orth": null, "hgr_description": "\u041a\u041e\u0420\u041e\u0412\u0410\u0419, \u0441\u0435\u043b\u043e \u041a\u0456\u0435\u0432\u0441\u043a\u0430\u0433\u043e \u041d\u0430\u043c\u0463\u0441\u0442\u043d\u0438\u0447\u0435\u0441\u0442\u0432\u0430 \u0432\u044a \u041b\u0443\u0431\u0435\u043d\u0441\u043a\u043e\u043c\u044a \u0443\u0463\u0437\u0434\u0463. \u0412\u044a \u043e\u043d\u043e\u043c\u044a \u0431\u044b\u0432\u0430\u0435\u0442\u044a \u044f\u0440\u043c\u0430\u0440\u043a\u0430 \u043f\u043e\u0441\u043b\u0463 \u0421\u0432\u0463\u0442\u043b\u0430\u0433\u043e \u0412\u043e\u0441\u043a\u0440\u0435\u0441\u0435\u043d\u0456\u044f \u043e \u0434\u0435\u0441\u044f\u0442\u043e\u0439 \u043f\u044f\u0442\u043d\u0438\u0446\u0463.", "hgr_html_text": "\u041a\u041e\u0420\u041e\u0412\u0410\u0419, </span><span class=\"font0\" style=\"font-style:italic;\">\u0441\u0435\u043b\u043e</span><span class=\"font0\"> \u041a\u0456\u0435\u0432\u0441\u043a\u0430\u0433\u043e \u041d\u0430\u043c\u0463\u0441\u0442\u043d\u0438\u0447\u0435\u0441\u0442\u0432\u0430 \u0432\u044a \u041b\u0443\u0431\u0435\u043d\u0441\u043a\u043e\u043c\u044a \u0443\u0463\u0437\u0434\u0463. \u0412\u044a \u043e\u043d\u043e\u043c\u044a \u0431\u044b\u0432\u0430\u0435\u0442\u044a \u044f\u0440\u043c\u0430\u0440\u043a\u0430 \u043f\u043e\u0441\u043b\u0463 \u0421\u0432\u0463\u0442\u043b\u0430\u0433\u043e \u0412\u043e\u0441\u043a\u0440\u0435\u0441\u0435\u043d\u0456\u044f \u043e \u0434\u0435\u0441\u044f\u0442\u043e\u0439 \u043f\u044f\u0442\u043d\u0438\u0446\u0463.</span>", "hgr_page": 59, "hgr_partof_id": "122.0", "hgr_prov_modern_sp": "\u041a\u0438\u0435\u0432\u0441\u043a\u043e\u0433\u043e \u041d\u0430\u043c\u0435\u0441\u0442\u043d\u0438\u0447\u0435\u0441\u0442\u0432\u0430", "hgr_prov_stem": "\u043a\u0438\u0435\u0432\u0441\u043a", "hgr_ru_new_orth": "\u041a\u043e\u0440\u043e\u0432\u0430\u0439", "hgr_ru_old_featuretype": "\u0441\u0435\u043b\u043e", "hgr_ru_old_orth": "\u041a\u043e\u0440\u043e\u0432\u0430\u0439", "hgr_ru_prov": "\u041a\u0456\u0435\u0432\u0441\u043a\u0430\u0433\u043e \u041d\u0430\u043c\u0463\u0441\u0442\u043d\u0438\u0447\u0435\u0441\u0442\u0432\u0430", "hgr_ru_uezd": "\u041b\u0443\u0431\u0435\u043d\u0441\u043a\u043e\u043c\u044a \u0443\u0463\u0437\u0434\u0463", "hgr_uezd_modern_sp": "\u041b\u0443\u0431\u0435\u043d\u0441\u043a\u043e\u043c \u0443\u0435\u0437\u0434\u0435", "hgr_uezd_stem": "\u043b\u0443\u0431\u0435\u043d\u0441\u043a", "lat": "50.15553", "lng": "32.34731", "name": "Korovayi", "population": 0, "toponymName": "Korovayi"}, "type": "Feature"}], "type": "FeatureCollection"}