{"features": [{"geometry": {"coordinates": [38.45, 55.85], "type": "Point"}, "properties": {"UPDATE_SCRIPT": "python add_town_by_geoname_id.py 57_\u0411\u043e\u0433\u043e\u0440\u043e\u0434\u0441\u043a.geojson 575561", "adminCode1": "47", "adminName1": "Moskovskaya", "countryCode": "RU", "countryId": "2017370", "countryName": "Russia", "fcl": "P", "fclName": "city, village,...", "fcode": "PPL", "fcodeName": "populated place", "geonameId": 575561, "hgr_SOURCE": "http://babel.hathitrust.org/cgi/pt?id=uc1.b4583201;view=1up;seq=18", "hgr_admin1_partofID": "1", "hgr_admin2_partofID": 206.0, "hgr_admin_hierarchy": "\u043c\u043e\u0441\u043a\u043e\u0432\u0441\u043a|\u0431\u043e\u0433\u043e\u0440\u043e\u0434\u0441\u043a", "hgr_alt_name_old_orth": null, "hgr_description": "\u0411\u041e\u0413\u041e\u0420\u041e\u0414\u0421\u041a\u042a, \u0433\u043e\u0440\u043e\u0434\u044a \u041c\u043e\u0441\u043a\u043e\u0432\u0441\u043a\u043e\u0439 \u0413\u0443\u0431\u0435\u0440\u043d\u0456\u0438. \u0412\u044a \u043d\u0435\u043c\u044a \u0431\u044b\u0432\u0430\u0435\u0442\u044a \u0434\u0432\u0463 \u0432\u044a \u0433\u043e\u0434\u0443 \u044f\u0440\u043c\u0430\u0440\u043a\u0438: \u043f\u0435\u0440\u0432\u0430\u044f \u041c\u0430\u0456\u044f 9, \u0432\u0442\u043e\u0440\u0430\u044f \u0414\u0435\u043a\u0430\u0431\u0440\u044f 6, \u043d\u0430 \u043a\u043e\u0442\u043e\u0440\u044b\u044f \u0442\u043e\u0439 \u043e\u043a\u0440\u0443\u0433\u0438 \u043a\u0440\u0435\u0441\u0442\u044c\u044f\u043d\u0435 \u043f\u0440\u0438\u0432\u043e\u0437\u044f\u0442\u044a \u0440\u0430\u0437\u043d\u044b\u0435 \u0441\u044a\u0463\u0441\u0442\u043d\u044b\u0435 \u043f\u0440\u0438\u043f\u0430\u0441\u044b, \u0430 \u043a\u0443\u043f\u0446\u044b \u043c\u0463\u043b\u043e\u0447\u043d\u044b\u0435 \u0442\u043e\u0432\u0430\u0440\u044b.", "hgr_html_text": "\u0411\u041e\u0413\u041e\u0420\u041e\u0414\u0421\u041a\u042a, </span><span class=\"font0\" style=\"font-style:italic;\">\u0433\u043e\u0440\u043e\u0434\u044a</span><span class=\"font0\"> \u041c\u043e\u0441\u043a\u043e\u0432\u0441\u043a\u043e\u0439 \u0413\u0443\u0431\u0435\u0440\u043d\u0456\u0438. \u0412\u044a \u043d\u0435\u043c\u044a \u0431\u044b\u0432\u0430\u0435\u0442\u044a \u0434\u0432\u0463 \u0432\u044a \u0433\u043e\u0434\u0443 \u044f\u0440\u043c\u0430\u0440\u043a\u0438: \u043f\u0435\u0440\u0432\u0430\u044f \u041c\u0430\u0456\u044f 9, \u0432\u0442\u043e\u0440\u0430\u044f \u0414\u0435\u043a\u0430\u0431\u0440\u044f 6, \u043d\u0430 \u043a\u043e\u0442\u043e\u0440\u044b\u044f \u0442\u043e\u0439 \u043e\u043a\u0440\u0443\u0433\u0438 \u043a\u0440\u0435\u0441\u0442\u044c\u044f\u043d\u0435 \u043f\u0440\u0438\u0432\u043e\u0437\u044f\u0442\u044a \u0440\u0430\u0437\u043d\u044b\u0435 \u0441\u044a\u0463\u0441\u0442\u043d\u044b\u0435 \u043f\u0440\u0438\u043f\u0430\u0441\u044b, \u0430 \u043a\u0443\u043f\u0446\u044b \u043c\u0463\u043b\u043e\u0447\u043d\u044b\u0435 \u0442\u043e\u0432\u0430\u0440\u044b.</span>", "hgr_page": 19, "hgr_partof_id": "206.0", "hgr_prov_modern_sp": "\u041c\u043e\u0441\u043a\u043e\u0432\u0441\u043a\u043e\u0439 \u0413\u0443\u0431\u0435\u0440\u043d\u0438\u0438", "hgr_prov_stem": "\u043c\u043e\u0441\u043a\u043e\u0432\u0441\u043a", "hgr_ru_new_orth": "\u0411\u043e\u0433\u043e\u0440\u043e\u0434\u0441\u043a", "hgr_ru_old_featuretype": "\u0433\u043e\u0440\u043e\u0434\u044a", "hgr_ru_old_orth": "\u0411\u043e\u0433\u043e\u0440\u043e\u0434\u0441\u043a\u044a", "hgr_ru_prov": "\u041c\u043e\u0441\u043a\u043e\u0432\u0441\u043a\u043e\u0439 \u0413\u0443\u0431\u0435\u0440\u043d\u0456\u0438", "hgr_ru_uezd": null, "hgr_uezd_modern_sp": null, "hgr_uezd_stem": "\u0431\u043e\u0433\u043e\u0440\u043e\u0434\u0441\u043a", "lat": "55.85", "lng": "38.45", "name": "Bogorodsk", "population": 0, "toponymName": "Bogorodsk"}, "type": "Feature"}], "type": "FeatureCollection"}