{"features": [{"geometry": {"coordinates": [46.5848, 60.4763], "type": "Point"}, "properties": {"UPDATE_SCRIPT": "python add_town_by_geoname_id.py 676_\u0422\u0430\u0440\u043d\u044f\u043d\u0441\u043a\u043e\u0439_f0.5.geojson 7513044", "adminCode1": "85", "adminName1": "Vologda", "countryCode": "RU", "countryId": "2017370", "countryName": "Russia", "fcl": "P", "fclName": "city, village,...", "fcode": "PPL", "fcodeName": "populated place", "geonameId": 7513044, "hgr_SOURCE": "http://babel.hathitrust.org/cgi/pt?id=uc1.b4583201;view=1up;seq=112", "hgr_admin1_partofID": "\u043d\u043e\u0442_\u0438\u043d_\u0442\u0435x\u0442", "hgr_admin2_partofID": null, "hgr_admin_hierarchy": "not_in_text|\u0432\u0430\u0433", "hgr_alt_name_old_orth": null, "hgr_description": "\u0422\u0410\u0420\u041d\u042f\u041d\u0421\u041a\u041e\u0419, \u0433\u043e\u0440\u043e\u0434\u043e\u043a\u044a \u041a\u043e\u043a\u0448\u0430\u0439\u0441\u043a\u043e\u0439 \u0447\u0435\u0442\u0432\u0435\u0440\u0442\u0438 \u0432\u044a \u0443\u0463\u0437\u0434\u0463 \u0433\u043e\u0440\u043e\u0434\u0430 \u0412\u0430\u0433\u0438. \u0411\u044b\u0432\u0430\u0435\u0442\u044a \u0437\u0434\u0463\u0441\u044c \u0433\u043e\u0434\u043e\u0432\u0430\u044f \u044f\u0440\u043c\u0430\u0440\u043a\u0430, \u043d\u0430\u0447\u0438\u043d\u0430\u044e\u0449\u0430\u044f\u0441\u044f \u0441\u044a 1 \u0413\u0435\u043d\u0432\u0430\u0440\u044f \u0438 \u043f\u0440\u043e\u0434\u043e\u043b\u0436\u0430\u044e\u0449\u0430\u044f\u0441\u044f \u0434\u043e 7 \u0434\u043d\u044f \u0442\u043e\u0433\u043e \u0436\u0435 \u043c\u0463\u0441\u044f\u0446\u0430. \u041a\u0443\u043f\u0446\u044b \u043f\u0440\u0456\u0463\u0437\u0436\u0430\u044e\u0442\u044a \u043d\u0430 \u043e\u043d\u044b\u044f \u0438\u0437\u044a \u0431\u043b\u0438\u0436\u043d\u0438\u0445\u044a \u0433\u043e\u0440\u043e\u0434\u043e\u0432\u044a \u0441\u044a \u0440\u0430\u0437\u043d\u044b\u043c\u0438 \u043c\u0463\u043b\u043e\u0447\u043d\u044b\u043c\u0438 \u043c\u043e\u0441\u043a\u043e\u0442\u0438\u043b\u044c\u043d\u044b\u043c\u0438 \u0438 \u043f\u0440\u043e\u0447\u0438\u043c\u0438 \u0442\u043e\u0432\u0430\u0440\u0430\u043c\u0438.", "hgr_html_text": "\u0422\u0410\u0420\u041d\u042f\u041d\u0421\u041a\u041e\u0419, </span><span class=\"font0\" style=\"font-style:italic;\">\u0433\u043e\u0440\u043e\u0434\u043e\u043a\u044a </span><span class=\"font0\">\u041a\u043e\u043a\u0448\u0430\u0439\u0441\u043a\u043e\u0439 \u0447\u0435\u0442\u0432\u0435\u0440\u0442\u0438 \u0432\u044a \u0443\u0463\u0437\u0434\u0463 \u0433\u043e\u0440\u043e\u0434\u0430 \u0412\u0430\u0433\u0438. \u0411\u044b\u0432\u0430\u0435\u0442\u044a \u0437\u0434\u0463\u0441\u044c \u0433\u043e\u0434\u043e\u0432\u0430\u044f \u044f\u0440\u043c\u0430\u0440\u043a\u0430, \u043d\u0430\u0447\u0438\u043d\u0430\u044e\u0449\u0430\u044f\u0441\u044f \u0441\u044a 1 \u0413\u0435\u043d\u0432\u0430\u0440\u044f \u0438 \u043f\u0440\u043e\u0434\u043e\u043b\u0436\u0430\u044e\u0449\u0430\u044f\u0441\u044f \u0434\u043e 7 \u0434\u043d\u044f \u0442\u043e\u0433\u043e \u0436\u0435 \u043c\u0463\u0441\u044f\u0446\u0430. \u041a\u0443\u043f\u0446\u044b \u043f\u0440\u0456\u0463\u0437\u0436\u0430\u044e\u0442\u044a \u043d\u0430 \u043e\u043d\u044b\u044f \u0438\u0437\u044a \u0431\u043b\u0438\u0436\u043d\u0438\u0445\u044a \u0433\u043e\u0440\u043e\u0434\u043e\u0432\u044a \u0441\u044a \u0440\u0430\u0437\u043d\u044b\u043c\u0438 \u043c\u0463\u043b\u043e\u0447\u043d\u044b\u043c\u0438 \u043c\u043e\u0441\u043a\u043e\u0442\u0438\u043b\u044c\u043d\u044b\u043c\u0438 \u0438 \u043f\u0440\u043e\u0447\u0438\u043c\u0438 \u0442\u043e\u0432\u0430\u0440\u0430\u043c\u0438.</span>", "hgr_page": 113, "hgr_partof_id": "\u043d\u043e\u0442_\u0438\u043d_\u0442\u0435x\u0442", "hgr_prov_modern_sp": null, "hgr_prov_stem": "not_in_text", "hgr_ru_new_orth": "\u0422\u0430\u0440\u043d\u044f\u043d\u0441\u043a\u043e\u0439", "hgr_ru_old_featuretype": "\u0433\u043e\u0440\u043e\u0434\u043e\u043a\u044a", "hgr_ru_old_orth": "\u0422\u0430\u0440\u043d\u044f\u043d\u0441\u043a\u043e\u0439", "hgr_ru_prov": null, "hgr_ru_uezd": "\u0412\u0430\u0433\u0438", "hgr_txt_id": 676, "hgr_uezd_modern_sp": "\u0412\u0430\u0433\u0438", "hgr_uezd_stem": "\u0432\u0430\u0433", "lat": "60.4763", "lng": "46.5848", "name": "Tarasovskoye", "population": 0, "toponymName": "Tarasovskoye"}, "type": "Feature"}], "type": "FeatureCollection"}