{"features": [{"geometry": {"coordinates": [40.54242, 57.78332], "type": "Point"}, "properties": {"UPDATE_SCRIPT": "python add_town_by_geoname_id.py 724_\u0423\u0442\u0432\u044b\u043c\u0441\u043a\u0430\u044f_f0.3.geojson 479694", "adminCode1": "88", "adminName1": "Jaroslavl", "countryCode": "RU", "countryId": "2017370", "countryName": "Russia", "fcl": "P", "fclName": "city, village,...", "fcode": "PPL", "fcodeName": "populated place", "geonameId": 479694, "hgr_SOURCE": "http://babel.hathitrust.org/cgi/pt?id=uc1.b4583201;view=1up;seq=120", "hgr_admin1_partofID": "4", "hgr_admin2_partofID": 158.0, "hgr_admin_hierarchy": "\u0432\u043e\u043b\u043e\u0433\u043e\u0434\u0441\u043a|\u044f\u0440\u0435\u043d\u0441\u043a", "hgr_alt_name_old_orth": null, "hgr_description": "\u0423\u0422\u0412\u042b\u041c\u0421\u041a\u0410\u042f, \u0432\u043e\u043b\u043e\u0441\u0442\u044c \u0412\u043e\u043b\u043e\u0433\u043e\u0434\u0441\u043a\u0430\u0433\u043e \u041d\u0430\u043c\u0463\u0441\u0442\u043d\u0438\u0447\u0435\u0441\u0442\u0432\u0430 \u0432\u044a \u0443\u0463\u0437\u0434\u0463 \u0433\u043e\u0440\u043e\u0434\u0430 \u042f\u0440\u0435\u043d\u0441\u043a\u0430. \u0417\u0434\u0463\u0441\u044c \u0431\u044b\u0432\u0430\u0435\u0442\u044a \u044f\u0440\u043c\u0430\u0440\u043a\u0430 \u0413\u0435\u043d\u0432\u0430\u0440\u044f \u0441\u044a 24 \u0424\u0435\u0432\u0440\u0430\u043b\u044f \u043f\u043e 5 \u0447\u0438\u0441\u043b\u043e, \u043d\u0430 \u043a\u043e\u0442\u043e\u0440\u0443\u044e \u043f\u0440\u0456\u0463\u0437\u0436\u0430\u044e\u0442\u044a \u043a\u0443\u043f\u0446\u044b \u0438\u0437\u044a \u0440\u0430\u0437\u043d\u044b\u0445\u044a \u0420\u043e\u0441\u0441\u0456\u0439\u0441\u043a\u0438\u0445\u044a \u0433\u043e\u0440\u043e\u0434\u043e\u0432\u044a \u0441\u044a \u043b\u0430\u0432\u043e\u0447\u043d\u044b\u043c\u0438 \u0442\u043e\u0432\u0430\u0440\u0430\u043c\u0438.", "hgr_html_text": "\u0423\u0422\u0412\u042b\u041c\u0421\u041a\u0410\u042f, </span><span class=\"font0\" style=\"font-style:italic;\">\u0432\u043e\u043b\u043e\u0441\u0442\u044c</span><span class=\"font0\"> \u0412\u043e\u043b\u043e\u0433\u043e\u0434\u0441\u043a\u0430\u0433\u043e \u041d\u0430\u043c\u0463\u0441\u0442\u043d\u0438\u0447\u0435\u0441\u0442\u0432\u0430 \u0432\u044a \u0443\u0463\u0437\u0434\u0463 \u0433\u043e\u0440\u043e\u0434\u0430 \u042f\u0440\u0435\u043d\u0441\u043a\u0430. \u0417\u0434\u0463\u0441\u044c \u0431\u044b\u0432\u0430\u0435\u0442\u044a \u044f\u0440\u043c\u0430\u0440\u043a\u0430 \u0413\u0435\u043d\u0432\u0430\u0440\u044f \u0441\u044a 24 \u0424\u0435\u0432\u0440\u0430\u043b\u044f \u043f\u043e 5 \u0447\u0438\u0441\u043b\u043e, \u043d\u0430 \u043a\u043e\u0442\u043e\u0440\u0443\u044e \u043f\u0440\u0456\u0463\u0437\u0436\u0430\u044e\u0442\u044a \u043a\u0443\u043f\u0446\u044b \u0438\u0437\u044a \u0440\u0430\u0437\u043d\u044b\u0445\u044a \u0420\u043e\u0441\u0441\u0456\u0439\u0441\u043a\u0438\u0445\u044a \u0433\u043e\u0440\u043e\u0434\u043e\u0432\u044a \u0441\u044a \u043b\u0430\u0432\u043e\u0447\u043d\u044b\u043c\u0438 \u0442\u043e\u0432\u0430\u0440\u0430\u043c\u0438.</span>", "hgr_page": 121, "hgr_partof_id": "158.0", "hgr_prov_modern_sp": "\u0412\u043e\u043b\u043e\u0433\u043e\u0434\u0441\u043a\u043e\u0433\u043e \u041d\u0430\u043c\u0435\u0441\u0442\u043d\u0438\u0447\u0435\u0441\u0442\u0432\u0430", "hgr_prov_stem": "\u0432\u043e\u043b\u043e\u0433\u043e\u0434\u0441\u043a", "hgr_ru_new_orth": "\u0423\u0442\u0432\u044b\u043c\u0441\u043a\u0430\u044f", "hgr_ru_old_featuretype": "\u0432\u043e\u043b\u043e\u0441\u0442\u044c", "hgr_ru_old_orth": "\u0423\u0442\u0432\u044b\u043c\u0441\u043a\u0430\u044f", "hgr_ru_prov": "\u0412\u043e\u043b\u043e\u0433\u043e\u0434\u0441\u043a\u0430\u0433\u043e \u041d\u0430\u043c\u0463\u0441\u0442\u043d\u0438\u0447\u0435\u0441\u0442\u0432\u0430", "hgr_ru_uezd": "\u042f\u0440\u0435\u043d\u0441\u043a\u0430", "hgr_txt_id": 724, "hgr_uezd_modern_sp": "\u042f\u0440\u0435\u043d\u0441\u043a\u0430", "hgr_uezd_stem": "\u044f\u0440\u0435\u043d\u0441\u043a", "lat": "57.78332", "lng": "40.54242", "name": "Uchen'zha", "population": 0, "toponymName": "Uchenzha"}, "type": "Feature"}], "type": "FeatureCollection"}