{"features": [{"geometry": {"coordinates": [32.65549, 49.08376], "type": "Point"}, "properties": {"UPDATE_SCRIPT": "python add_town_by_geoname_id.py 748_\u0426\u0435\u0432\u043b\u044f_f0.3.geojson 710473", "adminCode1": "01", "adminName1": "Cherkasy", "countryCode": "UA", "countryId": "690791", "countryName": "Ukraine", "fcl": "P", "fclName": "city, village,...", "fcode": "PPL", "fcodeName": "populated place", "geonameId": 710473, "hgr_SOURCE": "http://babel.hathitrust.org/cgi/pt?id=uc1.b4583201;view=1up;seq=123", "hgr_admin1_partofID": "\u043d\u043e\u0442_\u0438\u043d_\u0442\u0435x\u0442", "hgr_admin2_partofID": null, "hgr_admin_hierarchy": "not_in_text|\u043e\u043f\u043e\u0447\u0435\u043a", "hgr_alt_name_old_orth": null, "hgr_description": "\u0426\u0415\u0412\u041b\u042f, \u0441\u0435\u043b\u043e \u0413. \u0421\u0443\u043c\u0430\u0440\u043e\u043a\u043e\u0432\u0430 \u0432\u044a \u0443\u0463\u0437\u0434\u0463 \u0433\u043e\u0440\u043e\u0434\u0430 \u041e\u043f\u043e\u0447\u0435\u043a\u044a. \u0417\u0434\u0463\u0441\u044c \u0431\u044b\u0432\u0430\u0435\u0442\u044a \u043e\u0434\u043d\u0430 \u0432\u044a \u0433\u043e\u0434\u0443 \u044f\u0440\u043c\u0430\u0440\u043a\u0430.", "hgr_html_text": "\u0426\u0415\u0412\u041b\u042f, </span><span class=\"font0\" style=\"font-style:italic;\">\u0441\u0435\u043b\u043e</span><span class=\"font0\"> \u0413. \u0421\u0443\u043c\u0430\u0440\u043e\u043a\u043e\u0432\u0430 \u0432\u044a \u0443\u0463\u0437\u0434\u0463 \u0433\u043e\u0440\u043e\u0434\u0430 \u041e\u043f\u043e\u0447\u0435\u043a\u044a. \u0417\u0434\u0463\u0441\u044c \u0431\u044b\u0432\u0430\u0435\u0442\u044a \u043e\u0434\u043d\u0430 \u0432\u044a \u0433\u043e\u0434\u0443 \u044f\u0440\u043c\u0430\u0440\u043a\u0430.</span>", "hgr_page": 124, "hgr_partof_id": "\u043d\u043e\u0442_\u0438\u043d_\u0442\u0435x\u0442", "hgr_prov_modern_sp": null, "hgr_prov_stem": "not_in_text", "hgr_ru_new_orth": "\u0426\u0435\u0432\u043b\u044f", "hgr_ru_old_featuretype": "\u0441\u0435\u043b\u043e", "hgr_ru_old_orth": "\u0426\u0435\u0432\u043b\u044f", "hgr_ru_prov": null, "hgr_ru_uezd": "\u041e\u043f\u043e\u0447\u0435\u043a\u044a", "hgr_txt_id": 748, "hgr_uezd_modern_sp": "\u041e\u043f\u043e\u0447\u0435\u043a", "hgr_uezd_stem": "\u043e\u043f\u043e\u0447\u0435\u043a", "lat": "49.08376", "lng": "32.65549", "name": "Chyhyryn", "population": 11515, "toponymName": "Chyhyryn"}, "type": "Feature"}], "type": "FeatureCollection"}