{"features": [{"geometry": {"coordinates": [41.30472, 48.88417], "type": "Point"}, "properties": {"UPDATE_SCRIPT": "python add_town_by_geoname_id.py 767_\u0427\u0435\u0440\u043d\u0435\u0435\u0432 \u041d\u0438\u043a\u043e\u043b\u0430\u0435\u0432\u0441\u043a\u043e\u0439_f0.5.geojson 568842", "adminCode1": "61", "adminName1": "Rostov", "countryCode": "RU", "countryId": "2017370", "countryName": "Russia", "fcl": "P", "fclName": "city, village,...", "fcode": "PPL", "fcodeName": "populated place", "geonameId": 568842, "hgr_SOURCE": "http://babel.hathitrust.org/cgi/pt?id=uc1.b4583201;view=1up;seq=126", "hgr_admin1_partofID": "32", "hgr_admin2_partofID": 156.0, "hgr_admin_hierarchy": "\u0442\u0430\u043c\u0431\u043e\u0432\u0441\u043a|\u0448\u0430\u0442\u0441\u043a", "hgr_alt_name_old_orth": null, "hgr_description": "\u0427\u0415\u0420\u041d\u0462\u0415\u0412\u042a \u041d\u0418\u041a\u041e\u041b\u0410\u0415\u0412\u0421\u041a\u041e\u0419, \u043c\u043e\u043d\u0430\u0441\u0442\u044b\u0440\u044c \u0422\u0430\u043c\u0431\u043e\u0432\u0441\u043a\u0430\u0433\u043e \u041d\u0430\u043c\u0463\u0441\u0442\u043d\u0438\u0447\u0435\u0441\u0442\u0432\u0430 \u0432\u044a \u0443\u0463\u0437\u0434\u0463 \u0433\u043e\u0440\u043e\u0434\u0430 \u0428\u0430\u0442\u0441\u043a\u0430. \u0417\u0434\u0463\u0441\u044c \u0431\u044b\u0432\u0430\u0435\u0442\u044a \u0432\u044a \u0433\u043e\u0434\u0443 \u044f\u0440\u043c\u0430\u0440\u043a\u0430 \u041c\u0430\u0456\u044f 9; \u0442\u043e\u0440\u0433\u0443\u044e\u0442\u044a \u0440\u0430\u0437\u043d\u044b\u043c\u0438 \u0432\u043d\u0443\u0442\u0440\u0435\u043d\u043d\u0438\u043c\u0438 \u0442\u043e\u0432\u0430\u0440\u0430\u043c\u0438, \u0445\u043e\u043b\u0441\u0442\u043e\u043c\u044a, \u043f\u0435\u043d\u044c\u043a\u043e\u044e , \u0448\u0435\u0440\u0441\u0442\u044c\u044e \u0438 \u043f\u0440\u043e\u0447\u0438\u043c\u0438.", "hgr_html_text": "\u0427\u0415\u0420\u041d\u0462\u0415\u0412\u042a \u041d\u0418\u041a\u041e\u041b\u0410\u0415\u0412\u0421\u041a\u041e\u0419, </span><span class=\"font0\" style=\"font-style:italic;\">\u043c\u043e\u043d\u0430\u0441\u0442\u044b\u0440\u044c</span><span class=\"font0\"> \u0422\u0430\u043c\u0431\u043e\u0432\u0441\u043a\u0430\u0433\u043e \u041d\u0430\u043c\u0463\u0441\u0442\u043d\u0438\u0447\u0435\u0441\u0442\u0432\u0430 \u0432\u044a \u0443\u0463\u0437\u0434\u0463 \u0433\u043e\u0440\u043e\u0434\u0430 \u0428\u0430\u0442\u0441\u043a\u0430. \u0417\u0434\u0463\u0441\u044c \u0431\u044b\u0432\u0430\u0435\u0442\u044a \u0432\u044a \u0433\u043e\u0434\u0443 \u044f\u0440\u043c\u0430\u0440\u043a\u0430 \u041c\u0430\u0456\u044f 9; \u0442\u043e\u0440\u0433\u0443\u044e\u0442\u044a \u0440\u0430\u0437\u043d\u044b\u043c\u0438 \u0432\u043d\u0443\u0442\u0440\u0435\u043d\u043d\u0438\u043c\u0438 \u0442\u043e\u0432\u0430\u0440\u0430\u043c\u0438, \u0445\u043e\u043b\u0441\u0442\u043e\u043c\u044a, \u043f\u0435\u043d\u044c\u043a\u043e\u044e , \u0448\u0435\u0440\u0441\u0442\u044c\u044e \u0438 \u043f\u0440\u043e\u0447\u0438\u043c\u0438.</span>", "hgr_page": 127, "hgr_partof_id": "156.0", "hgr_prov_modern_sp": "\u0422\u0430\u043c\u0431\u043e\u0432\u0441\u043a\u043e\u0433\u043e \u041d\u0430\u043c\u0435\u0441\u0442\u043d\u0438\u0447\u0435\u0441\u0442\u0432\u0430", "hgr_prov_stem": "\u0442\u0430\u043c\u0431\u043e\u0432\u0441\u043a", "hgr_ru_new_orth": "\u0427\u0435\u0440\u043d\u0435\u0435\u0432 \u041d\u0438\u043a\u043e\u043b\u0430\u0435\u0432\u0441\u043a\u043e\u0439", "hgr_ru_old_featuretype": "\u043c\u043e\u043d\u0430\u0441\u0442\u044b\u0440\u044c", "hgr_ru_old_orth": "\u0427\u0435\u0440\u043d\u0463\u0435\u0432\u044a \u041d\u0438\u043a\u043e\u043b\u0430\u0435\u0432\u0441\u043a\u043e\u0439", "hgr_ru_prov": "\u0422\u0430\u043c\u0431\u043e\u0432\u0441\u043a\u0430\u0433\u043e \u041d\u0430\u043c\u0463\u0441\u0442\u043d\u0438\u0447\u0435\u0441\u0442\u0432\u0430", "hgr_ru_uezd": "\u0428\u0430\u0442\u0441\u043a\u0430", "hgr_txt_id": 767, "hgr_uezd_modern_sp": "\u0428\u0430\u0442\u0441\u043a\u0430", "hgr_uezd_stem": "\u0448\u0430\u0442\u0441\u043a", "lat": "48.88417", "lng": "41.30472", "name": "Chernigov-Tokmachevskiy", "population": 0, "toponymName": "Chernigov-Tokmachevskiy"}, "type": "Feature"}], "type": "FeatureCollection"}