{"features": [{"geometry": {"coordinates": [37.1225, 58.5081], "type": "Point"}, "properties": {"UPDATE_SCRIPT": "python add_town_by_geoname_id.py 785_\u0428\u0443\u043d\u0433\u0441\u043a\u043e\u0439_f0.6.geojson 7591225", "adminCode1": "77", "adminName1": "Tverskaya", "countryCode": "RU", "countryId": "2017370", "countryName": "Russia", "fcl": "P", "fclName": "city, village,...", "fcode": "PPL", "fcodeName": "populated place", "geonameId": 7591225, "hgr_SOURCE": "http://babel.hathitrust.org/cgi/pt?id=uc1.b4583201;view=1up;seq=129", "hgr_admin1_partofID": "20", "hgr_admin2_partofID": 220.0, "hgr_admin_hierarchy": "\u043e\u043b\u043e\u043d\u0435\u0446\u043a|\u043f\u043e\u0432\u0435\u043d\u0435\u0446\u043a", "hgr_alt_name_old_orth": null, "hgr_description": "\u0428\u0423\u041d\u0413\u0421\u041a\u041e\u0419, \u043f\u043e\u0433\u043e\u0441\u0442\u044a \u041e\u043b\u043e\u043d\u0435\u0446\u043a\u0430\u0433\u043e \u041d\u0430\u043c\u0463\u0441\u0442\u043d\u0438\u0447\u0435\u0441\u0442\u0432\u0430 \u0432\u044a \u041f\u043e\u0432\u0463\u043d\u0435\u0446\u043a\u043e\u043c\u044a \u0443\u0463\u0437\u0434\u0463. \u0412\u044a \u043e\u043d\u043e\u043c\u044a \u0431\u044b\u0432\u0430\u044e\u0442\u044a \u0432\u044a \u0433\u043e\u0434\u0443 \u0434\u0432\u0463 \u044f\u0440\u043c\u0430\u0440\u043a\u0438: \u043f\u0435\u0440\u0432\u0430\u044f \u0413\u0435\u043d\u0432\u0430\u0440\u044f 6, \u0432\u0442\u043e\u0440\u0430\u044f \u041c\u0430\u0440\u0442\u0430 25, \u043d\u0430 \u043a\u043e\u0438 \u043f\u0440\u0456\u0463\u0437\u0436\u0430\u044e\u0442\u044a \u043a\u0443\u043f\u0446\u044b \u0441\u044a \u0448\u0435\u043b\u043a\u043e\u0432\u044b\u043c\u0438, \u0431\u0443\u043c\u0430\u0436\u043d\u044b\u043c\u0438, \u0433\u0430\u0440\u0443\u0441\u043d\u044b\u043c\u0438 \u0438 \u043f\u0440\u043e\u0447\u0438\u043c\u0438 \u0442\u043e\u0432\u0430\u0440\u0430\u043c\u0438.", "hgr_html_text": "\u0428\u0423\u041d\u0413\u0421\u041a\u041e\u0419, </span><span class=\"font0\" style=\"font-style:italic;\">\u043f\u043e\u0433\u043e\u0441\u0442\u044a</span><span class=\"font0\"> \u041e\u043b\u043e\u043d\u0435\u0446\u043a\u0430\u0433\u043e \u041d\u0430\u043c\u0463\u0441\u0442\u043d\u0438\u0447\u0435\u0441\u0442\u0432\u0430 \u0432\u044a \u041f\u043e\u0432\u0463\u043d\u0435\u0446\u043a\u043e\u043c\u044a \u0443\u0463\u0437\u0434\u0463. \u0412\u044a \u043e\u043d\u043e\u043c\u044a \u0431\u044b\u0432\u0430\u044e\u0442\u044a \u0432\u044a \u0433\u043e\u0434\u0443 \u0434\u0432\u0463 \u044f\u0440\u043c\u0430\u0440\u043a\u0438: \u043f\u0435\u0440\u0432\u0430\u044f \u0413\u0435\u043d\u0432\u0430\u0440\u044f 6, \u0432\u0442\u043e\u0440\u0430\u044f \u041c\u0430\u0440\u0442\u0430 25, \u043d\u0430 \u043a\u043e\u0438 \u043f\u0440\u0456\u0463\u0437\u0436\u0430\u044e\u0442\u044a \u043a\u0443\u043f\u0446\u044b \u0441\u044a \u0448\u0435\u043b\u043a\u043e\u0432\u044b\u043c\u0438, \u0431\u0443\u043c\u0430\u0436\u043d\u044b\u043c\u0438, \u0433\u0430\u0440\u0443\u0441\u043d\u044b\u043c\u0438 \u0438 \u043f\u0440\u043e\u0447\u0438\u043c\u0438 \u0442\u043e\u0432\u0430\u0440\u0430\u043c\u0438.</span>", "hgr_page": 130, "hgr_partof_id": "220.0", "hgr_prov_modern_sp": "\u041e\u043b\u043e\u043d\u0435\u0446\u043a\u043e\u0433\u043e \u041d\u0430\u043c\u0435\u0441\u0442\u043d\u0438\u0447\u0435\u0441\u0442\u0432\u0430", "hgr_prov_stem": "\u043e\u043b\u043e\u043d\u0435\u0446\u043a", "hgr_ru_new_orth": "\u0428\u0443\u043d\u0433\u0441\u043a\u043e\u0439", "hgr_ru_old_featuretype": "\u043f\u043e\u0433\u043e\u0441\u0442\u044a", "hgr_ru_old_orth": "\u0428\u0443\u043d\u0433\u0441\u043a\u043e\u0439", "hgr_ru_prov": "\u041e\u043b\u043e\u043d\u0435\u0446\u043a\u0430\u0433\u043e \u041d\u0430\u043c\u0463\u0441\u0442\u043d\u0438\u0447\u0435\u0441\u0442\u0432\u0430", "hgr_ru_uezd": "\u041f\u043e\u0432\u0463\u043d\u0435\u0446\u043a\u043e\u043c\u044a \u0443\u0463\u0437\u0434\u0463", "hgr_txt_id": 785, "hgr_uezd_modern_sp": "\u041f\u043e\u0432\u0435\u043d\u0435\u0446\u043a\u043e\u043c \u0443\u0435\u0437\u0434\u0435", "hgr_uezd_stem": "\u043f\u043e\u0432\u0435\u043d\u0435\u0446\u043a", "lat": "58.5081", "lng": "37.1225", "name": "Shenskoye", "population": 0, "toponymName": "Shenskoye"}, "type": "Feature"}], "type": "FeatureCollection"}