{"features": [{"properties": {"hgr_name_modern_sp": "\u0410\u0442\u0435\u043c\u0430\u0440", "countryCode": "RU", "hgr_admin_hierarchy": "\u043f\u0435\u043d\u0437\u0435\u043d\u0441\u043a|\u0441\u0430\u0440\u0430\u043d\u0441\u043a", "fcl": "P", "toponymName": "Atemar", "countryName": "Russia", "adminCode1": "46", "fcodeName": "populated place", "population": 4052, "hgr_partof_id": 117.0, "hgr_page": 14, "hgr_html_text": "\u0410\u0422\u0415\u041c\u0410\u0420\u042a, </span><span class=\"font0\" style=\"font-style:italic;\">\u0441\u0435\u043b\u043e</span><span class=\"font0\"> \u041f\u0435\u043d\u0437\u0435\u043d\u0441\u043a\u0430\u0433\u043e \u041d\u0430\u043c\u0463\u0441\u0442\u043d\u0438\u0447\u0435\u0441\u0442\u0432\u0430 \u0432\u044a \u0421\u0430\u0440\u0430\u043d\u0441\u043a\u043e\u043c\u044a \u0443\u0463\u0437\u0434\u0463. \u0417\u0434\u0463\u0441\u044c \u0431\u044b\u0432\u0430\u0435\u0442\u044a \u044f\u0440\u043c\u0430\u0440\u043a\u0430 \u0432\u044a \u043f\u043e\u0441\u043b\u0463\u0434\u043d\u0438\u0445\u044a \u0447\u0438\u0441\u043b\u0430\u0445\u044a \u0406\u044e\u043b\u044f \u043c\u0463\u0441\u044f\u0446\u0430; \u043f\u0440\u0438\u0432\u043e\u0437\u044f\u0442\u044a \u043a\u0443\u043f\u0446\u044b \u0440\u0430\u0437\u043d\u044b\u0435 \u043c\u0463\u043b\u043e\u0447\u043d\u044b\u0435 \u0448\u0435\u043b\u043a\u043e\u0432\u044b\u0435 \u0442\u043e\u0432\u0430\u0440\u044b.</span>", "UPDATE_SCRIPT": "python add_town_by_geoname_id.py \u0410\u0442\u0435\u043c\u0430\u0440_26.geojson 580432", "hgr_text": "\u0410\u0422\u0415\u041c\u0410\u0420\u042a, \u0441\u0435\u043b\u043e \u041f\u0435\u043d\u0437\u0435\u043d\u0441\u043a\u0430\u0433\u043e \u041d\u0430\u043c\u0463\u0441\u0442\u043d\u0438\u0447\u0435\u0441\u0442\u0432\u0430 \u0432\u044a \u0421\u0430\u0440\u0430\u043d\u0441\u043a\u043e\u043c\u044a \u0443\u0463\u0437\u0434\u0463. \u0417\u0434\u0463\u0441\u044c \u0431\u044b\u0432\u0430\u0435\u0442\u044a \u044f\u0440\u043c\u0430\u0440\u043a\u0430 \u0432\u044a \u043f\u043e\u0441\u043b\u0463\u0434\u043d\u0438\u0445\u044a \u0447\u0438\u0441\u043b\u0430\u0445\u044a \u0406\u044e\u043b\u044f \u043c\u0463\u0441\u044f\u0446\u0430; \u043f\u0440\u0438\u0432\u043e\u0437\u044f\u0442\u044a \u043a\u0443\u043f\u0446\u044b \u0440\u0430\u0437\u043d\u044b\u0435 \u043c\u0463\u043b\u043e\u0447\u043d\u044b\u0435 \u0448\u0435\u043b\u043a\u043e\u0432\u044b\u0435 \u0442\u043e\u0432\u0430\u0440\u044b.", "hgr_prov_modern_sp": "\u041f\u0435\u043d\u0437\u0435\u043d\u0441\u043a\u043e\u0433\u043e \u041d\u0430\u043c\u0435\u0441\u0442\u043d\u0438\u0447\u0435\u0441\u0442\u0432\u0430", "hgr_name": "\u0410\u0442\u0435\u043c\u0430\u0440\u044a", "name": "Atemar", "hgr_ru_uezd": "\u0421\u0430\u0440\u0430\u043d\u0441\u043a\u043e\u043c\u044a \u0443\u0463\u0437\u0434\u0463", "hgr_source_url": "http://babel.hathitrust.org/cgi/pt?id=uc1.b4583201;view=1up;seq=13", "countryId": "2017370", "hgr_ru_prov": "\u041f\u0435\u043d\u0437\u0435\u043d\u0441\u043a\u0430\u0433\u043e \u041d\u0430\u043c\u0463\u0441\u0442\u043d\u0438\u0447\u0435\u0441\u0442\u0432\u0430", "hgr_uezd_stem": "\u0441\u0430\u0440\u0430\u043d\u0441\u043a", "hgr_admin1_partof": 22.0, "hgr_alt_name": null, "adminName1": "Mordoviya", "hgr_admin2_partof": 117.0, "fcode": "PPL", "fclName": "city, village,...", "hgr_prov_stem": "\u043f\u0435\u043d\u0437\u0435\u043d\u0441\u043a", "geonameId": 580432, "hgr_type": "\u0441\u0435\u043b\u043e", "hgr_uezd_modern_sp": "\u0421\u0430\u0440\u0430\u043d\u0441\u043a\u043e\u043c \u0443\u0435\u0437\u0434\u0435"}, "geometry": {"coordinates": [45.40909, 54.18097], "type": "Point"}, "type": "Feature"}], "type": "FeatureCollection"}