{"features": [{"properties": {"fcl": "P", "geonameId": 580432, "countryId": "2017370", "fcode": "PPL", "name": "Atemar", "countryName": "Russia", "population": 4052, "fclName": "city, village,...", "adminName1": "Mordoviya", "adminCode1": "46", "fcodeName": "populated place", "countryCode": "RU", "toponymName": "Atemar"}, "geometry": {"coordinates": [45.40909, 54.18097], "type": "Point"}, "type": "Feature"}], "type": "FeatureCollection"}