{"type": "FeatureCollection", "features": [{"properties": {"countryId": "2017370", "toponymName": "Atemar", "adminCode1": "46", "geonameId": 580432, "fcl": "P", "name": "Atemar", "countryName": "Russia", "fclName": "city, village,...", "fcode": "PPL", "adminName1": "Mordoviya", "countryCode": "RU", "population": 4052, "fcodeName": "populated place"}, "geometry": {"coordinates": [45.40909, 54.18097], "type": "Point"}, "type": "feature"}]}