{"type": "FeatureCollection", "features": [{"type": "Feature", "geometry": {"coordinates": [45.40909, 54.18097], "type": "Point"}, "properties": {"countryCode": "RU", "countryId": "2017370", "fcodeName": "populated place", "adminName1": "Mordoviya", "fclName": "city, village,...", "fcl": "P", "countryName": "Russia", "fcode": "PPL", "geonameId": 580432, "population": 4052, "adminCode1": "46", "name": "Atemar", "toponymName": "Atemar"}}]}