{"type": "FeatureCollection", "features": [{"properties": {"countryId": "2017370", "toponymName": "Novaya Balakhna", "adminCode1": "51", "geonameId": 579514, "fcl": "P", "name": "Balakhna", "countryName": "Russia", "fclName": "city, village,...", "fcode": "PPL", "adminName1": "Nizjnij Novgorod", "countryCode": "RU", "population": 63083, "fcodeName": "populated place"}, "geometry": {"coordinates": [43.60114, 56.48989], "type": "Point"}, "type": "feature"}, {"properties": {"countryId": "2017370", "toponymName": "Balakhna", "adminCode1": "21", "geonameId": 579512, "fcl": "P", "name": "Balakhna", "countryName": "Russia", "fclName": "city, village,...", "fcode": "PPL", "adminName1": "Ivanovo", "countryCode": "RU", "population": 0, "fcodeName": "populated place"}, "geometry": {"coordinates": [40.4, 57.25], "type": "Point"}, "type": "feature"}, {"properties": {"countryId": "2017370", "toponymName": "Balakhna", "adminCode1": "21", "geonameId": 579513, "fcl": "P", "name": "Balakhna", "countryName": "Russia", "fclName": "city, village,...", "fcode": "PPL", "adminName1": "Ivanovo", "countryCode": "RU", "population": 0, "fcodeName": "populated place"}, "geometry": {"coordinates": [40.86545, 57.22361], "type": "Point"}, "type": "feature"}]}