{"type": "FeatureCollection", "features": [{"type": "Feature", "geometry": {"coordinates": [43.60114, 56.48989], "type": "Point"}, "properties": {"countryCode": "RU", "countryId": "2017370", "fcodeName": "populated place", "adminName1": "Nizjnij Novgorod", "fclName": "city, village,...", "fcl": "P", "countryName": "Russia", "fcode": "PPL", "geonameId": 579514, "population": 63083, "adminCode1": "51", "name": "Balakhna", "toponymName": "Novaya Balakhna"}}, {"type": "Feature", "geometry": {"coordinates": [40.4, 57.25], "type": "Point"}, "properties": {"countryCode": "RU", "countryId": "2017370", "fcodeName": "populated place", "adminName1": "Ivanovo", "fclName": "city, village,...", "fcl": "P", "countryName": "Russia", "fcode": "PPL", "geonameId": 579512, "population": 0, "adminCode1": "21", "name": "Balakhna", "toponymName": "Balakhna"}}, {"type": "Feature", "geometry": {"coordinates": [40.86545, 57.22361], "type": "Point"}, "properties": {"countryCode": "RU", "countryId": "2017370", "fcodeName": "populated place", "adminName1": "Ivanovo", "fclName": "city, village,...", "fcl": "P", "countryName": "Russia", "fcode": "PPL", "geonameId": 579513, "population": 0, "adminCode1": "21", "name": "Balakhna", "toponymName": "Balakhna"}}]}