{"type": "FeatureCollection", "features": [{"properties": {"countryId": "2017370", "toponymName": "Belgorod", "adminCode1": "09", "geonameId": 578072, "fcl": "P", "name": "Belgorod", "countryName": "Russia", "fclName": "city, village,...", "fcode": "PPLA", "adminName1": "Belgorod", "countryCode": "RU", "population": 345289, "fcodeName": "seat of a first-order administrative division"}, "geometry": {"coordinates": [36.58015, 50.61074], "type": "Point"}, "type": "feature"}, {"properties": {"countryId": "2017370", "toponymName": "Belgorod", "adminCode1": "10", "geonameId": 819579, "fcl": "P", "name": "Belgorod", "countryName": "Russia", "fclName": "city, village,...", "fcode": "PPL", "adminName1": "Brjansk", "countryCode": "RU", "population": 0, "fcodeName": "populated place"}, "geometry": {"coordinates": [34.65388, 52.87333], "type": "Point"}, "type": "feature"}]}