{"type": "FeatureCollection", "features": [{"type": "Feature", "geometry": {"coordinates": [36.58015, 50.61074], "type": "Point"}, "properties": {"countryCode": "RU", "countryId": "2017370", "fcodeName": "seat of a first-order administrative division", "adminName1": "Belgorod", "fclName": "city, village,...", "fcl": "P", "countryName": "Russia", "fcode": "PPLA", "geonameId": 578072, "population": 345289, "adminCode1": "09", "name": "Belgorod", "toponymName": "Belgorod"}}, {"type": "Feature", "geometry": {"coordinates": [34.65388, 52.87333], "type": "Point"}, "properties": {"countryCode": "RU", "countryId": "2017370", "fcodeName": "populated place", "adminName1": "Brjansk", "fclName": "city, village,...", "fcl": "P", "countryName": "Russia", "fcode": "PPL", "geonameId": 819579, "population": 0, "adminCode1": "10", "name": "Belgorod", "toponymName": "Belgorod"}}]}