{"features": [{"type": "Feature", "geometry": {"coordinates": [37.8084, 60.0288], "type": "Point"}, "properties": {"hgr_name_modern_sp": "\u0411\u0435\u043b\u043e\u0437\u0435\u0440\u0441\u043a", "hgr_uezd_stem": "\u043d\u043e\u0442_\u0438\u043d_\u0442\u0435x\u0442", "hgr_admin_hierarchy": "\u043d\u043e\u0432\u043e\u0433\u043e\u0440\u043e\u0434\u0441\u043a", "hgr_admin1_partof": 18.0, "toponymName": "Beloz\u00ebrsk", "hgr_html_text": "\u0411\u0462\u041b\u041e\u0417\u0415\u0420\u0421\u041a\u042a, </span><span class=\"font0\" style=\"font-style:italic;\">\u0433\u043e\u0440\u043e\u0434\u044a</span><span class=\"font0\"> \u041d\u043e\u0432\u043e\u0433\u043e\u0440\u043e\u0434\u0441\u043a\u0430\u0433\u043e \u041d\u0430\u043c\u0463\u0441\u0442\u043d\u0438\u0447\u0435\u0441\u0442\u0432\u0430. \u0412\u044a \u043d\u0435\u043c\u044a \u0432\u044a \u0437\u0438\u043c\u043d\u0435\u0435 \u0432\u0440\u0435\u043c\u044f \u0431\u044b\u0432\u0430\u044e\u0442\u044a \u043a\u0430\u0436\u0434\u0443\u044e \u043d\u0435\u0434\u0463\u043b\u044e \u043f\u043e \u043f\u043e\u043d\u0435\u0434\u0463\u043b\u044c\u043d\u0438\u043a\u0430\u043c\u044a \u0441\u044a\u0463\u0437\u0434\u044b , \u043d\u0430 \u043a\u043e\u0442\u043e\u0440\u044b\u0445\u044a \u0442\u043e\u0440\u0433\u0443\u0435\u0442\u044a \u043a\u0440\u0435\u0441\u0442\u044c\u044f\u043d\u0441\u0442\u0432\u043e \u0440\u0430\u0437\u043d\u044b\u043c\u0438 \u0438\u0445\u044a \u0434\u043e\u043c\u043e\u0432\u043d\u044b\u043c\u0438 \u0438\u0437\u0434\u0463\u043b\u044c\u044f\u043c\u0438 , \u0442\u0430\u043a\u0436\u0435 \u043f\u0440\u0438\u0432\u043e\u0437\u044f\u0442\u044a \u043c\u044f \u0441\u0463\u043d\u043e \u0438 \u0445\u043b\u0463\u0431\u044a.</span>", "adminCode1": "85", "fcodeName": "populated place", "fcode": "PPL", "hgr_partof_id": 18.0, "hgr_page": 24, "countryName": "Russia", "hgr_text": "\u0411\u0462\u041b\u041e\u0417\u0415\u0420\u0421\u041a\u042a, \u0433\u043e\u0440\u043e\u0434\u044a \u041d\u043e\u0432\u043e\u0433\u043e\u0440\u043e\u0434\u0441\u043a\u0430\u0433\u043e \u041d\u0430\u043c\u0463\u0441\u0442\u043d\u0438\u0447\u0435\u0441\u0442\u0432\u0430. \u0412\u044a \u043d\u0435\u043c\u044a \u0432\u044a \u0437\u0438\u043c\u043d\u0435\u0435 \u0432\u0440\u0435\u043c\u044f \u0431\u044b\u0432\u0430\u044e\u0442\u044a \u043a\u0430\u0436\u0434\u0443\u044e \u043d\u0435\u0434\u0463\u043b\u044e \u043f\u043e \u043f\u043e\u043d\u0435\u0434\u0463\u043b\u044c\u043d\u0438\u043a\u0430\u043c\u044a \u0441\u044a\u0463\u0437\u0434\u044b , \u043d\u0430 \u043a\u043e\u0442\u043e\u0440\u044b\u0445\u044a \u0442\u043e\u0440\u0433\u0443\u0435\u0442\u044a \u043a\u0440\u0435\u0441\u0442\u044c\u044f\u043d\u0441\u0442\u0432\u043e \u0440\u0430\u0437\u043d\u044b\u043c\u0438 \u0438\u0445\u044a \u0434\u043e\u043c\u043e\u0432\u043d\u044b\u043c\u0438 \u0438\u0437\u0434\u0463\u043b\u044c\u044f\u043c\u0438 , \u0442\u0430\u043a\u0436\u0435 \u043f\u0440\u0438\u0432\u043e\u0437\u044f\u0442\u044a \u043c\u044f \u0441\u0463\u043d\u043e \u0438 \u0445\u043b\u0463\u0431\u044a.", "hgr_prov_modern_sp": "\u041d\u043e\u0432\u043e\u0433\u043e\u0440\u043e\u0434\u0441\u043a\u043e\u0433\u043e \u041d\u0430\u043c\u0435\u0441\u0442\u043d\u0438\u0447\u0435\u0441\u0442\u0432\u0430", "hgr_name": "\u0411\u0463\u043b\u043e\u0437\u0435\u0440\u0441\u043a\u044a", "name": "Belozersk", "hgr_ru_uezd": "not_in_text", "population": 11049, "countryId": "2017370", "hgr_ru_prov": "\u041d\u043e\u0432\u043e\u0433\u043e\u0440\u043e\u0434\u0441\u043a\u0430\u0433\u043e \u041d\u0430\u043c\u0463\u0441\u0442\u043d\u0438\u0447\u0435\u0441\u0442\u0432\u0430", "hgr_source_url": "http://babel.hathitrust.org/cgi/pt?id=uc1.b4583201;view=1up;seq=23", "fcl": "P", "hgr_alt_name": null, "adminName1": "Vologda", "hgr_admin2_partof": null, "hgr_prov_stem": "\u043d\u043e\u0432\u043e\u0433\u043e\u0440\u043e\u0434\u0441\u043a", "fclName": "city, village,...", "countryCode": "RU", "geonameId": 577711, "hgr_type": "\u0433\u043e\u0440\u043e\u0434\u044a", "hgr_uezd_modern_sp": "not_\u0438n_text"}}], "type": "FeatureCollection"}