{"features": [{"properties": {"fcl": "P", "geonameId": 578072, "countryId": "2017370", "fcode": "PPLA", "name": "Belgorod", "countryName": "Russia", "population": 345289, "fclName": "city, village,...", "adminName1": "Belgorod", "adminCode1": "09", "fcodeName": "seat of a first-order administrative division", "countryCode": "RU", "toponymName": "Belgorod"}, "geometry": {"coordinates": [36.58015, 50.61074], "type": "Point"}, "type": "Feature"}, {"properties": {"fcl": "P", "geonameId": 819579, "countryId": "2017370", "fcode": "PPL", "name": "Belgorod", "countryName": "Russia", "population": 0, "fclName": "city, village,...", "adminName1": "Brjansk", "adminCode1": "10", "fcodeName": "populated place", "countryCode": "RU", "toponymName": "Belgorod"}, "geometry": {"coordinates": [34.65388, 52.87333], "type": "Point"}, "type": "Feature"}], "type": "FeatureCollection"}