{"type": "FeatureCollection", "features": [{"type": "Feature", "geometry": {"coordinates": [37.27123, 54.29385], "type": "Point"}, "properties": {"countryCode": "RU", "countryId": "2017370", "fcodeName": "populated place", "adminName1": "Tula", "fclName": "city, village,...", "fcl": "P", "countryName": "Russia", "fcode": "PPL", "geonameId": 576759, "population": 0, "adminCode1": "76", "name": "Berniki", "toponymName": "Berniki"}}, {"type": "Feature", "geometry": {"coordinates": [37.13041, 54.29483], "type": "Point"}, "properties": {"countryCode": "RU", "countryId": "2017370", "fcodeName": "populated place", "adminName1": "Tula", "fclName": "city, village,...", "fcl": "P", "countryName": "Russia", "fcode": "PPL", "geonameId": 817567, "population": 0, "adminCode1": "76", "name": "Berniki", "toponymName": "Berniki"}}]}