{"type": "FeatureCollection", "features": [{"type": "Feature", "geometry": {"coordinates": [37.8084, 60.0288], "type": "Point"}, "properties": {"countryCode": "RU", "countryId": "2017370", "fcodeName": "populated place", "adminName1": "Vologda", "fclName": "city, village,...", "fcl": "P", "countryName": "Russia", "fcode": "PPL", "geonameId": 577711, "population": 11049, "adminCode1": "85", "name": "Belozersk", "toponymName": "Beloz\u00ebrsk"}}]}