{"type": "FeatureCollection", "features": [{"properties": {"countryId": "2017370", "toponymName": "Berniki", "adminCode1": "76", "geonameId": 576759, "fcl": "P", "name": "Berniki", "countryName": "Russia", "fclName": "city, village,...", "fcode": "PPL", "adminName1": "Tula", "countryCode": "RU", "population": 0, "fcodeName": "populated place"}, "geometry": {"coordinates": [37.27123, 54.29385], "type": "Point"}, "type": "feature"}, {"properties": {"countryId": "2017370", "toponymName": "Berniki", "adminCode1": "76", "geonameId": 817567, "fcl": "P", "name": "Berniki", "countryName": "Russia", "fclName": "city, village,...", "fcode": "PPL", "adminName1": "Tula", "countryCode": "RU", "population": 0, "fcodeName": "populated place"}, "geometry": {"coordinates": [37.13041, 54.29483], "type": "Point"}, "type": "feature"}]}