{"features": [{"properties": {"fcl": "P", "geonameId": 577711, "countryId": "2017370", "fcode": "PPL", "name": "Belozersk", "countryName": "Russia", "population": 11049, "fclName": "city, village,...", "adminName1": "Vologda", "adminCode1": "85", "fcodeName": "populated place", "countryCode": "RU", "toponymName": "Beloz\u00ebrsk"}, "geometry": {"coordinates": [37.8084, 60.0288], "type": "Point"}, "type": "Feature"}], "type": "FeatureCollection"}