{"type": "FeatureCollection", "features": [{"properties": {"countryId": "2017370", "toponymName": "Beloz\u00ebrsk", "adminCode1": "85", "geonameId": 577711, "fcl": "P", "name": "Belozersk", "countryName": "Russia", "fclName": "city, village,...", "fcode": "PPL", "adminName1": "Vologda", "countryCode": "RU", "population": 11049, "fcodeName": "populated place"}, "geometry": {"coordinates": [37.8084, 60.0288], "type": "Point"}, "type": "feature"}]}