{"features": [{"geometry": {"coordinates": [36.02332, 50.97632], "type": "Point"}, "properties": {"UPDATE_SCRIPT": "python add_town_by_geoname_id.py \u0411\u043e\u0433\u0430\u0442\u044b\u0439_51.geojson 575757", "adminCode1": "09", "adminName1": "Belgorod", "countryCode": "RU", "countryId": "2017370", "countryName": "Russia", "fcl": "P", "fclName": "city, village,...", "fcode": "PPL", "fcodeName": "populated place", "geonameId": 575757, "hgr_admin1_partof": 15.0, "hgr_admin2_partof": null, "hgr_admin_hierarchy": "\u043a\u0443\u0440\u0441\u043a", "hgr_alt_name": null, "hgr_html_text": "\u0411\u041e\u0413\u0410\u0422\u042b\u0419, </span><span class=\"font0\" style=\"font-style:italic;\">\u0433\u043e\u0440\u043e\u0434\u044a</span><span class=\"font0\"> \u041a\u0443\u0440\u0441\u043a\u0430\u0433\u043e \u041d\u0430\u043c\u0463\u0441\u0442\u043d\u0438\u0447\u0435\u0441\u0442\u0432\u0430. \u0412\u044a \u043d\u0435\u043c\u044a \u0431\u044b\u0432\u0430\u044e\u0442\u044a \u043a\u0430\u0436\u0434\u0443\u044e \u043d\u0435\u0434\u0463\u043b\u044e \u043f\u043e \u043f\u043e\u043d\u0435\u0434\u0463\u043b\u044c\u043d\u0438\u043a\u0430\u043c\u044a \u0438 \u043f\u044f\u0442\u043d\u0438\u0446\u0430\u043c\u044a \u0442\u043e\u0440\u0433\u0438.</span>", "hgr_name": "\u0411\u043e\u0433\u0430\u0442\u044b\u0439", "hgr_name_modern_sp": "\u0411\u043e\u0433\u0430\u0442\u044b\u0439", "hgr_page": 18, "hgr_partof_id": 15.0, "hgr_prov_modern_sp": "\u041a\u0443\u0440\u0441\u043a\u043e\u0433\u043e \u041d\u0430\u043c\u0435\u0441\u0442\u043d\u0438\u0447\u0435\u0441\u0442\u0432\u0430", "hgr_prov_stem": "\u043a\u0443\u0440\u0441\u043a", "hgr_ru_prov": "\u041a\u0443\u0440\u0441\u043a\u0430\u0433\u043e \u041d\u0430\u043c\u0463\u0441\u0442\u043d\u0438\u0447\u0435\u0441\u0442\u0432\u0430", "hgr_ru_uezd": "not_in_text", "hgr_source_url": "http://babel.hathitrust.org/cgi/pt?id=uc1.b4583201;view=1up;seq=17", "hgr_text": "\u0411\u041e\u0413\u0410\u0422\u042b\u0419, \u0433\u043e\u0440\u043e\u0434\u044a \u041a\u0443\u0440\u0441\u043a\u0430\u0433\u043e \u041d\u0430\u043c\u0463\u0441\u0442\u043d\u0438\u0447\u0435\u0441\u0442\u0432\u0430. \u0412\u044a \u043d\u0435\u043c\u044a \u0431\u044b\u0432\u0430\u044e\u0442\u044a \u043a\u0430\u0436\u0434\u0443\u044e \u043d\u0435\u0434\u0463\u043b\u044e \u043f\u043e \u043f\u043e\u043d\u0435\u0434\u0463\u043b\u044c\u043d\u0438\u043a\u0430\u043c\u044a \u0438 \u043f\u044f\u0442\u043d\u0438\u0446\u0430\u043c\u044a \u0442\u043e\u0440\u0433\u0438.", "hgr_type": "\u0433\u043e\u0440\u043e\u0434\u044a", "hgr_uezd_modern_sp": "not_\u0438n_text", "hgr_uezd_stem": "\u043d\u043e\u0442_\u0438\u043d_\u0442\u0435x\u0442", "name": "Bogatoye", "population": 0, "toponymName": "Bogatoye"}, "type": "Feature"}], "type": "FeatureCollection"}