{"type": "FeatureCollection", "features": [{"properties": {"countryId": "2017370", "toponymName": "Bogatyy", "adminCode1": "09", "geonameId": 808810, "fcl": "P", "name": "Bogatyy", "countryName": "Russia", "fclName": "city, village,...", "fcode": "PPL", "adminName1": "Belgorod", "countryCode": "RU", "population": 0, "fcodeName": "populated place"}, "geometry": {"coordinates": [37.88558, 50.65372], "type": "Point"}, "type": "feature"}, {"properties": {"countryId": "2017370", "toponymName": "Bogatyy", "adminCode1": "76", "geonameId": 575730, "fcl": "P", "name": "Bogatyy", "countryName": "Russia", "fclName": "city, village,...", "fcode": "PPL", "adminName1": "Tula", "countryCode": "RU", "population": 0, "fcodeName": "populated place"}, "geometry": {"coordinates": [36.88588, 53.4992], "type": "Point"}, "type": "feature"}]}