{"type": "FeatureCollection", "features": [{"type": "Feature", "geometry": {"coordinates": [37.88558, 50.65372], "type": "Point"}, "properties": {"countryCode": "RU", "countryId": "2017370", "fcodeName": "populated place", "adminName1": "Belgorod", "fclName": "city, village,...", "fcl": "P", "countryName": "Russia", "fcode": "PPL", "geonameId": 808810, "population": 0, "adminCode1": "09", "name": "Bogatyy", "toponymName": "Bogatyy"}}, {"type": "Feature", "geometry": {"coordinates": [36.88588, 53.4992], "type": "Point"}, "properties": {"countryCode": "RU", "countryId": "2017370", "fcodeName": "populated place", "adminName1": "Tula", "fclName": "city, village,...", "fcl": "P", "countryName": "Russia", "fcode": "PPL", "geonameId": 575730, "population": 0, "adminCode1": "76", "name": "Bogatyy", "toponymName": "Bogatyy"}}]}