{"features": [{"properties": {"hgr_name_modern_sp": "\u0412\u0430\u0448\u043a\u0430", "countryCode": "RU", "hgr_admin_hierarchy": "\u0430\u0440\u0445\u0430\u043d\u0433\u0435\u043b\u044c\u0441\u043a|\u043c\u0435\u0437\u0435\u043d\u0441\u043a", "fcl": "P", "toponymName": "Melospol\u2019ye", "countryName": "Russia", "adminCode1": "06", "fcodeName": "populated place", "population": 0, "hgr_partof_id": 90.0, "hgr_page": 26, "hgr_html_text": "\u0412\u0410\u0428\u041a\u0410 , </span><span class=\"font0\" style=\"font-style:italic;\">\u0434\u0435\u0440\u0435\u0432\u043d\u044f</span><span class=\"font0\"> \u0410\u0440\u0445\u0430\u043d\u0433\u0435\u043b\u044c\u0441\u043a\u0430\u0433\u043e \u041d\u0430\u043c\u0463\u0441\u0442\u043d\u0438\u0447\u0435\u0441\u0442\u0432\u0430 \u0432\u044a \u041c\u0435\u0437\u0435\u043d\u0441\u043a\u043e\u043c\u044a \u0443\u0463\u0437\u0434\u0463. \u0417\u0434\u0463\u0441\u044c \u0431\u044b\u0432\u0430\u0435\u0442\u044a \u043d\u0435\u0431\u043e\u043b\u044c\u0448\u0430\u044f \u0433\u043e\u0434\u043e\u0432\u0430\u044f \u044f\u0440\u043c\u0430\u0440\u043a\u0430 \u0432\u044a \u0413\u0435\u043d\u0432\u0430\u0440\u0463 \u043c\u0463\u0441\u044f\u0446\u0463, \u043d\u0430\u0437\u044b\u0432\u0430\u0435\u043c\u0430\u044f \u041c\u0435\u0437\u0435\u043d\u0441\u043a\u0430\u044f, \u043d\u0430 \u043a\u043e\u0442\u043e\u0440\u0443\u044e \u0441\u044a \u0412\u043e\u043b\u043e\u043a\u043e\u043f\u0438\u043d\u0435\u0436\u0441\u043a\u043e\u0439 \u044f\u0440\u043c\u0430\u0440\u043a\u0438 \u043d\u0463\u043a\u043e\u0442\u043e\u0440\u0430\u044f \u0447\u0430\u0435\u0448\u044c \u043c\u0463\u043b\u043e\u0447\u043d\u044b\u0445\u044a \u0442\u043e\u0432\u0430\u0440\u043e\u0432\u044a \u043f\u0435\u0440\u0435\u0445\u043e\u0434\u0438\u0442\u044a.</span>", "UPDATE_SCRIPT": "python add_town_by_geoname_id.py \u0412\u0430\u0448\u043a\u0430_99.geojson 527624", "hgr_text": "\u0412\u0410\u0428\u041a\u0410 , \u0434\u0435\u0440\u0435\u0432\u043d\u044f \u0410\u0440\u0445\u0430\u043d\u0433\u0435\u043b\u044c\u0441\u043a\u0430\u0433\u043e \u041d\u0430\u043c\u0463\u0441\u0442\u043d\u0438\u0447\u0435\u0441\u0442\u0432\u0430 \u0432\u044a \u041c\u0435\u0437\u0435\u043d\u0441\u043a\u043e\u043c\u044a \u0443\u0463\u0437\u0434\u0463. \u0417\u0434\u0463\u0441\u044c \u0431\u044b\u0432\u0430\u0435\u0442\u044a \u043d\u0435\u0431\u043e\u043b\u044c\u0448\u0430\u044f \u0433\u043e\u0434\u043e\u0432\u0430\u044f \u044f\u0440\u043c\u0430\u0440\u043a\u0430 \u0432\u044a \u0413\u0435\u043d\u0432\u0430\u0440\u0463 \u043c\u0463\u0441\u044f\u0446\u0463, \u043d\u0430\u0437\u044b\u0432\u0430\u0435\u043c\u0430\u044f \u041c\u0435\u0437\u0435\u043d\u0441\u043a\u0430\u044f, \u043d\u0430 \u043a\u043e\u0442\u043e\u0440\u0443\u044e \u0441\u044a \u0412\u043e\u043b\u043e\u043a\u043e\u043f\u0438\u043d\u0435\u0436\u0441\u043a\u043e\u0439 \u044f\u0440\u043c\u0430\u0440\u043a\u0438 \u043d\u0463\u043a\u043e\u0442\u043e\u0440\u0430\u044f \u0447\u0430\u0435\u0448\u044c \u043c\u0463\u043b\u043e\u0447\u043d\u044b\u0445\u044a \u0442\u043e\u0432\u0430\u0440\u043e\u0432\u044a \u043f\u0435\u0440\u0435\u0445\u043e\u0434\u0438\u0442\u044a.", "hgr_prov_modern_sp": "\u0410\u0440\u0445\u0430\u043d\u0433\u0435\u043b\u044c\u0441\u043a\u043e\u0433\u043e \u041d\u0430\u043c\u0435\u0441\u0442\u043d\u0438\u0447\u0435\u0441\u0442\u0432\u0430", "hgr_name": "\u0412\u0430\u0448\u043a\u0430", "name": "Melospol\u2019ye", "hgr_ru_uezd": "\u041c\u0435\u0437\u0435\u043d\u0441\u043a\u043e\u043c\u044a \u0443\u0463\u0437\u0434\u0463", "hgr_source_url": "http://babel.hathitrust.org/cgi/pt?id=uc1.b4583201;view=1up;seq=25", "countryId": "2017370", "hgr_ru_prov": "\u0410\u0440\u0445\u0430\u043d\u0433\u0435\u043b\u044c\u0441\u043a\u0430\u0433\u043e \u041d\u0430\u043c\u0463\u0441\u0442\u043d\u0438\u0447\u0435\u0441\u0442\u0432\u0430", "hgr_uezd_stem": "\u043c\u0435\u0437\u0435\u043d\u0441\u043a", "hgr_admin1_partof": 2.0, "hgr_alt_name": null, "adminName1": "Arkhangelskaya", "hgr_admin2_partof": 90.0, "fcode": "PPL", "fclName": "city, village,...", "hgr_prov_stem": "\u0430\u0440\u0445\u0430\u043d\u0433\u0435\u043b\u044c\u0441\u043a", "geonameId": 527624, "hgr_type": "\u0434\u0435\u0440\u0435\u0432\u043d\u044f", "hgr_uezd_modern_sp": "\u041c\u0435\u0437\u0435\u043d\u0441\u043a\u043e\u043c \u0443\u0435\u0437\u0434\u0435"}, "geometry": {"coordinates": [45.7464, 64.8827], "type": "Point"}, "type": "Feature"}], "type": "FeatureCollection"}