{"type": "FeatureCollection", "features": [{"type": "Feature", "geometry": {"coordinates": [45.7464, 64.8827], "type": "Point"}, "properties": {"countryCode": "RU", "countryId": "2017370", "fcodeName": "populated place", "adminName1": "Arkhangelskaya", "fclName": "city, village,...", "fcl": "P", "countryName": "Russia", "fcode": "PPL", "geonameId": 527624, "population": 0, "adminCode1": "06", "name": "Melospol\u2019ye", "toponymName": "Melospol\u2019ye"}}]}