{"type": "FeatureCollection", "features": [{"properties": {"countryId": "690791", "toponymName": "Valky", "adminCode1": "07", "geonameId": 690509, "fcl": "P", "name": "Valky", "countryName": "Ukraine", "fclName": "city, village,...", "fcode": "PPL", "adminName1": "Kharkiv", "countryCode": "UA", "population": 10099, "fcodeName": "populated place"}, "geometry": {"coordinates": [35.61223, 49.83597], "type": "Point"}, "type": "feature"}, {"properties": {"countryId": "690791", "toponymName": "Valky", "adminCode1": "21", "geonameId": 807464, "fcl": "P", "name": "Valky", "countryName": "Ukraine", "fclName": "city, village,...", "fcode": "PPL", "adminName1": "Sumy", "countryCode": "UA", "population": 0, "fcodeName": "populated place"}, "geometry": {"coordinates": [34.64599, 50.77849], "type": "Point"}, "type": "feature"}, {"properties": {"countryId": "690791", "toponymName": "Valki", "adminCode1": "07", "geonameId": 807503, "fcl": "P", "name": "Valki", "countryName": "Ukraine", "fclName": "city, village,...", "fcode": "PPL", "adminName1": "Kharkiv", "countryCode": "UA", "population": 0, "fcodeName": "populated place"}, "geometry": {"coordinates": [37.31389, 50.29611], "type": "Point"}, "type": "feature"}, {"properties": {"countryId": "690791", "toponymName": "Stari Valky", "adminCode1": "07", "geonameId": 8678360, "fcl": "P", "name": "Stari Valky", "countryName": "Ukraine", "fclName": "city, village,...", "fcode": "PPL", "adminName1": "Kharkiv", "countryCode": "UA", "population": 0, "fcodeName": "populated place"}, "geometry": {"coordinates": [35.56431, 49.86111], "type": "Point"}, "type": "feature"}]}