{"type": "FeatureCollection", "features": [{"properties": {"countryId": "2017370", "toponymName": "Melospol\u2019ye", "adminCode1": "06", "geonameId": 527624, "fcl": "P", "name": "Melospol\u2019ye", "countryName": "Russia", "fclName": "city, village,...", "fcode": "PPL", "adminName1": "Arkhangelskaya", "countryCode": "RU", "population": 0, "fcodeName": "populated place"}, "geometry": {"coordinates": [45.7464, 64.8827], "type": "Point"}, "type": "feature"}]}