{"type": "FeatureCollection", "features": [{"type": "Feature", "geometry": {"coordinates": [35.61223, 49.83597], "type": "Point"}, "properties": {"countryCode": "UA", "countryId": "690791", "fcodeName": "populated place", "adminName1": "Kharkiv", "fclName": "city, village,...", "fcl": "P", "countryName": "Ukraine", "fcode": "PPL", "geonameId": 690509, "population": 10099, "adminCode1": "07", "name": "Valky", "toponymName": "Valky"}}, {"type": "Feature", "geometry": {"coordinates": [34.64599, 50.77849], "type": "Point"}, "properties": {"countryCode": "UA", "countryId": "690791", "fcodeName": "populated place", "adminName1": "Sumy", "fclName": "city, village,...", "fcl": "P", "countryName": "Ukraine", "fcode": "PPL", "geonameId": 807464, "population": 0, "adminCode1": "21", "name": "Valky", "toponymName": "Valky"}}, {"type": "Feature", "geometry": {"coordinates": [37.31389, 50.29611], "type": "Point"}, "properties": {"countryCode": "UA", "countryId": "690791", "fcodeName": "populated place", "adminName1": "Kharkiv", "fclName": "city, village,...", "fcl": "P", "countryName": "Ukraine", "fcode": "PPL", "geonameId": 807503, "population": 0, "adminCode1": "07", "name": "Valki", "toponymName": "Valki"}}, {"type": "Feature", "geometry": {"coordinates": [35.56431, 49.86111], "type": "Point"}, "properties": {"countryCode": "UA", "countryId": "690791", "fcodeName": "populated place", "adminName1": "Kharkiv", "fclName": "city, village,...", "fcl": "P", "countryName": "Ukraine", "fcode": "PPL", "geonameId": 8678360, "population": 0, "adminCode1": "07", "name": "Stari Valky", "toponymName": "Stari Valky"}}]}