{"type": "FeatureCollection", "features": [{"type": "Feature", "geometry": {"coordinates": [37.2604, 58.66398], "type": "Point"}, "properties": {"countryCode": "RU", "countryId": "2017370", "fcodeName": "populated place", "adminName1": "Tverskaya", "fclName": "city, village,...", "fcl": "P", "countryName": "Russia", "fcode": "PPL", "geonameId": 473943, "population": 8200, "adminCode1": "77", "name": "Ves'yegonsk", "toponymName": "Ves\u2019yegonsk"}}]}