{"features": [{"properties": {"fcl": "P", "geonameId": 473943, "countryId": "2017370", "fcode": "PPL", "name": "Ves'yegonsk", "countryName": "Russia", "population": 8200, "fclName": "city, village,...", "adminName1": "Tverskaya", "adminCode1": "77", "fcodeName": "populated place", "countryCode": "RU", "toponymName": "Ves\u2019yegonsk"}, "geometry": {"coordinates": [37.2604, 58.66398], "type": "Point"}, "type": "Feature"}], "type": "FeatureCollection"}