{"type": "FeatureCollection", "features": [{"properties": {"countryId": "2017370", "toponymName": "Ves\u2019yegonsk", "adminCode1": "77", "geonameId": 473943, "fcl": "P", "name": "Ves'yegonsk", "countryName": "Russia", "fclName": "city, village,...", "fcode": "PPL", "adminName1": "Tverskaya", "countryCode": "RU", "population": 8200, "fcodeName": "populated place"}, "geometry": {"coordinates": [37.2604, 58.66398], "type": "Point"}, "type": "feature"}]}