{"features": [{"properties": {"fcl": "P", "geonameId": 471122, "countryId": "2017370", "fcode": "PPL", "name": "Vrev", "countryName": "Russia", "population": 0, "fclName": "city, village,...", "adminName1": "Pskov", "adminCode1": "60", "fcodeName": "populated place", "countryCode": "RU", "toponymName": "Vrev"}, "geometry": {"coordinates": [28.84938, 57.20557], "type": "Point"}, "type": "Feature"}], "type": "FeatureCollection"}