{"type": "FeatureCollection", "features": [{"type": "Feature", "geometry": {"coordinates": [28.84938, 57.20557], "type": "Point"}, "properties": {"countryCode": "RU", "countryId": "2017370", "fcodeName": "populated place", "adminName1": "Pskov", "fclName": "city, village,...", "fcl": "P", "countryName": "Russia", "fcode": "PPL", "geonameId": 471122, "population": 0, "adminCode1": "60", "name": "Vrev", "toponymName": "Vrev"}}]}