{"features": [{"geometry": {"coordinates": [28.84938, 57.20557], "type": "Point"}, "properties": {"UPDATE_SCRIPT": "python add_town_by_geoname_id.py \u0412\u0440\u0435\u0432_128.geojson 471122", "adminCode1": "60", "adminName1": "Pskov", "countryCode": "RU", "countryId": "2017370", "countryName": "Russia", "fcl": "P", "fclName": "city, village,...", "fcode": "PPL", "fcodeName": "populated place", "geonameId": 471122, "hgr_admin1_partof": 25.0, "hgr_admin2_partof": null, "hgr_admin_hierarchy": "\u043f\u0441\u043a\u043e\u0432\u0441\u043a", "hgr_alt_name": null, "hgr_html_text": "\u0412\u0420\u0415\u0412\u042a, </span><span class=\"font0\" style=\"font-style:italic;\">\u043f\u0440\u0438\u0433\u043e\u0440\u043e\u0434\u044a</span><span class=\"font0\"> \u041f\u0441\u043a\u043e\u0432\u0441\u043a\u0430\u0433\u043e \u041d\u0430\u043c\u0463\u0441\u0442\u043d\u0438\u0447\u0435\u0441\u0442\u0432\u0430. \u0417\u0434\u0463\u0441\u044c \u0431\u044b\u0432\u0430\u0435\u0442\u044a \u044f\u0440\u043c\u0430\u0440\u043a\u0430 \u0432\u044a \u0434\u0435\u043d\u044c \u041d\u0438\u043a\u043e\u043b\u0430\u044f \u0427\u0443\u0434\u043e\u0442\u0432\u043e\u0440\u0446\u0430 , \u043d\u0430 \u043a\u043e\u0442\u043e\u0440\u0443\u044e \u043f\u0440\u0456\u0463\u0437\u0436\u0430\u044e\u0442\u044a \u0438\u0437\u044a \u0440\u0430\u0437\u043d\u044b\u0445\u044a \u043c\u0463\u0441\u0442\u044a \u0441\u044a \u043c\u0463\u043b\u043e\u0447\u043d\u044b\u043c\u044a \u0442\u043e\u0432\u0430\u0440\u043e\u043c\u044a.</span>", "hgr_name": "\u0412\u0440\u0435\u0432\u044a", "hgr_name_modern_sp": "\u0412\u0440\u0435\u0432", "hgr_page": 30, "hgr_partof_id": 25.0, "hgr_prov_modern_sp": "\u041f\u0441\u043a\u043e\u0432\u0441\u043a\u043e\u0433\u043e \u041d\u0430\u043c\u0435\u0441\u0442\u043d\u0438\u0447\u0435\u0441\u0442\u0432\u0430", "hgr_prov_stem": "\u043f\u0441\u043a\u043e\u0432\u0441\u043a", "hgr_ru_prov": "\u041f\u0441\u043a\u043e\u0432\u0441\u043a\u0430\u0433\u043e \u041d\u0430\u043c\u0463\u0441\u0442\u043d\u0438\u0447\u0435\u0441\u0442\u0432\u0430", "hgr_ru_uezd": "not_in_text", "hgr_source_url": "http://babel.hathitrust.org/cgi/pt?id=uc1.b4583201;view=1up;seq=29", "hgr_text": "\u0412\u0420\u0415\u0412\u042a, \u043f\u0440\u0438\u0433\u043e\u0440\u043e\u0434\u044a \u041f\u0441\u043a\u043e\u0432\u0441\u043a\u0430\u0433\u043e \u041d\u0430\u043c\u0463\u0441\u0442\u043d\u0438\u0447\u0435\u0441\u0442\u0432\u0430. \u0417\u0434\u0463\u0441\u044c \u0431\u044b\u0432\u0430\u0435\u0442\u044a \u044f\u0440\u043c\u0430\u0440\u043a\u0430 \u0432\u044a \u0434\u0435\u043d\u044c \u041d\u0438\u043a\u043e\u043b\u0430\u044f \u0427\u0443\u0434\u043e\u0442\u0432\u043e\u0440\u0446\u0430 , \u043d\u0430 \u043a\u043e\u0442\u043e\u0440\u0443\u044e \u043f\u0440\u0456\u0463\u0437\u0436\u0430\u044e\u0442\u044a \u0438\u0437\u044a \u0440\u0430\u0437\u043d\u044b\u0445\u044a \u043c\u0463\u0441\u0442\u044a \u0441\u044a \u043c\u0463\u043b\u043e\u0447\u043d\u044b\u043c\u044a \u0442\u043e\u0432\u0430\u0440\u043e\u043c\u044a.", "hgr_type": "\u043f\u0440\u0438\u0433\u043e\u0440\u043e\u0434\u044a", "hgr_uezd_modern_sp": "not_\u0438n_text", "hgr_uezd_stem": "\u043d\u043e\u0442_\u0438\u043d_\u0442\u0435x\u0442", "name": "Vrev", "population": 0, "toponymName": "Vrev"}, "type": "Feature"}], "type": "FeatureCollection"}