{"type": "FeatureCollection", "features": [{"properties": {"countryId": "2017370", "toponymName": "Vrev", "adminCode1": "60", "geonameId": 471122, "fcl": "P", "name": "Vrev", "countryName": "Russia", "fclName": "city, village,...", "fcode": "PPL", "adminName1": "Pskov", "countryCode": "RU", "population": 0, "fcodeName": "populated place"}, "geometry": {"coordinates": [28.84938, 57.20557], "type": "Point"}, "type": "feature"}]}