{"type": "FeatureCollection", "features": [{"type": "Feature", "geometry": {"coordinates": [29.1663, 57.22716], "type": "Point"}, "properties": {"countryCode": "RU", "countryId": "2017370", "fcodeName": "populated place", "adminName1": "Pskov", "fclName": "city, village,...", "fcl": "P", "countryName": "Russia", "fcode": "PPL", "geonameId": 470549, "population": 1500, "adminCode1": "60", "name": "Vybor", "toponymName": "Vybor"}}, {"type": "Feature", "geometry": {"coordinates": [30.10436, 58.69725], "type": "Point"}, "properties": {"countryCode": "RU", "countryId": "2017370", "fcodeName": "populated place", "adminName1": "Leningrad", "fclName": "city, village,...", "fcl": "P", "countryName": "Russia", "fcode": "PPL", "geonameId": 470548, "population": 0, "adminCode1": "42", "name": "Vybor", "toponymName": "Vybor"}}]}