{"features": [{"properties": {"fcl": "P", "geonameId": 470549, "countryId": "2017370", "fcode": "PPL", "name": "Vybor", "countryName": "Russia", "population": 1500, "fclName": "city, village,...", "adminName1": "Pskov", "adminCode1": "60", "fcodeName": "populated place", "countryCode": "RU", "toponymName": "Vybor"}, "geometry": {"coordinates": [29.1663, 57.22716], "type": "Point"}, "type": "Feature"}, {"properties": {"fcl": "P", "geonameId": 470548, "countryId": "2017370", "fcode": "PPL", "name": "Vybor", "countryName": "Russia", "population": 0, "fclName": "city, village,...", "adminName1": "Leningrad", "adminCode1": "42", "fcodeName": "populated place", "countryCode": "RU", "toponymName": "Vybor"}, "geometry": {"coordinates": [30.10436, 58.69725], "type": "Point"}, "type": "Feature"}], "type": "FeatureCollection"}