{"type": "FeatureCollection", "features": [{"properties": {"countryId": "2017370", "toponymName": "Vybor", "adminCode1": "60", "geonameId": 470549, "fcl": "P", "name": "Vybor", "countryName": "Russia", "fclName": "city, village,...", "fcode": "PPL", "adminName1": "Pskov", "countryCode": "RU", "population": 1500, "fcodeName": "populated place"}, "geometry": {"coordinates": [29.1663, 57.22716], "type": "Point"}, "type": "feature"}, {"properties": {"countryId": "2017370", "toponymName": "Vybor", "adminCode1": "42", "geonameId": 470548, "fcl": "P", "name": "Vybor", "countryName": "Russia", "fclName": "city, village,...", "fcode": "PPL", "adminName1": "Leningrad", "countryCode": "RU", "population": 0, "fcodeName": "populated place"}, "geometry": {"coordinates": [30.10436, 58.69725], "type": "Point"}, "type": "feature"}]}