{"type": "FeatureCollection", "features": [{"type": "Feature", "geometry": {"coordinates": [38.10556, 54.60417], "type": "Point"}, "properties": {"countryCode": "RU", "countryId": "2017370", "fcodeName": "populated place", "adminName1": "Tula", "fclName": "city, village,...", "fcl": "P", "countryName": "Russia", "fcode": "PPL", "geonameId": 558505, "population": 0, "adminCode1": "76", "name": "Gritchino", "toponymName": "Gritchino"}}]}