{"type": "FeatureCollection", "features": [{"properties": {"countryId": "2017370", "toponymName": "Gritchino", "adminCode1": "76", "geonameId": 558505, "fcl": "P", "name": "Gritchino", "countryName": "Russia", "fclName": "city, village,...", "fcode": "PPL", "adminName1": "Tula", "countryCode": "RU", "population": 0, "fcodeName": "populated place"}, "geometry": {"coordinates": [38.10556, 54.60417], "type": "Point"}, "type": "feature"}]}