{"type": "FeatureCollection", "features": [{"type": "Feature", "geometry": {"coordinates": [39.127, 55.05594], "type": "Point"}, "properties": {"countryCode": "RU", "countryId": "2017370", "fcodeName": "populated place", "adminName1": "Moskovskaya", "fclName": "city, village,...", "fcl": "P", "countryName": "Russia", "fcode": "PPL", "geonameId": 566883, "population": 0, "adminCode1": "47", "name": "Dedinovo", "toponymName": "Dedinovo"}}]}