{"features": [{"properties": {"hgr_name_modern_sp": "\u0414\u0435\u0434\u0438\u043d\u043e\u0432\u043e", "countryCode": "RU", "hgr_admin_hierarchy": "\u043c\u043e\u0441\u043a\u043e\u0432\u0441\u043a|\u043a\u043e\u043b\u043e\u043c\u043d", "fcl": "P", "toponymName": "Dedinovo", "countryName": "Russia", "adminCode1": "47", "fcodeName": "populated place", "population": 0, "hgr_partof_id": 81.0, "hgr_page": 42, "hgr_html_text": "\u0414\u0462\u0414\u0418\u041d\u041e\u0412\u041e, </span><span class=\"font0\" style=\"font-style:italic;\">\u0441\u0435\u043b\u043e</span><span class=\"font0\"> \u041c\u043e\u0441\u043a\u043e\u0432\u0441\u043a\u043e\u0439 \u0413\u0443\u0431\u0435\u0440\u043d\u0456\u0438 \u0432\u044a \u0443\u0463\u0437\u0434\u0463 \u0433\u043e\u0440\u043e\u0434\u0430 \u041a\u043e\u043b\u043e\u043c\u043d\u044b. \u0412\u044a \u043d\u0435\u043c\u044a \u0438\u043c\u0463\u0435\u0442\u0441\u044f \u0434\u0432\u0430 \u0440\u044f\u0434\u0430, \u0438\u0437\u044a \u043a\u043e\u0442\u043e\u0440\u044b\u0445\u044a \u0432\u044a \u043e\u0434\u043d\u043e\u043c\u044a \u0442\u043e\u0440\u0433\u0443\u044e\u0442\u044a \u0441\u0463\u0463\u0441\u0442\u043d\u044b\u043c\u0438 \u043f\u0440\u0438\u043f\u0430\u0441\u0430\u043c\u0438, \u0430 \u0432\u044a \u0434\u0440\u0443\u0433\u043e\u043c\u044a \u0432\u044a \u0431\u044b\u0432\u0430\u044e\u0449\u0456\u0439 \u0435\u0436\u0435\u043d\u0435\u0434\u0463\u043b\u044c\u043d\u043e \u0432\u044a \u043f\u044f\u0442\u043d\u0438\u0446\u0443 \u0442\u043e\u0440\u0433\u044a \u043f\u0440\u043e\u0434\u0430\u0435\u0442\u0441\u044f \u0442\u0430\u043c\u043e\u0448\u043d\u0438\u043c\u044a \u043e\u0431\u044b\u0432\u0430\u0442\u0435\u043b\u044f\u043c\u044a \u043f\u0440\u0438\u0432\u043e\u0437\u0438\u043c\u043e\u0439 \u0438\u0437\u044a \u041a\u043e\u043b\u043e\u043c\u043d\u044b \u0440\u0430\u0437\u043d\u043e\u0439 \u0449\u0435\u043f\u0435\u0442\u0438\u043b\u044c\u043d\u043e\u0439 \u0442\u043e\u0432\u0430\u0440\u044a, \u0438 \u0438\u0437\u044a \u0440\u0430\u0437\u043d\u044b\u0445\u044a \u0434\u0435\u0440\u0435\u0432\u0435\u043d\u044c \u0432\u0441\u044f\u043a\u043e\u0439 \u0445\u043b\u0463\u0431\u044a.</span>", "UPDATE_SCRIPT": "python add_town_by_geoname_id.py \u0414\u0435\u0434\u0438\u043d\u043e\u0432\u043e_210.geojson 566883", "hgr_text": "\u0414\u0462\u0414\u0418\u041d\u041e\u0412\u041e, \u0441\u0435\u043b\u043e \u041c\u043e\u0441\u043a\u043e\u0432\u0441\u043a\u043e\u0439 \u0413\u0443\u0431\u0435\u0440\u043d\u0456\u0438 \u0432\u044a \u0443\u0463\u0437\u0434\u0463 \u0433\u043e\u0440\u043e\u0434\u0430 \u041a\u043e\u043b\u043e\u043c\u043d\u044b. \u0412\u044a \u043d\u0435\u043c\u044a \u0438\u043c\u0463\u0435\u0442\u0441\u044f \u0434\u0432\u0430 \u0440\u044f\u0434\u0430, \u0438\u0437\u044a \u043a\u043e\u0442\u043e\u0440\u044b\u0445\u044a \u0432\u044a \u043e\u0434\u043d\u043e\u043c\u044a \u0442\u043e\u0440\u0433\u0443\u044e\u0442\u044a \u0441\u0463\u0463\u0441\u0442\u043d\u044b\u043c\u0438 \u043f\u0440\u0438\u043f\u0430\u0441\u0430\u043c\u0438, \u0430 \u0432\u044a \u0434\u0440\u0443\u0433\u043e\u043c\u044a \u0432\u044a \u0431\u044b\u0432\u0430\u044e\u0449\u0456\u0439 \u0435\u0436\u0435\u043d\u0435\u0434\u0463\u043b\u044c\u043d\u043e \u0432\u044a \u043f\u044f\u0442\u043d\u0438\u0446\u0443 \u0442\u043e\u0440\u0433\u044a \u043f\u0440\u043e\u0434\u0430\u0435\u0442\u0441\u044f \u0442\u0430\u043c\u043e\u0448\u043d\u0438\u043c\u044a \u043e\u0431\u044b\u0432\u0430\u0442\u0435\u043b\u044f\u043c\u044a \u043f\u0440\u0438\u0432\u043e\u0437\u0438\u043c\u043e\u0439 \u0438\u0437\u044a \u041a\u043e\u043b\u043e\u043c\u043d\u044b \u0440\u0430\u0437\u043d\u043e\u0439 \u0449\u0435\u043f\u0435\u0442\u0438\u043b\u044c\u043d\u043e\u0439 \u0442\u043e\u0432\u0430\u0440\u044a, \u0438 \u0438\u0437\u044a \u0440\u0430\u0437\u043d\u044b\u0445\u044a \u0434\u0435\u0440\u0435\u0432\u0435\u043d\u044c \u0432\u0441\u044f\u043a\u043e\u0439 \u0445\u043b\u0463\u0431\u044a.", "hgr_prov_modern_sp": "\u041c\u043e\u0441\u043a\u043e\u0432\u0441\u043a\u043e\u0439 \u0413\u0443\u0431\u0435\u0440\u043d\u0438\u0438", "hgr_name": "\u0414\u0463\u0434\u0438\u043d\u043e\u0432\u043e", "name": "Dedinovo", "hgr_ru_uezd": "\u041a\u043e\u043b\u043e\u043c\u043d\u044b", "hgr_source_url": "http://babel.hathitrust.org/cgi/pt?id=uc1.b4583201;view=1up;seq=41", "countryId": "2017370", "hgr_ru_prov": "\u041c\u043e\u0441\u043a\u043e\u0432\u0441\u043a\u043e\u0439 \u0413\u0443\u0431\u0435\u0440\u043d\u0456\u0438", "hgr_uezd_stem": "\u043a\u043e\u043b\u043e\u043c\u043d", "hgr_admin1_partof": 1.0, "hgr_alt_name": null, "adminName1": "Moskovskaya", "hgr_admin2_partof": 81.0, "fcode": "PPL", "fclName": "city, village,...", "hgr_prov_stem": "\u043c\u043e\u0441\u043a\u043e\u0432\u0441\u043a", "geonameId": 566883, "hgr_type": "\u0441\u0435\u043b\u043e", "hgr_uezd_modern_sp": "\u041a\u043e\u043b\u043e\u043c\u043d\u044b"}, "geometry": {"coordinates": [39.127, 55.05594], "type": "Point"}, "type": "Feature"}], "type": "FeatureCollection"}