{"features": [{"properties": {"fcl": "P", "geonameId": 566883, "countryId": "2017370", "fcode": "PPL", "name": "Dedinovo", "countryName": "Russia", "population": 0, "fclName": "city, village,...", "adminName1": "Moskovskaya", "adminCode1": "47", "fcodeName": "populated place", "countryCode": "RU", "toponymName": "Dedinovo"}, "geometry": {"coordinates": [39.127, 55.05594], "type": "Point"}, "type": "Feature"}], "type": "FeatureCollection"}