{"type": "FeatureCollection", "features": [{"properties": {"countryId": "2017370", "toponymName": "Dedinovo", "adminCode1": "47", "geonameId": 566883, "fcl": "P", "name": "Dedinovo", "countryName": "Russia", "fclName": "city, village,...", "fcode": "PPL", "adminName1": "Moskovskaya", "countryCode": "RU", "population": 0, "fcodeName": "populated place"}, "geometry": {"coordinates": [39.127, 55.05594], "type": "Point"}, "type": "feature"}]}