{"type": "FeatureCollection", "features": [{"properties": {"countryId": "690791", "toponymName": "Khutor Dergachi", "adminCode1": "07", "geonameId": 710099, "fcl": "P", "name": "Khutor Dergachi", "countryName": "Ukraine", "fclName": "city, village,...", "fcode": "PPLQ", "adminName1": "Kharkiv", "countryCode": "UA", "population": 0, "fcodeName": "abandoned populated place"}, "geometry": {"coordinates": [35.4808, 49.96385], "type": "Point"}, "type": "feature"}, {"properties": {"countryId": "690791", "toponymName": "Derhachi", "adminCode1": "07", "geonameId": 710098, "fcl": "P", "name": "Derhachi", "countryName": "Ukraine", "fclName": "city, village,...", "fcode": "PPLA2", "adminName1": "Kharkiv", "countryCode": "UA", "population": 19322, "fcodeName": "seat of a second-order administrative division"}, "geometry": {"coordinates": [36.12112, 50.10659], "type": "Point"}, "type": "feature"}, {"properties": {"countryId": "690791", "toponymName": "Dergachi", "adminCode1": "18", "geonameId": 710095, "fcl": "P", "name": "Dergachi", "countryName": "Ukraine", "fclName": "city, village,...", "fcode": "PPL", "adminName1": "Poltava", "countryCode": "UA", "population": 0, "fcodeName": "populated place"}, "geometry": {"coordinates": [34.51667, 49.4], "type": "Point"}, "type": "feature"}]}