{"type": "FeatureCollection", "features": [{"type": "Feature", "geometry": {"coordinates": [35.4808, 49.96385], "type": "Point"}, "properties": {"countryCode": "UA", "countryId": "690791", "fcodeName": "abandoned populated place", "adminName1": "Kharkiv", "fclName": "city, village,...", "fcl": "P", "countryName": "Ukraine", "fcode": "PPLQ", "geonameId": 710099, "population": 0, "adminCode1": "07", "name": "Khutor Dergachi", "toponymName": "Khutor Dergachi"}}, {"type": "Feature", "geometry": {"coordinates": [36.12112, 50.10659], "type": "Point"}, "properties": {"countryCode": "UA", "countryId": "690791", "fcodeName": "seat of a second-order administrative division", "adminName1": "Kharkiv", "fclName": "city, village,...", "fcl": "P", "countryName": "Ukraine", "fcode": "PPLA2", "geonameId": 710098, "population": 19322, "adminCode1": "07", "name": "Derhachi", "toponymName": "Derhachi"}}, {"type": "Feature", "geometry": {"coordinates": [34.51667, 49.4], "type": "Point"}, "properties": {"countryCode": "UA", "countryId": "690791", "fcodeName": "populated place", "adminName1": "Poltava", "fclName": "city, village,...", "fcl": "P", "countryName": "Ukraine", "fcode": "PPL", "geonameId": 710095, "population": 0, "adminCode1": "18", "name": "Dergachi", "toponymName": "Dergachi"}}]}