{"type": "FeatureCollection", "features": [{"properties": {"countryId": "2017370", "toponymName": "Dorogobuzh", "adminCode1": "52", "geonameId": 565200, "fcl": "P", "name": "Dorogobuzh", "countryName": "Russia", "fclName": "city, village,...", "fcode": "PPL", "adminName1": "Novgorod", "countryCode": "RU", "population": 0, "fcodeName": "populated place"}, "geometry": {"coordinates": [30.62305, 58.60721], "type": "Point"}, "type": "feature"}, {"properties": {"countryId": "2017370", "toponymName": "Dorogobuzh", "adminCode1": "69", "geonameId": 565201, "fcl": "P", "name": "Dorogobuzh", "countryName": "Russia", "fclName": "city, village,...", "fcode": "PPL", "adminName1": "Smolensk", "countryCode": "RU", "population": 0, "fcodeName": "populated place"}, "geometry": {"coordinates": [33.25, 55.11667], "type": "Point"}, "type": "feature"}, {"properties": {"countryId": "2017370", "toponymName": "Dorogobuzh", "adminCode1": "69", "geonameId": 565202, "fcl": "P", "name": "Dorogobuzh", "countryName": "Russia", "fclName": "city, village,...", "fcode": "PPL", "adminName1": "Smolensk", "countryCode": "RU", "population": 12293, "fcodeName": "populated place"}, "geometry": {"coordinates": [33.29722, 54.915], "type": "Point"}, "type": "feature"}]}