{"type": "FeatureCollection", "features": [{"type": "Feature", "geometry": {"coordinates": [30.62305, 58.60721], "type": "Point"}, "properties": {"countryCode": "RU", "countryId": "2017370", "fcodeName": "populated place", "adminName1": "Novgorod", "fclName": "city, village,...", "fcl": "P", "countryName": "Russia", "fcode": "PPL", "geonameId": 565200, "population": 0, "adminCode1": "52", "name": "Dorogobuzh", "toponymName": "Dorogobuzh"}}, {"type": "Feature", "geometry": {"coordinates": [33.25, 55.11667], "type": "Point"}, "properties": {"countryCode": "RU", "countryId": "2017370", "fcodeName": "populated place", "adminName1": "Smolensk", "fclName": "city, village,...", "fcl": "P", "countryName": "Russia", "fcode": "PPL", "geonameId": 565201, "population": 0, "adminCode1": "69", "name": "Dorogobuzh", "toponymName": "Dorogobuzh"}}, {"type": "Feature", "geometry": {"coordinates": [33.29722, 54.915], "type": "Point"}, "properties": {"countryCode": "RU", "countryId": "2017370", "fcodeName": "populated place", "adminName1": "Smolensk", "fclName": "city, village,...", "fcl": "P", "countryName": "Russia", "fcode": "PPL", "geonameId": 565202, "population": 12293, "adminCode1": "69", "name": "Dorogobuzh", "toponymName": "Dorogobuzh"}}]}