{"features": [{"properties": {"fcl": "P", "geonameId": 565200, "countryId": "2017370", "fcode": "PPL", "name": "Dorogobuzh", "countryName": "Russia", "population": 0, "fclName": "city, village,...", "adminName1": "Novgorod", "adminCode1": "52", "fcodeName": "populated place", "countryCode": "RU", "toponymName": "Dorogobuzh"}, "geometry": {"coordinates": [30.62305, 58.60721], "type": "Point"}, "type": "Feature"}, {"properties": {"fcl": "P", "geonameId": 565201, "countryId": "2017370", "fcode": "PPL", "name": "Dorogobuzh", "countryName": "Russia", "population": 0, "fclName": "city, village,...", "adminName1": "Smolensk", "adminCode1": "69", "fcodeName": "populated place", "countryCode": "RU", "toponymName": "Dorogobuzh"}, "geometry": {"coordinates": [33.25, 55.11667], "type": "Point"}, "type": "Feature"}, {"properties": {"fcl": "P", "geonameId": 565202, "countryId": "2017370", "fcode": "PPL", "name": "Dorogobuzh", "countryName": "Russia", "population": 12293, "fclName": "city, village,...", "adminName1": "Smolensk", "adminCode1": "69", "fcodeName": "populated place", "countryCode": "RU", "toponymName": "Dorogobuzh"}, "geometry": {"coordinates": [33.29722, 54.915], "type": "Point"}, "type": "Feature"}], "type": "FeatureCollection"}