{"type": "FeatureCollection", "features": [{"properties": {"countryId": "2017370", "toponymName": "Zaraysk", "adminCode1": "47", "geonameId": 464687, "fcl": "P", "name": "Zaraysk", "countryName": "Russia", "fclName": "city, village,...", "fcode": "PPL", "adminName1": "Moskovskaya", "countryCode": "RU", "population": 24637, "fcodeName": "populated place"}, "geometry": {"coordinates": [38.87841, 54.7605], "type": "Point"}, "type": "feature"}]}