{"features": [{"properties": {"fcl": "P", "geonameId": 464687, "countryId": "2017370", "fcode": "PPL", "name": "Zaraysk", "countryName": "Russia", "population": 24637, "fclName": "city, village,...", "adminName1": "Moskovskaya", "adminCode1": "47", "fcodeName": "populated place", "countryCode": "RU", "toponymName": "Zaraysk"}, "geometry": {"coordinates": [38.87841, 54.7605], "type": "Point"}, "type": "Feature"}], "type": "FeatureCollection"}