{"type": "FeatureCollection", "features": [{"type": "Feature", "geometry": {"coordinates": [38.87841, 54.7605], "type": "Point"}, "properties": {"countryCode": "RU", "countryId": "2017370", "fcodeName": "populated place", "adminName1": "Moskovskaya", "fclName": "city, village,...", "fcl": "P", "countryName": "Russia", "fcode": "PPL", "geonameId": 464687, "population": 24637, "adminCode1": "47", "name": "Zaraysk", "toponymName": "Zaraysk"}}]}