{"type": "FeatureCollection", "features": [{"type": "Feature", "geometry": {"coordinates": [32.72819, 51.5804], "type": "Point"}, "properties": {"countryCode": "UA", "countryId": "690791", "fcodeName": "populated place", "adminName1": "Chernihiv", "fclName": "city, village,...", "fcl": "P", "countryName": "Ukraine", "fcode": "PPL", "geonameId": 686929, "population": 0, "adminCode1": "02", "name": "Zmetnev", "toponymName": "Zmitniv"}}]}