{"features": [{"type": "Feature", "geometry": {"coordinates": [32.72819, 51.5804], "type": "Point"}, "properties": {"hgr_name_modern_sp": "\u0417\u043c\u0435\u0442\u043d\u0435\u0432", "hgr_uezd_stem": "\u0441\u043e\u0441\u043d\u0438\u0446\u043a", "hgr_admin_hierarchy": "\u043d\u043e\u0432\u043e\u0433\u043e\u0440\u043e\u0434\u0441\u043a\u043e\u0433\u043e - \u0441\u0435\u0432\u0435\u0440\u0441\u043a|\u0441\u043e\u0441\u043d\u0438\u0446\u043a", "hgr_admin1_partof": null, "toponymName": "Zmitniv", "hgr_html_text": "\u0417\u041c\u0462\u0422\u041d\u0415\u0412\u042a, </span><span class=\"font0\" style=\"font-style:italic;\">\u0441\u0435\u043b\u043e</span><span class=\"font0\"> \u041d\u043e\u0432\u043e\u0433\u043e\u0440\u043e\u0434\u0441\u043a\u0430\u0433\u043e - \u0421\u0463\u0432\u0435\u0440\u0441\u043a\u0430\u0433\u043e \u041d\u0430\u043c\u0463\u0441\u0442\u043d\u0438\u0447\u0435\u0441\u0442\u0432\u0430 \u0432\u044a \u0421\u043e\u0441\u043d\u0438\u0446\u043a\u043e\u043c\u044a \u0443\u0463\u0437\u0434\u0463. \u041e\u0431\u044b\u0432\u0430\u0442\u0435\u043b\u0438 \u043e\u043d\u0430\u0433\u043e \u0438\u043c\u0463\u044e\u0442\u044a \u0438\u0437\u0440\u044f\u0434\u043d\u043e\u0439 \u043f\u0440\u043e\u043c\u044b\u0441\u043b\u044a \u0431\u043e\u0431\u0440\u0430\u043c\u0438 , \u0432\u044b\u0434\u0440\u0430\u043c\u0438 \u0438 \u0440\u044b\u0431\u043d\u043e\u044e \u0432\u044a \u0414\u0435\u0441\u043d\u0463 \u043b\u043e\u0432\u043b\u0435\u044e.</span>", "adminCode1": "02", "fcodeName": "populated place", "fcode": "PPL", "hgr_partof_id": 121.0, "hgr_page": 46, "countryName": "Ukraine", "hgr_text": "\u0417\u041c\u0462\u0422\u041d\u0415\u0412\u042a, \u0441\u0435\u043b\u043e \u041d\u043e\u0432\u043e\u0433\u043e\u0440\u043e\u0434\u0441\u043a\u0430\u0433\u043e - \u0421\u0463\u0432\u0435\u0440\u0441\u043a\u0430\u0433\u043e \u041d\u0430\u043c\u0463\u0441\u0442\u043d\u0438\u0447\u0435\u0441\u0442\u0432\u0430 \u0432\u044a \u0421\u043e\u0441\u043d\u0438\u0446\u043a\u043e\u043c\u044a \u0443\u0463\u0437\u0434\u0463. \u041e\u0431\u044b\u0432\u0430\u0442\u0435\u043b\u0438 \u043e\u043d\u0430\u0433\u043e \u0438\u043c\u0463\u044e\u0442\u044a \u0438\u0437\u0440\u044f\u0434\u043d\u043e\u0439 \u043f\u0440\u043e\u043c\u044b\u0441\u043b\u044a \u0431\u043e\u0431\u0440\u0430\u043c\u0438 , \u0432\u044b\u0434\u0440\u0430\u043c\u0438 \u0438 \u0440\u044b\u0431\u043d\u043e\u044e \u0432\u044a \u0414\u0435\u0441\u043d\u0463 \u043b\u043e\u0432\u043b\u0435\u044e.", "hgr_prov_modern_sp": "\u041d\u043e\u0432\u043e\u0433\u043e\u0440\u043e\u0434\u0441\u043a\u043e\u0433\u043e - \u0421\u0435\u0432\u0435\u0440\u0441\u043a\u043e\u0433\u043e \u041d\u0430\u043c\u0435\u0441\u0442\u043d\u0438\u0447\u0435\u0441\u0442\u0432\u0430", "hgr_name": "\u0417\u043c\u0463\u0442\u043d\u0435\u0432\u044a", "name": "Zmetnev", "hgr_ru_uezd": "\u0421\u043e\u0441\u043d\u0438\u0446\u043a\u043e\u043c\u044a \u0443\u0463\u0437\u0434\u0463", "population": 0, "countryId": "690791", "hgr_ru_prov": "\u041d\u043e\u0432\u043e\u0433\u043e\u0440\u043e\u0434\u0441\u043a\u0430\u0433\u043e - \u0421\u0463\u0432\u0435\u0440\u0441\u043a\u0430\u0433\u043e \u041d\u0430\u043c\u0463\u0441\u0442\u043d\u0438\u0447\u0435\u0441\u0442\u0432\u0430", "hgr_source_url": "http://babel.hathitrust.org/cgi/pt?id=uc1.b4583201;view=1up;seq=45", "fcl": "P", "hgr_alt_name": null, "adminName1": "Chernihiv", "hgr_admin2_partof": 121.0, "hgr_prov_stem": "\u043d\u043e\u0432\u043e\u0433\u043e\u0440\u043e\u0434\u0441\u043a\u043e\u0433\u043e - \u0441\u0435\u0432\u0435\u0440\u0441\u043a", "fclName": "city, village,...", "countryCode": "UA", "geonameId": 686929, "hgr_type": "\u0441\u0435\u043b\u043e", "hgr_uezd_modern_sp": "\u0421\u043e\u0441\u043d\u0438\u0446\u043a\u043e\u043c \u0443\u0435\u0437\u0434\u0435"}}], "type": "FeatureCollection"}