{"features": [{"properties": {"fcl": "P", "geonameId": 686929, "countryId": "690791", "fcode": "PPL", "name": "Zmetnev", "countryName": "Ukraine", "population": 0, "fclName": "city, village,...", "adminName1": "Chernihiv", "adminCode1": "02", "fcodeName": "populated place", "countryCode": "UA", "toponymName": "Zmitniv"}, "geometry": {"coordinates": [32.72819, 51.5804], "type": "Point"}, "type": "Feature"}], "type": "FeatureCollection"}