{"type": "FeatureCollection", "features": [{"properties": {"countryId": "690791", "toponymName": "Zmitniv", "adminCode1": "02", "geonameId": 686929, "fcl": "P", "name": "Zmetnev", "countryName": "Ukraine", "fclName": "city, village,...", "fcode": "PPL", "adminName1": "Chernihiv", "countryCode": "UA", "population": 0, "fcodeName": "populated place"}, "geometry": {"coordinates": [32.72819, 51.5804], "type": "Point"}, "type": "feature"}]}