{"type": "FeatureCollection", "features": [{"type": "Feature", "geometry": {"coordinates": [63.071, 57.67052], "type": "Point"}, "properties": {"countryCode": "RU", "countryId": "2017370", "fcodeName": "populated place", "adminName1": "Sverdlovsk", "fclName": "city, village,...", "fcl": "P", "countryName": "Russia", "fcode": "PPL", "geonameId": 1505526, "population": 41647, "adminCode1": "71", "name": "Irbit", "toponymName": "Irbit"}}]}