{"features": [{"properties": {"fcl": "P", "geonameId": 1505526, "countryId": "2017370", "fcode": "PPL", "name": "Irbit", "countryName": "Russia", "population": 41647, "fclName": "city, village,...", "adminName1": "Sverdlovsk", "adminCode1": "71", "fcodeName": "populated place", "countryCode": "RU", "toponymName": "Irbit"}, "geometry": {"coordinates": [63.071, 57.67052], "type": "Point"}, "type": "Feature"}], "type": "FeatureCollection"}