{"type": "FeatureCollection", "features": [{"properties": {"countryId": "2017370", "toponymName": "Irbit", "adminCode1": "71", "geonameId": 1505526, "fcl": "P", "name": "Irbit", "countryName": "Russia", "fclName": "city, village,...", "fcode": "PPL", "adminName1": "Sverdlovsk", "countryCode": "RU", "population": 41647, "fcodeName": "populated place"}, "geometry": {"coordinates": [63.071, 57.67052], "type": "Point"}, "type": "feature"}]}