{"type": "FeatureCollection", "features": [{"type": "Feature", "geometry": {"coordinates": [39.52999, 53.31524], "type": "Point"}, "properties": {"countryCode": "RU", "countryId": "2017370", "fcodeName": "populated place", "adminName1": "Lipetsk", "fclName": "city, village,...", "fcl": "P", "countryName": "Russia", "fcode": "PPL", "geonameId": 531622, "population": 0, "adminCode1": "43", "name": "Malaya Karpovka", "toponymName": "Malaya Karpovka"}}, {"type": "Feature", "geometry": {"coordinates": [39.50564, 53.30268], "type": "Point"}, "properties": {"countryCode": "RU", "countryId": "2017370", "fcodeName": "populated place", "adminName1": "Lipetsk", "fclName": "city, village,...", "fcl": "P", "countryName": "Russia", "fcode": "PPL", "geonameId": 575042, "population": 0, "adminCode1": "43", "name": "Bol\u2019shaya Karpovka", "toponymName": "Bol\u2019shaya Karpovka"}}, {"type": "Feature", "geometry": {"coordinates": [41.4148, 55.7497], "type": "Point"}, "properties": {"countryCode": "RU", "countryId": "2017370", "fcodeName": "populated place", "adminName1": "Vladimir", "fclName": "city, village,...", "fcl": "P", "countryName": "Russia", "fcode": "PPL", "geonameId": 552226, "population": 0, "adminCode1": "83", "name": "Karpovo", "toponymName": "Karpovo"}}]}