{"type": "FeatureCollection", "features": [{"properties": {"countryId": "2017370", "toponymName": "Malaya Karpovka", "adminCode1": "43", "geonameId": 531622, "fcl": "P", "name": "Malaya Karpovka", "countryName": "Russia", "fclName": "city, village,...", "fcode": "PPL", "adminName1": "Lipetsk", "countryCode": "RU", "population": 0, "fcodeName": "populated place"}, "geometry": {"coordinates": [39.52999, 53.31524], "type": "Point"}, "type": "feature"}, {"properties": {"countryId": "2017370", "toponymName": "Bol\u2019shaya Karpovka", "adminCode1": "43", "geonameId": 575042, "fcl": "P", "name": "Bol\u2019shaya Karpovka", "countryName": "Russia", "fclName": "city, village,...", "fcode": "PPL", "adminName1": "Lipetsk", "countryCode": "RU", "population": 0, "fcodeName": "populated place"}, "geometry": {"coordinates": [39.50564, 53.30268], "type": "Point"}, "type": "feature"}, {"properties": {"countryId": "2017370", "toponymName": "Karpovo", "adminCode1": "83", "geonameId": 552226, "fcl": "P", "name": "Karpovo", "countryName": "Russia", "fclName": "city, village,...", "fcode": "PPL", "adminName1": "Vladimir", "countryCode": "RU", "population": 0, "fcodeName": "populated place"}, "geometry": {"coordinates": [41.4148, 55.7497], "type": "Point"}, "type": "feature"}]}