{"type": "FeatureCollection", "features": [{"properties": {"countryId": "2017370", "toponymName": "Vadinsk", "adminCode1": "57", "geonameId": 477418, "fcl": "P", "name": "Vadinsk", "countryName": "Russia", "fclName": "city, village,...", "fcode": "PPL", "adminName1": "Penza", "countryCode": "RU", "population": 4708, "fcodeName": "populated place"}, "geometry": {"coordinates": [43.05744, 53.69157], "type": "Point"}, "type": "feature"}]}