{"features": [{"type": "Feature", "geometry": {"coordinates": [43.05744, 53.69157], "type": "Point"}, "properties": {"hgr_name_modern_sp": "\u041a\u0435\u0440\u0435\u043d\u0441\u043a", "hgr_uezd_stem": "\u043d\u043e\u0442_\u0438\u043d_\u0442\u0435x\u0442", "hgr_admin_hierarchy": "\u043f\u0435\u043d\u0437\u0435\u043d\u0441\u043a", "hgr_admin1_partof": 22.0, "toponymName": "Vadinsk", "hgr_html_text": "\u041a\u0415\u0420\u0415\u041d\u0421\u041a\u042a, </span><span class=\"font0\" style=\"font-style:italic;\">\u0433\u043e\u0440\u043e\u0434\u044a</span><span class=\"font0\"> \u041f\u0435\u043d\u0437\u0435\u043d\u0441\u043a\u0430\u0433\u043e \u041d\u0430\u043c\u0463\u0441\u0442\u043d\u0438\u0447\u0435\u0441\u0442\u0432\u0430. \u0412\u044a \u043e\u043d\u043e\u043c\u044a \u0431\u044b\u0432\u0430\u044e\u0442\u044a \u0434\u0432\u0463 \u044f\u0440\u043c\u0430\u0440\u043a\u0438 \u0432\u044a \u0433\u043e\u0434\u0443: \u043f\u0435\u0440\u0432\u0430\u044f \u0432\u044a \u0406\u044e\u043d\u0463, \u0430 \u0434\u0440\u0443\u0433\u0430\u044f \u0432\u044a \u0406\u044e\u043b\u0463 \u043c\u0463\u0441\u044f\u0446\u0430\u0445\u044a, \u0438 \u043f\u0440\u043e\u0434\u043e\u043b\u0436\u0430\u044e\u0442\u0441\u044f , \u043f\u0435\u0440\u0432\u0430\u044f \u0434\u0435\u043d\u044c , \u0430 \u0434\u0440\u0443\u0433\u0430\u044f \u0434\u0432\u0430, \u0441\u0432\u0435\u0440\u0445\u044a \u043a\u0430\u0436\u0434\u043e\u043d\u0435\u0434\u0463\u043b\u044c\u043d\u044b\u0445\u044a \u0442\u043e\u0440\u0433\u043e\u0432\u044a. \u041a\u0443\u043f\u0446\u044b \u043d\u0430 \u043e\u043d\u044b\u044f \u043f\u0440\u0456\u0463-</span>\u0437\u0436\u0430\u044e\u0442\u044a \u041a\u0430\u0434\u043e\u043c\u043e\u043d\u0441\u043a\u0456\u0435 , \u041a\u0430\u0441\u0438\u043c\u043e\u0432\u0441\u043a\u0456\u0435 \u0438 \u0410\u0440\u0441\u0430\u043c\u0430\u0437\u0441\u043a\u0456\u0435 \u0441\u044a \u0440\u0430\u0437\u043d\u044b\u043c\u0438 \u043c\u0463\u043b\u043e\u0447\u043d\u044b\u043c\u0438 \u0442\u043e\u0432\u0430\u0440\u0430\u043c\u0438.", "adminCode1": "57", "fcodeName": "populated place", "fcode": "PPL", "hgr_partof_id": 22.0, "hgr_page": 53, "countryName": "Russia", "hgr_text": "\u041a\u0415\u0420\u0415\u041d\u0421\u041a\u042a, \u0433\u043e\u0440\u043e\u0434\u044a \u041f\u0435\u043d\u0437\u0435\u043d\u0441\u043a\u0430\u0433\u043e \u041d\u0430\u043c\u0463\u0441\u0442\u043d\u0438\u0447\u0435\u0441\u0442\u0432\u0430. \u0412\u044a \u043e\u043d\u043e\u043c\u044a \u0431\u044b\u0432\u0430\u044e\u0442\u044a \u0434\u0432\u0463 \u044f\u0440\u043c\u0430\u0440\u043a\u0438 \u0432\u044a \u0433\u043e\u0434\u0443: \u043f\u0435\u0440\u0432\u0430\u044f \u0432\u044a \u0406\u044e\u043d\u0463, \u0430 \u0434\u0440\u0443\u0433\u0430\u044f \u0432\u044a \u0406\u044e\u043b\u0463 \u043c\u0463\u0441\u044f\u0446\u0430\u0445\u044a, \u0438 \u043f\u0440\u043e\u0434\u043e\u043b\u0436\u0430\u044e\u0442\u0441\u044f , \u043f\u0435\u0440\u0432\u0430\u044f \u0434\u0435\u043d\u044c , \u0430 \u0434\u0440\u0443\u0433\u0430\u044f \u0434\u0432\u0430, \u0441\u0432\u0435\u0440\u0445\u044a \u043a\u0430\u0436\u0434\u043e\u043d\u0435\u0434\u0463\u043b\u044c\u043d\u044b\u0445\u044a \u0442\u043e\u0440\u0433\u043e\u0432\u044a. \u041a\u0443\u043f\u0446\u044b \u043d\u0430 \u043e\u043d\u044b\u044f \u043f\u0440\u0456\u0463-\u0437\u0436\u0430\u044e\u0442\u044a \u041a\u0430\u0434\u043e\u043c\u043e\u043d\u0441\u043a\u0456\u0435 , \u041a\u0430\u0441\u0438\u043c\u043e\u0432\u0441\u043a\u0456\u0435 \u0438 \u0410\u0440\u0441\u0430\u043c\u0430\u0437\u0441\u043a\u0456\u0435 \u0441\u044a \u0440\u0430\u0437\u043d\u044b\u043c\u0438 \u043c\u0463\u043b\u043e\u0447\u043d\u044b\u043c\u0438 \u0442\u043e\u0432\u0430\u0440\u0430\u043c\u0438.", "hgr_prov_modern_sp": "\u041f\u0435\u043d\u0437\u0435\u043d\u0441\u043a\u043e\u0433\u043e \u041d\u0430\u043c\u0435\u0441\u0442\u043d\u0438\u0447\u0435\u0441\u0442\u0432\u0430", "hgr_name": "\u041a\u0435\u0440\u0435\u043d\u0441\u043a\u044a", "name": "Vadinsk", "hgr_ru_uezd": "not_in_text", "population": 4708, "countryId": "2017370", "hgr_ru_prov": "\u041f\u0435\u043d\u0437\u0435\u043d\u0441\u043a\u0430\u0433\u043e \u041d\u0430\u043c\u0463\u0441\u0442\u043d\u0438\u0447\u0435\u0441\u0442\u0432\u0430", "hgr_source_url": "http://babel.hathitrust.org/cgi/pt?id=uc1.b4583201;view=1up;seq=52", "fcl": "P", "hgr_alt_name": null, "adminName1": "Penza", "hgr_admin2_partof": null, "hgr_prov_stem": "\u043f\u0435\u043d\u0437\u0435\u043d\u0441\u043a", "fclName": "city, village,...", "countryCode": "RU", "geonameId": 477418, "hgr_type": "\u0433\u043e\u0440\u043e\u0434\u044a", "hgr_uezd_modern_sp": "not_\u0438n_text"}}], "type": "FeatureCollection"}