{"features": [{"properties": {"fcl": "P", "geonameId": 477418, "countryId": "2017370", "fcode": "PPL", "name": "Vadinsk", "countryName": "Russia", "population": 4708, "fclName": "city, village,...", "adminName1": "Penza", "adminCode1": "57", "fcodeName": "populated place", "countryCode": "RU", "toponymName": "Vadinsk"}, "geometry": {"coordinates": [43.05744, 53.69157], "type": "Point"}, "type": "Feature"}], "type": "FeatureCollection"}