{"type": "FeatureCollection", "features": [{"type": "Feature", "geometry": {"coordinates": [43.05744, 53.69157], "type": "Point"}, "properties": {"countryCode": "RU", "countryId": "2017370", "fcodeName": "populated place", "adminName1": "Penza", "fclName": "city, village,...", "fcl": "P", "countryName": "Russia", "fcode": "PPL", "geonameId": 477418, "population": 4708, "adminCode1": "57", "name": "Vadinsk", "toponymName": "Vadinsk"}}]}