{"type": "FeatureCollection", "features": [{"type": "Feature", "geometry": {"coordinates": [48.348, 58.3089], "type": "Point"}, "properties": {"countryCode": "RU", "countryId": "2017370", "fcodeName": "populated place", "adminName1": "Kirov", "fclName": "city, village,...", "fcl": "P", "countryName": "Russia", "fcode": "PPL", "geonameId": 543737, "population": 27600, "adminCode1": "33", "name": "Kotel'nich", "toponymName": "Kotel\u2019nich"}}]}