{"features": [{"properties": {"hgr_name_modern_sp": "\u041a\u043e\u0442\u0435\u043b\u044c\u043d\u0438\u0447\u044c", "countryCode": "RU", "hgr_admin_hierarchy": "\u0432\u044f\u0442\u0441\u043a", "fcl": "P", "toponymName": "Kotel\u2019nich", "countryName": "Russia", "adminCode1": "33", "fcodeName": "populated place", "population": 27600, "hgr_partof_id": 7.0, "hgr_page": 60, "hgr_html_text": "\u041a\u041e\u0422\u0415\u041b\u042c\u041d\u0418\u0427\u042c, </span><span class=\"font0\" style=\"font-style:italic;\">\u0433\u043e\u0440\u043e\u0434\u044a</span><span class=\"font0\"> \u0412\u044f\u0442\u0441\u043a\u0430\u0433\u043e \u041d\u0430\u043c\u0463\u0441\u0442\u043d\u0438\u0447\u0435\u0441\u0442\u0432\u0430. \u0412\u044a \u0441\u0435\u043c\u044a \u0433\u043e\u0440\u043e\u0434\u0463 \u0431\u044b\u0432\u0430\u0435\u0442\u044a \u043e\u0434\u043d\u0430 \u0432\u044a \u0433\u043e\u0434\u0443 \u044f\u0440\u043c\u0430\u0440\u043a\u0430.</span>", "UPDATE_SCRIPT": "python add_town_by_geoname_id.py \u041a\u043e\u0442\u0435\u043b\u044c\u043d\u0438\u0447\u044c_332.geojson 543737", "hgr_text": "\u041a\u041e\u0422\u0415\u041b\u042c\u041d\u0418\u0427\u042c, \u0433\u043e\u0440\u043e\u0434\u044a \u0412\u044f\u0442\u0441\u043a\u0430\u0433\u043e \u041d\u0430\u043c\u0463\u0441\u0442\u043d\u0438\u0447\u0435\u0441\u0442\u0432\u0430. \u0412\u044a \u0441\u0435\u043c\u044a \u0433\u043e\u0440\u043e\u0434\u0463 \u0431\u044b\u0432\u0430\u0435\u0442\u044a \u043e\u0434\u043d\u0430 \u0432\u044a \u0433\u043e\u0434\u0443 \u044f\u0440\u043c\u0430\u0440\u043a\u0430.", "hgr_prov_modern_sp": "\u0412\u044f\u0442\u0441\u043a\u043e\u0433\u043e \u041d\u0430\u043c\u0435\u0441\u0442\u043d\u0438\u0447\u0435\u0441\u0442\u0432\u0430", "hgr_name": "\u041a\u043e\u0442\u0435\u043b\u044c\u043d\u0438\u0447\u044c", "name": "Kotel'nich", "hgr_ru_uezd": "not_in_text", "hgr_source_url": "http://babel.hathitrust.org/cgi/pt?id=uc1.b4583201;view=1up;seq=59", "countryId": "2017370", "hgr_ru_prov": "\u0412\u044f\u0442\u0441\u043a\u0430\u0433\u043e \u041d\u0430\u043c\u0463\u0441\u0442\u043d\u0438\u0447\u0435\u0441\u0442\u0432\u0430", "hgr_uezd_stem": "\u043d\u043e\u0442_\u0438\u043d_\u0442\u0435x\u0442", "hgr_admin1_partof": 7.0, "hgr_alt_name": null, "adminName1": "Kirov", "hgr_admin2_partof": null, "fcode": "PPL", "fclName": "city, village,...", "hgr_prov_stem": "\u0432\u044f\u0442\u0441\u043a", "geonameId": 543737, "hgr_type": "\u0433\u043e\u0440\u043e\u0434\u044a", "hgr_uezd_modern_sp": "not_\u0438n_text"}, "geometry": {"coordinates": [48.348, 58.3089], "type": "Point"}, "type": "Feature"}], "type": "FeatureCollection"}