{"type": "FeatureCollection", "features": [{"properties": {"countryId": "2017370", "toponymName": "Kotel\u2019nich", "adminCode1": "33", "geonameId": 543737, "fcl": "P", "name": "Kotel'nich", "countryName": "Russia", "fclName": "city, village,...", "fcode": "PPL", "adminName1": "Kirov", "countryCode": "RU", "population": 27600, "fcodeName": "populated place"}, "geometry": {"coordinates": [48.348, 58.3089], "type": "Point"}, "type": "feature"}]}