{"type": "FeatureCollection", "features": [{"properties": {"countryId": "690791", "toponymName": "Svitlovods\u2019k", "adminCode1": "10", "geonameId": 692087, "fcl": "P", "name": "Svitlovods'k", "countryName": "Ukraine", "fclName": "city, village,...", "fcode": "PPL", "adminName1": "Kirovohrad", "countryCode": "UA", "population": 47946, "fcodeName": "populated place"}, "geometry": {"coordinates": [33.24106, 49.04894], "type": "Point"}, "type": "feature"}]}