{"features": [{"properties": {"fcl": "P", "geonameId": 692087, "countryId": "690791", "fcode": "PPL", "name": "Svitlovods'k", "countryName": "Ukraine", "population": 47946, "fclName": "city, village,...", "adminName1": "Kirovohrad", "adminCode1": "10", "fcodeName": "populated place", "countryCode": "UA", "toponymName": "Svitlovods\u2019k"}, "geometry": {"coordinates": [33.24106, 49.04894], "type": "Point"}, "type": "Feature"}], "type": "FeatureCollection"}