{"features": [{"geometry": {"coordinates": [33.24106, 49.04894], "type": "Point"}, "properties": {"UPDATE_SCRIPT": "python add_town_by_geoname_id.py \u041a\u0440\u044b\u043b\u043e\u0432_356.geojson 692087", "adminCode1": "10", "adminName1": "Kirovohrad", "countryCode": "UA", "countryId": "690791", "countryName": "Ukraine", "fcl": "P", "fclName": "city, village,...", "fcode": "PPL", "fcodeName": "populated place", "geonameId": 692087, "hgr_admin1_partof": 8.0, "hgr_admin2_partof": null, "hgr_admin_hierarchy": "\u0435\u043a\u0430\u0442\u0435\u0440\u0438\u043d\u043e\u0441\u043b\u0430\u0432\u0441\u043a", "hgr_alt_name": null, "hgr_html_text": "\u041a\u0420\u042b\u041b\u041e\u0412\u042a, </span><span class=\"font0\" style=\"font-style:italic;\">\u0441\u043b\u043e\u0431\u043e\u0434\u0430</span><span class=\"font0\"> \u0415\u043a\u0430\u0442\u0435\u0440\u0438\u043d\u043e\u0441\u043b\u0430\u0432\u0441\u043a\u0430\u0433\u043e \u041d\u0430\u043c\u0463\u0441\u0442\u043d\u0438\u0447\u0435\u0441\u0442\u0432\u0430</span>\u0412\u044a \u043e\u043d\u043e\u0439 \u0431\u044b\u0432\u0430\u0435\u0442\u044a \u0432\u044a \u0433\u043e\u0434\u0443 \u0434\u0435\u0432\u044f\u0442\u044c \u044f\u0440\u043c\u0430\u0440\u043e\u043a\u044a.", "hgr_name": "\u041a\u0440\u044b\u043b\u043e\u0432\u044a", "hgr_name_modern_sp": "\u041a\u0440\u044b\u043b\u043e\u0432", "hgr_page": 63, "hgr_partof_id": 8.0, "hgr_prov_modern_sp": "\u0415\u043a\u0430\u0442\u0435\u0440\u0438\u043d\u043e\u0441\u043b\u0430\u0432\u0441\u043a\u043e\u0433\u043e \u041d\u0430\u043c\u0435\u0441\u0442\u043d\u0438\u0447\u0435\u0441\u0442\u0432\u0430", "hgr_prov_stem": "\u0435\u043a\u0430\u0442\u0435\u0440\u0438\u043d\u043e\u0441\u043b\u0430\u0432\u0441\u043a", "hgr_ru_prov": "\u0415\u043a\u0430\u0442\u0435\u0440\u0438\u043d\u043e\u0441\u043b\u0430\u0432\u0441\u043a\u0430\u0433\u043e \u041d\u0430\u043c\u0463\u0441\u0442\u043d\u0438\u0447\u0435\u0441\u0442\u0432\u0430", "hgr_ru_uezd": "not_in_text", "hgr_source_url": "http://babel.hathitrust.org/cgi/pt?id=uc1.b4583201;view=1up;seq=62", "hgr_text": "\u041a\u0420\u042b\u041b\u041e\u0412\u042a, \u0441\u043b\u043e\u0431\u043e\u0434\u0430 \u0415\u043a\u0430\u0442\u0435\u0440\u0438\u043d\u043e\u0441\u043b\u0430\u0432\u0441\u043a\u0430\u0433\u043e \u041d\u0430\u043c\u0463\u0441\u0442\u043d\u0438\u0447\u0435\u0441\u0442\u0432\u0430\u0412\u044a \u043e\u043d\u043e\u0439 \u0431\u044b\u0432\u0430\u0435\u0442\u044a \u0432\u044a \u0433\u043e\u0434\u0443 \u0434\u0435\u0432\u044f\u0442\u044c \u044f\u0440\u043c\u0430\u0440\u043e\u043a\u044a.", "hgr_type": "\u0441\u043b\u043e\u0431\u043e\u0434\u0430", "hgr_uezd_modern_sp": "not_\u0438n_text", "hgr_uezd_stem": "\u043d\u043e\u0442_\u0438\u043d_\u0442\u0435x\u0442", "name": "Svitlovods'k", "population": 47946, "toponymName": "Svitlovods\u2019k"}, "type": "Feature"}], "type": "FeatureCollection"}