{"type": "FeatureCollection", "features": [{"type": "Feature", "geometry": {"coordinates": [33.24106, 49.04894], "type": "Point"}, "properties": {"countryCode": "UA", "countryId": "690791", "fcodeName": "populated place", "adminName1": "Kirovohrad", "fclName": "city, village,...", "fcl": "P", "countryName": "Ukraine", "fcode": "PPL", "geonameId": 692087, "population": 47946, "adminCode1": "10", "name": "Svitlovods'k", "toponymName": "Svitlovods\u2019k"}}]}