{"type": "FeatureCollection", "features": [{"type": "Feature", "geometry": {"coordinates": [32.74462, 50.21186], "type": "Point"}, "properties": {"countryCode": "UA", "countryId": "690791", "fcodeName": "populated place", "adminName1": "Poltava", "fclName": "city, village,...", "fcl": "P", "countryName": "Ukraine", "fcode": "PPL", "geonameId": 703624, "population": 0, "adminCode1": "18", "name": "Kuren'ka", "toponymName": "Kurin\u2019ka"}}]}