{"type": "FeatureCollection", "features": [{"properties": {"countryId": "690791", "toponymName": "Kurin\u2019ka", "adminCode1": "18", "geonameId": 703624, "fcl": "P", "name": "Kuren'ka", "countryName": "Ukraine", "fclName": "city, village,...", "fcode": "PPL", "adminName1": "Poltava", "countryCode": "UA", "population": 0, "fcodeName": "populated place"}, "geometry": {"coordinates": [32.74462, 50.21186], "type": "Point"}, "type": "feature"}]}