{"features": [{"properties": {"hgr_name_modern_sp": "\u041a\u0443\u0440\u0435\u043d\u044c\u043a\u0438", "countryCode": "UA", "hgr_admin_hierarchy": "\u043a\u0438\u0435\u0432\u0441\u043a|\u043b\u0443\u0431\u0435\u043d\u0441\u043a", "fcl": "P", "toponymName": "Kurin\u2019ka", "countryName": "Ukraine", "adminCode1": "18", "fcodeName": "populated place", "population": 0, "hgr_partof_id": 88.0, "hgr_page": 64, "hgr_html_text": "\u041a\u0423\u0420\u0415\u041d\u042c\u041a\u0418, </span><span class=\"font0\" style=\"font-style:italic;\">\u043c\u0463\u0441\u0442\u0435\u0447\u043a\u043e</span><span class=\"font0\"> \u041a\u0456\u0435\u0432\u0441\u043a\u0430\u0433\u043e \u041d\u0430\u043c\u0463\u0441\u0442\u043d\u0438\u0447\u0435\u0441\u0442\u0432\u0430 \u0432\u044a \u041b\u0443\u0431\u0435\u043d\u0441\u043a\u043e\u043c\u044a \u0443\u0463\u0437\u0434\u0463. \u0417\u0434\u0463\u0441\u044c \u0431\u044b\u0432\u0430-</span>\u0435\u0442\u044a \u0432\u044a \u0433\u043e\u0434\u044a \u0442\u0440\u0438 \u044f\u0440\u043c\u0430\u0440\u043a\u0438: \u043f\u0435\u0440\u0432\u0430\u044f \u0424\u0435\u0432\u0440\u0430\u043b\u044f 2, \u0434\u0440\u0443\u0433\u0430\u044f \u0406\u044e\u043d\u044f 29, \u0442\u0440\u0435\u0442\u0456\u044f \u041e\u043a\u0442\u044f\u0431\u0440\u044f 26 \u0447\u0438\u0441\u0435\u043b\u044a.", "UPDATE_SCRIPT": "python add_town_by_geoname_id.py \u041a\u0443\u0440\u0435\u043d\u044c\u043a\u0438_365.geojson 703624", "hgr_text": "\u041a\u0423\u0420\u0415\u041d\u042c\u041a\u0418, \u043c\u0463\u0441\u0442\u0435\u0447\u043a\u043e \u041a\u0456\u0435\u0432\u0441\u043a\u0430\u0433\u043e \u041d\u0430\u043c\u0463\u0441\u0442\u043d\u0438\u0447\u0435\u0441\u0442\u0432\u0430 \u0432\u044a \u041b\u0443\u0431\u0435\u043d\u0441\u043a\u043e\u043c\u044a \u0443\u0463\u0437\u0434\u0463. \u0417\u0434\u0463\u0441\u044c \u0431\u044b\u0432\u0430-\u0435\u0442\u044a \u0432\u044a \u0433\u043e\u0434\u044a \u0442\u0440\u0438 \u044f\u0440\u043c\u0430\u0440\u043a\u0438: \u043f\u0435\u0440\u0432\u0430\u044f \u0424\u0435\u0432\u0440\u0430\u043b\u044f 2, \u0434\u0440\u0443\u0433\u0430\u044f \u0406\u044e\u043d\u044f 29, \u0442\u0440\u0435\u0442\u0456\u044f \u041e\u043a\u0442\u044f\u0431\u0440\u044f 26 \u0447\u0438\u0441\u0435\u043b\u044a.", "hgr_prov_modern_sp": "\u041a\u0438\u0435\u0432\u0441\u043a\u043e\u0433\u043e \u041d\u0430\u043c\u0435\u0441\u0442\u043d\u0438\u0447\u0435\u0441\u0442\u0432\u0430", "hgr_name": "\u041a\u0443\u0440\u0435\u043d\u044c\u043a\u0438", "name": "Kuren'ka", "hgr_ru_uezd": "\u041b\u0443\u0431\u0435\u043d\u0441\u043a\u043e\u043c\u044a \u0443\u0463\u0437\u0434\u0463", "hgr_source_url": "http://babel.hathitrust.org/cgi/pt?id=uc1.b4583201;view=1up;seq=63", "countryId": "690791", "hgr_ru_prov": "\u041a\u0456\u0435\u0432\u0441\u043a\u0430\u0433\u043e \u041d\u0430\u043c\u0463\u0441\u0442\u043d\u0438\u0447\u0435\u0441\u0442\u0432\u0430", "hgr_uezd_stem": "\u043b\u0443\u0431\u0435\u043d\u0441\u043a", "hgr_admin1_partof": 13.0, "hgr_alt_name": null, "adminName1": "Poltava", "hgr_admin2_partof": 88.0, "fcode": "PPL", "fclName": "city, village,...", "hgr_prov_stem": "\u043a\u0438\u0435\u0432\u0441\u043a", "geonameId": 703624, "hgr_type": "\u043c\u0463\u0441\u0442\u0435\u0447\u043a\u043e", "hgr_uezd_modern_sp": "\u041b\u0443\u0431\u0435\u043d\u0441\u043a\u043e\u043c \u0443\u0435\u0437\u0434\u0435"}, "geometry": {"coordinates": [32.74462, 50.21186], "type": "Point"}, "type": "Feature"}], "type": "FeatureCollection"}