{"type": "FeatureCollection", "features": [{"type": "Feature", "geometry": {"coordinates": [39.16639, 53.01942], "type": "Point"}, "properties": {"countryCode": "RU", "countryId": "2017370", "fcodeName": "populated place", "adminName1": "Lipetsk", "fclName": "city, village,...", "fcl": "P", "countryName": "Russia", "fcode": "PPL", "geonameId": 536518, "population": 22970, "adminCode1": "43", "name": "Lebedyan'", "toponymName": "Lebedyan\u2019"}}, {"type": "Feature", "geometry": {"coordinates": [41.18443, 52.1461], "type": "Point"}, "properties": {"countryCode": "RU", "countryId": "2017370", "fcodeName": "populated place", "adminName1": "Tambov", "fclName": "city, village,...", "fcl": "P", "countryName": "Russia", "fcode": "PPL", "geonameId": 555541, "population": 0, "adminCode1": "72", "name": "Ivano-Lebedyan\u2019", "toponymName": "Ivano-Lebedyan\u2019"}}]}