{"type": "FeatureCollection", "features": [{"properties": {"countryId": "2017370", "toponymName": "Lebedyan\u2019", "adminCode1": "43", "geonameId": 536518, "fcl": "P", "name": "Lebedyan'", "countryName": "Russia", "fclName": "city, village,...", "fcode": "PPL", "adminName1": "Lipetsk", "countryCode": "RU", "population": 22970, "fcodeName": "populated place"}, "geometry": {"coordinates": [39.16639, 53.01942], "type": "Point"}, "type": "feature"}, {"properties": {"countryId": "2017370", "toponymName": "Ivano-Lebedyan\u2019", "adminCode1": "72", "geonameId": 555541, "fcl": "P", "name": "Ivano-Lebedyan\u2019", "countryName": "Russia", "fclName": "city, village,...", "fcode": "PPL", "adminName1": "Tambov", "countryCode": "RU", "population": 0, "fcodeName": "populated place"}, "geometry": {"coordinates": [41.18443, 52.1461], "type": "Point"}, "type": "feature"}]}