{"type": "FeatureCollection", "features": [{"type": "Feature", "geometry": {"coordinates": [29.6975, 56.8842], "type": "Point"}, "properties": {"countryCode": "RU", "countryId": "2017370", "fcodeName": "populated place", "adminName1": "Pskov", "fclName": "city, village,...", "fcl": "P", "countryName": "Russia", "fcode": "PPL", "geonameId": 7597550, "population": 0, "adminCode1": "60", "name": "Liptsy", "toponymName": "Liptsy"}}, {"type": "Feature", "geometry": {"coordinates": [34.85787, 55.73716], "type": "Point"}, "properties": {"countryCode": "RU", "countryId": "2017370", "fcodeName": "populated place", "adminName1": "Smolensk", "fclName": "city, village,...", "fcl": "P", "countryName": "Russia", "fcode": "PPL", "geonameId": 534911, "population": 0, "adminCode1": "69", "name": "Liptsy", "toponymName": "Liptsy"}}, {"type": "Feature", "geometry": {"coordinates": [36.40774, 50.20366], "type": "Point"}, "properties": {"countryCode": "UA", "countryId": "690791", "fcodeName": "populated place", "adminName1": "Kharkiv", "fclName": "city, village,...", "fcl": "P", "countryName": "Ukraine", "fcode": "PPL", "geonameId": 702989, "population": 0, "adminCode1": "07", "name": "Liptsy", "toponymName": "Lyptsi"}}, {"type": "Feature", "geometry": {"coordinates": [35.3943, 50.8673], "type": "Point"}, "properties": {"countryCode": "RU", "countryId": "2017370", "fcodeName": "populated place", "adminName1": "Belgorod", "fclName": "city, village,...", "fcl": "P", "countryName": "Russia", "fcode": "PPL", "geonameId": 7687444, "population": 0, "adminCode1": "09", "name": "Liptsy", "toponymName": "Liptsy"}}]}