{"type": "FeatureCollection", "features": [{"properties": {"countryId": "2017370", "toponymName": "Liptsy", "adminCode1": "60", "geonameId": 7597550, "fcl": "P", "name": "Liptsy", "countryName": "Russia", "fclName": "city, village,...", "fcode": "PPL", "adminName1": "Pskov", "countryCode": "RU", "population": 0, "fcodeName": "populated place"}, "geometry": {"coordinates": [29.6975, 56.8842], "type": "Point"}, "type": "feature"}, {"properties": {"countryId": "2017370", "toponymName": "Liptsy", "adminCode1": "69", "geonameId": 534911, "fcl": "P", "name": "Liptsy", "countryName": "Russia", "fclName": "city, village,...", "fcode": "PPL", "adminName1": "Smolensk", "countryCode": "RU", "population": 0, "fcodeName": "populated place"}, "geometry": {"coordinates": [34.85787, 55.73716], "type": "Point"}, "type": "feature"}, {"properties": {"countryId": "690791", "toponymName": "Lyptsi", "adminCode1": "07", "geonameId": 702989, "fcl": "P", "name": "Liptsy", "countryName": "Ukraine", "fclName": "city, village,...", "fcode": "PPL", "adminName1": "Kharkiv", "countryCode": "UA", "population": 0, "fcodeName": "populated place"}, "geometry": {"coordinates": [36.40774, 50.20366], "type": "Point"}, "type": "feature"}, {"properties": {"countryId": "2017370", "toponymName": "Liptsy", "adminCode1": "09", "geonameId": 7687444, "fcl": "P", "name": "Liptsy", "countryName": "Russia", "fclName": "city, village,...", "fcode": "PPL", "adminName1": "Belgorod", "countryCode": "RU", "population": 0, "fcodeName": "populated place"}, "geometry": {"coordinates": [35.3943, 50.8673], "type": "Point"}, "type": "feature"}]}