{"type": "FeatureCollection", "features": [{"properties": {"countryId": "690791", "toponymName": "Lokhvytsya", "adminCode1": "18", "geonameId": 702874, "fcl": "P", "name": "Lokhvytsya", "countryName": "Ukraine", "fclName": "city, village,...", "fcode": "PPL", "adminName1": "Poltava", "countryCode": "UA", "population": 11950, "fcodeName": "populated place"}, "geometry": {"coordinates": [33.26024, 50.36776], "type": "Point"}, "type": "feature"}]}