{"type": "FeatureCollection", "features": [{"type": "Feature", "geometry": {"coordinates": [33.26024, 50.36776], "type": "Point"}, "properties": {"countryCode": "UA", "countryId": "690791", "fcodeName": "populated place", "adminName1": "Poltava", "fclName": "city, village,...", "fcl": "P", "countryName": "Ukraine", "fcode": "PPL", "geonameId": 702874, "population": 11950, "adminCode1": "18", "name": "Lokhvytsya", "toponymName": "Lokhvytsya"}}]}