{"type": "FeatureCollection", "features": [{"properties": {"countryId": "2017370", "toponymName": "Makhonovo", "adminCode1": "43", "geonameId": 532067, "fcl": "P", "name": "Makhonovo", "countryName": "Russia", "fclName": "city, village,...", "fcode": "PPL", "adminName1": "Lipetsk", "countryCode": "RU", "population": 0, "fcodeName": "populated place"}, "geometry": {"coordinates": [39.7671, 52.90838], "type": "Point"}, "type": "feature"}]}