{"type": "FeatureCollection", "features": [{"type": "Feature", "geometry": {"coordinates": [39.7671, 52.90838], "type": "Point"}, "properties": {"countryCode": "RU", "countryId": "2017370", "fcodeName": "populated place", "adminName1": "Lipetsk", "fclName": "city, village,...", "fcl": "P", "countryName": "Russia", "fcode": "PPL", "geonameId": 532067, "population": 0, "adminCode1": "43", "name": "Makhonovo", "toponymName": "Makhonovo"}}]}