{"features": [{"type": "Feature", "geometry": {"coordinates": [39.7671, 52.90838], "type": "Point"}, "properties": {"hgr_name_modern_sp": "\u041c\u0430\u0445\u043e\u043d\u043e\u0432\u043e", "hgr_uezd_stem": "\u043d\u043e\u0442_\u0438\u043d_\u0442\u0435x\u0442", "hgr_admin_hierarchy": "\u0442\u0430\u043c\u0431\u043e\u0432\u0441\u043a", "hgr_admin1_partof": 32.0, "toponymName": "Makhonovo", "hgr_html_text": "\u041c\u0410\u0425\u041e\u041d\u041e\u0412\u041e , </span><span class=\"font0\" style=\"font-style:italic;\">\u0441\u0435\u043b\u043e</span><span class=\"font0\"> \u0422\u0430\u043c\u0431\u043e\u0432\u0441\u043a\u0430\u0433\u043e \u041d\u0430\u043c\u0463\u0441\u0442\u043d\u0438\u0447\u0435\u0441\u0442\u0432\u0430 \u043e\u043a\u043e\u043b\u043e \u0433\u043e\u0440\u043e\u0434\u043a\u0430 \u0414\u043e\u0431\u0440\u0430\u0433\u043e. \u0417\u0434\u0463\u0441\u044c \u0431\u044b\u0432\u0430\u0435\u0442\u044a \u0432\u044a \u0433\u043e\u0434\u0443 \u044f\u0440\u043c\u0430\u0440\u043a\u0430 29 \u0410\u0432\u0433\u0443\u0441\u0442\u0430 ; \u043d\u0430 \u043e\u043d\u0443\u044e \u043f\u0440\u0456\u0463\u0437\u0436\u0430\u044e\u0442\u044a \u043a\u0443\u043f\u0446\u044b \u0441\u044a \u043c\u0463\u043b\u043e\u0447\u043d\u044b\u043c\u0438 \u0442\u043e\u0432\u0430\u0440\u0430\u043c\u0438.</span>", "adminCode1": "43", "fcodeName": "populated place", "fcode": "PPL", "hgr_partof_id": 32.0, "hgr_page": 72, "countryName": "Russia", "hgr_text": "\u041c\u0410\u0425\u041e\u041d\u041e\u0412\u041e , \u0441\u0435\u043b\u043e \u0422\u0430\u043c\u0431\u043e\u0432\u0441\u043a\u0430\u0433\u043e \u041d\u0430\u043c\u0463\u0441\u0442\u043d\u0438\u0447\u0435\u0441\u0442\u0432\u0430 \u043e\u043a\u043e\u043b\u043e \u0433\u043e\u0440\u043e\u0434\u043a\u0430 \u0414\u043e\u0431\u0440\u0430\u0433\u043e. \u0417\u0434\u0463\u0441\u044c \u0431\u044b\u0432\u0430\u0435\u0442\u044a \u0432\u044a \u0433\u043e\u0434\u0443 \u044f\u0440\u043c\u0430\u0440\u043a\u0430 29 \u0410\u0432\u0433\u0443\u0441\u0442\u0430 ; \u043d\u0430 \u043e\u043d\u0443\u044e \u043f\u0440\u0456\u0463\u0437\u0436\u0430\u044e\u0442\u044a \u043a\u0443\u043f\u0446\u044b \u0441\u044a \u043c\u0463\u043b\u043e\u0447\u043d\u044b\u043c\u0438 \u0442\u043e\u0432\u0430\u0440\u0430\u043c\u0438.", "hgr_prov_modern_sp": "\u0422\u0430\u043c\u0431\u043e\u0432\u0441\u043a\u043e\u0433\u043e \u041d\u0430\u043c\u0435\u0441\u0442\u043d\u0438\u0447\u0435\u0441\u0442\u0432\u0430", "hgr_name": "\u041c\u0430\u0445\u043e\u043d\u043e\u0432\u043e", "name": "Makhonovo", "hgr_ru_uezd": "not_in_text", "population": 0, "countryId": "2017370", "hgr_ru_prov": "\u0422\u0430\u043c\u0431\u043e\u0432\u0441\u043a\u0430\u0433\u043e \u041d\u0430\u043c\u0463\u0441\u0442\u043d\u0438\u0447\u0435\u0441\u0442\u0432\u0430", "hgr_source_url": "http://babel.hathitrust.org/cgi/pt?id=uc1.b4583201;view=1up;seq=71", "fcl": "P", "hgr_alt_name": null, "adminName1": "Lipetsk", "hgr_admin2_partof": null, "hgr_prov_stem": "\u0442\u0430\u043c\u0431\u043e\u0432\u0441\u043a", "fclName": "city, village,...", "countryCode": "RU", "geonameId": 532067, "hgr_type": "\u0441\u0435\u043b\u043e", "hgr_uezd_modern_sp": "not_\u0438n_text"}}], "type": "FeatureCollection"}