{"type": "FeatureCollection", "features": [{"type": "Feature", "geometry": {"coordinates": [32.21568, 51.5217], "type": "Point"}, "properties": {"countryCode": "UA", "countryId": "690791", "fcodeName": "populated place", "adminName1": "Chernihiv", "fclName": "city, village,...", "fcl": "P", "countryName": "Ukraine", "fcode": "PPL", "geonameId": 701372, "population": 12766, "adminCode1": "02", "name": "Mena", "toponymName": "Mena"}}]}