{"type": "FeatureCollection", "features": [{"properties": {"countryId": "690791", "toponymName": "Mena", "adminCode1": "02", "geonameId": 701372, "fcl": "P", "name": "Mena", "countryName": "Ukraine", "fclName": "city, village,...", "fcode": "PPL", "adminName1": "Chernihiv", "countryCode": "UA", "population": 12766, "fcodeName": "populated place"}, "geometry": {"coordinates": [32.21568, 51.5217], "type": "Point"}, "type": "feature"}]}