{"type": "FeatureCollection", "features": [{"type": "Feature", "geometry": {"coordinates": [32.253, 53.6882], "type": "Point"}, "properties": {"countryCode": "BY", "countryId": "630336", "fcodeName": "populated place", "adminName1": "Mahilyowskaya Voblasts\u02bc", "fclName": "city, village,...", "fcl": "P", "countryName": "Belarus", "fcode": "PPL", "geonameId": 625157, "population": 0, "adminCode1": "06", "name": "Miloslavichi", "toponymName": "Milaslavichy"}}]}