{"type": "FeatureCollection", "features": [{"properties": {"countryId": "630336", "toponymName": "Milaslavichy", "adminCode1": "06", "geonameId": 625157, "fcl": "P", "name": "Miloslavichi", "countryName": "Belarus", "fclName": "city, village,...", "fcode": "PPL", "adminName1": "Mahilyowskaya Voblasts\u02bc", "countryCode": "BY", "population": 0, "fcodeName": "populated place"}, "geometry": {"coordinates": [32.253, 53.6882], "type": "Point"}, "type": "feature"}]}