{"features": [{"geometry": {"coordinates": [32.253, 53.6882], "type": "Point"}, "properties": {"UPDATE_SCRIPT": "python add_town_by_geoname_id.py \u041c\u0438\u043b\u043e\u0441\u043b\u0430\u0432\u0438\u0447\u0438_426.geojson 625157", "adminCode1": "06", "adminName1": "Mahilyowskaya Voblasts\u02bc", "countryCode": "BY", "countryId": "630336", "countryName": "Belarus", "fcl": "P", "fclName": "city, village,...", "fcode": "PPL", "fcodeName": "populated place", "geonameId": 625157, "hgr_admin1_partof": 16.0, "hgr_admin2_partof": 78.0, "hgr_admin_hierarchy": "\u043c\u043e\u0433\u0438\u043b\u0435\u0432\u0441\u043a|\u043a\u043b\u0438\u043c\u043e\u0432\u0438\u0446\u043a", "hgr_alt_name": null, "hgr_html_text": "\u041c\u0418\u041b\u041e\u0421\u041b\u0410\u0412\u0418\u0427\u0418, </span><span class=\"font0\" style=\"font-style:italic;\">\u043c\u0463\u0441\u0442\u0435\u0447\u043a\u043e </span><span class=\"font0\">\u041c\u043e\u0433\u0438\u043b\u0435\u0432\u0441\u043a\u0430\u0433\u043e \u041d\u0430\u043c\u0463\u0441\u0442\u043d\u0438\u0447\u0435\u0441\u0442\u0432\u0430 \u0432\u044a \u041a\u043b\u0438\u043c\u043e\u0432\u0438\u0446\u043a\u043e\u043c\u044a \u0443\u0463\u0437\u0434\u0463. \u0412\u044a \u043e\u043d\u043e\u043c\u044a \u0431\u044b\u0432\u0430\u0435\u0442\u044a \u043e\u0434\u043d\u0430 \u0433\u043e\u0434\u043e\u0432\u0430\u044f \u044f\u0440\u043c\u0430\u0440\u043a\u0430.</span>", "hgr_name": "\u041c\u0438\u043b\u043e\u0441\u043b\u0430\u0432\u0438\u0447\u0438", "hgr_name_modern_sp": "\u041c\u0438\u043b\u043e\u0441\u043b\u0430\u0432\u0438\u0447\u0438", "hgr_page": 74, "hgr_partof_id": 78.0, "hgr_prov_modern_sp": "\u041c\u043e\u0433\u0438\u043b\u0435\u0432\u0441\u043a\u043e\u0433\u043e \u041d\u0430\u043c\u0435\u0441\u0442\u043d\u0438\u0447\u0435\u0441\u0442\u0432\u0430", "hgr_prov_stem": "\u043c\u043e\u0433\u0438\u043b\u0435\u0432\u0441\u043a", "hgr_ru_prov": "\u041c\u043e\u0433\u0438\u043b\u0435\u0432\u0441\u043a\u0430\u0433\u043e \u041d\u0430\u043c\u0463\u0441\u0442\u043d\u0438\u0447\u0435\u0441\u0442\u0432\u0430", "hgr_ru_uezd": "\u041a\u043b\u0438\u043c\u043e\u0432\u0438\u0446\u043a\u043e\u043c\u044a \u0443\u0463\u0437\u0434\u0463", "hgr_source_url": "http://babel.hathitrust.org/cgi/pt?id=uc1.b4583201;view=1up;seq=73", "hgr_text": "\u041c\u0418\u041b\u041e\u0421\u041b\u0410\u0412\u0418\u0427\u0418, \u043c\u0463\u0441\u0442\u0435\u0447\u043a\u043e \u041c\u043e\u0433\u0438\u043b\u0435\u0432\u0441\u043a\u0430\u0433\u043e \u041d\u0430\u043c\u0463\u0441\u0442\u043d\u0438\u0447\u0435\u0441\u0442\u0432\u0430 \u0432\u044a \u041a\u043b\u0438\u043c\u043e\u0432\u0438\u0446\u043a\u043e\u043c\u044a \u0443\u0463\u0437\u0434\u0463. \u0412\u044a \u043e\u043d\u043e\u043c\u044a \u0431\u044b\u0432\u0430\u0435\u0442\u044a \u043e\u0434\u043d\u0430 \u0433\u043e\u0434\u043e\u0432\u0430\u044f \u044f\u0440\u043c\u0430\u0440\u043a\u0430.", "hgr_type": "\u043c\u0463\u0441\u0442\u0435\u0447\u043a\u043e", "hgr_uezd_modern_sp": "\u041a\u043b\u0438\u043c\u043e\u0432\u0438\u0446\u043a\u043e\u043c \u0443\u0435\u0437\u0434\u0435", "hgr_uezd_stem": "\u043a\u043b\u0438\u043c\u043e\u0432\u0438\u0446\u043a", "name": "Miloslavichi", "population": 0, "toponymName": "Milaslavichy"}, "type": "Feature"}], "type": "FeatureCollection"}