{"type": "FeatureCollection", "features": [{"properties": {"countryId": "2017370", "toponymName": "Murikovo", "adminCode1": "47", "geonameId": 524313, "fcl": "P", "name": "Murikovo", "countryName": "Russia", "fclName": "city, village,...", "fcode": "PPL", "adminName1": "Moskovskaya", "countryCode": "RU", "population": 0, "fcodeName": "populated place"}, "geometry": {"coordinates": [35.37, 55.99461], "type": "Point"}, "type": "feature"}]}