{"features": [{"type": "Feature", "geometry": {"coordinates": [35.37, 55.99461], "type": "Point"}, "properties": {"hgr_name_modern_sp": "\u041c\u0443\u0440\u0438\u043a\u043e\u0432\u043e", "hgr_uezd_stem": "\u0432\u043e\u043b\u043e\u043a\u043e\u043b\u0430\u043c\u0441\u043a", "hgr_admin_hierarchy": "\u043c\u043e\u0441\u043a\u043e\u0432\u0441\u043a|\u0432\u043e\u043b\u043e\u043a\u043e\u043b\u0430\u043c\u0441\u043a", "hgr_admin1_partof": 1.0, "toponymName": "Murikovo", "hgr_html_text": "\u041c\u0423\u0420\u0418\u041a\u041e\u0412\u041e, </span><span class=\"font0\" style=\"font-style:italic;\">\u0441\u0435\u043b\u043e</span><span class=\"font0\"> \u041c\u043e\u0441\u043a\u043e\u0432\u0441\u043a\u043e\u0439 \u0413\u0443\u0431\u0435\u0440\u043d\u0456\u0438 \u0432\u044a \u0412\u043e\u043b\u043e\u043a\u043e\u043b\u0430\u043c\u0441\u043a\u043e\u043c\u044a \u0443\u0463\u0437\u0434\u0463. \u0417\u0434\u0463\u0441\u044c \u0431\u044b\u0432\u0430\u0435\u0442\u044a \u043e\u0434\u043d\u0430 \u0432\u044a \u0433\u043e\u0434\u0443 \u044f\u0440\u043c\u0430\u0440\u043a\u0430 \u0421\u0435\u043d\u0442\u044f\u0431\u0440\u044f 25 \u0434\u043d\u044f; \u0442\u043e\u0440\u0433\u0443\u044e\u0442\u044a \u043d\u0430 \u043e\u043d\u043e\u0439 \u0440\u0430\u0437\u043d\u044b\u043c\u0438 \u043a\u0440\u0435\u0441\u0442\u044c\u044f\u043d\u0441\u043a\u0438\u043c\u0438 \u0442\u043e\u0432\u0430\u0440\u0430\u043c\u0438.</span>", "adminCode1": "47", "fcodeName": "populated place", "fcode": "PPL", "hgr_partof_id": 56.0, "hgr_page": 77, "countryName": "Russia", "hgr_text": "\u041c\u0423\u0420\u0418\u041a\u041e\u0412\u041e, \u0441\u0435\u043b\u043e \u041c\u043e\u0441\u043a\u043e\u0432\u0441\u043a\u043e\u0439 \u0413\u0443\u0431\u0435\u0440\u043d\u0456\u0438 \u0432\u044a \u0412\u043e\u043b\u043e\u043a\u043e\u043b\u0430\u043c\u0441\u043a\u043e\u043c\u044a \u0443\u0463\u0437\u0434\u0463. \u0417\u0434\u0463\u0441\u044c \u0431\u044b\u0432\u0430\u0435\u0442\u044a \u043e\u0434\u043d\u0430 \u0432\u044a \u0433\u043e\u0434\u0443 \u044f\u0440\u043c\u0430\u0440\u043a\u0430 \u0421\u0435\u043d\u0442\u044f\u0431\u0440\u044f 25 \u0434\u043d\u044f; \u0442\u043e\u0440\u0433\u0443\u044e\u0442\u044a \u043d\u0430 \u043e\u043d\u043e\u0439 \u0440\u0430\u0437\u043d\u044b\u043c\u0438 \u043a\u0440\u0435\u0441\u0442\u044c\u044f\u043d\u0441\u043a\u0438\u043c\u0438 \u0442\u043e\u0432\u0430\u0440\u0430\u043c\u0438.", "hgr_prov_modern_sp": "\u041c\u043e\u0441\u043a\u043e\u0432\u0441\u043a\u043e\u0439 \u0413\u0443\u0431\u0435\u0440\u043d\u0438\u0438", "hgr_name": "\u041c\u0443\u0440\u0438\u043a\u043e\u0432\u043e", "name": "Murikovo", "hgr_ru_uezd": "\u0412\u043e\u043b\u043e\u043a\u043e\u043b\u0430\u043c\u0441\u043a\u043e\u043c\u044a \u0443\u0463\u0437\u0434\u0463", "population": 0, "countryId": "2017370", "hgr_ru_prov": "\u041c\u043e\u0441\u043a\u043e\u0432\u0441\u043a\u043e\u0439 \u0413\u0443\u0431\u0435\u0440\u043d\u0456\u0438", "hgr_source_url": "http://babel.hathitrust.org/cgi/pt?id=uc1.b4583201;view=1up;seq=76", "fcl": "P", "hgr_alt_name": null, "adminName1": "Moskovskaya", "hgr_admin2_partof": 56.0, "hgr_prov_stem": "\u043c\u043e\u0441\u043a\u043e\u0432\u0441\u043a", "fclName": "city, village,...", "countryCode": "RU", "geonameId": 524313, "hgr_type": "\u0441\u0435\u043b\u043e", "hgr_uezd_modern_sp": "\u0412\u043e\u043b\u043e\u043a\u043e\u043b\u0430\u043c\u0441\u043a\u043e\u043c \u0443\u0435\u0437\u0434\u0435"}}], "type": "FeatureCollection"}