{"type": "FeatureCollection", "features": [{"type": "Feature", "geometry": {"coordinates": [35.37, 55.99461], "type": "Point"}, "properties": {"countryCode": "RU", "countryId": "2017370", "fcodeName": "populated place", "adminName1": "Moskovskaya", "fclName": "city, village,...", "fcl": "P", "countryName": "Russia", "fcode": "PPL", "geonameId": 524313, "population": 0, "adminCode1": "47", "name": "Murikovo", "toponymName": "Murikovo"}}]}