{"type": "FeatureCollection", "features": [{"properties": {"countryId": "2017370", "toponymName": "Nevel\u2019", "adminCode1": "60", "geonameId": 522410, "fcl": "P", "name": "Nevel'", "countryName": "Russia", "fclName": "city, village,...", "fcode": "PPL", "adminName1": "Pskov", "countryCode": "RU", "population": 17832, "fcodeName": "populated place"}, "geometry": {"coordinates": [29.92844, 56.02094], "type": "Point"}, "type": "feature"}, {"properties": {"countryId": "630336", "toponymName": "Nyevyel\u2019", "adminCode1": "01", "geonameId": 700254, "fcl": "P", "name": "Nyevyel\u2019", "countryName": "Belarus", "fclName": "city, village,...", "fcode": "PPL", "adminName1": "Brestskaya Voblasts\u02bc", "countryCode": "BY", "population": 0, "fcodeName": "populated place"}, "geometry": {"coordinates": [25.8443, 51.93], "type": "Point"}, "type": "feature"}]}