{"type": "FeatureCollection", "features": [{"type": "Feature", "geometry": {"coordinates": [29.92844, 56.02094], "type": "Point"}, "properties": {"countryCode": "RU", "countryId": "2017370", "fcodeName": "populated place", "adminName1": "Pskov", "fclName": "city, village,...", "fcl": "P", "countryName": "Russia", "fcode": "PPL", "geonameId": 522410, "population": 17832, "adminCode1": "60", "name": "Nevel'", "toponymName": "Nevel\u2019"}}, {"type": "Feature", "geometry": {"coordinates": [25.8443, 51.93], "type": "Point"}, "properties": {"countryCode": "BY", "countryId": "630336", "fcodeName": "populated place", "adminName1": "Brestskaya Voblasts\u02bc", "fclName": "city, village,...", "fcl": "P", "countryName": "Belarus", "fcode": "PPL", "geonameId": 700254, "population": 0, "adminCode1": "01", "name": "Nyevyel\u2019", "toponymName": "Nyevyel\u2019"}}]}