{"type": "FeatureCollection", "features": [{"type": "Feature", "geometry": {"coordinates": [31.2675, 52.2792], "type": "Point"}, "properties": {"countryCode": "BY", "countryId": "630336", "fcodeName": "populated place", "adminName1": "Gomel", "fclName": "city, village,...", "fcl": "P", "countryName": "Belarus", "fcode": "PPL", "geonameId": 624611, "population": 0, "adminCode1": "02", "name": "Nosovichi", "toponymName": "Nasovichy"}}, {"type": "Feature", "geometry": {"coordinates": [29.5797, 52.2836], "type": "Point"}, "properties": {"countryCode": "BY", "countryId": "630336", "fcodeName": "populated place", "adminName1": "Gomel", "fclName": "city, village,...", "fcl": "P", "countryName": "Belarus", "fcode": "PPL", "geonameId": 624795, "population": 0, "adminCode1": "02", "name": "Nasavichi", "toponymName": "Nasavichy"}}]}