{"type": "FeatureCollection", "features": [{"properties": {"countryId": "630336", "toponymName": "Nasovichy", "adminCode1": "02", "geonameId": 624611, "fcl": "P", "name": "Nosovichi", "countryName": "Belarus", "fclName": "city, village,...", "fcode": "PPL", "adminName1": "Gomel", "countryCode": "BY", "population": 0, "fcodeName": "populated place"}, "geometry": {"coordinates": [31.2675, 52.2792], "type": "Point"}, "type": "feature"}, {"properties": {"countryId": "630336", "toponymName": "Nasavichy", "adminCode1": "02", "geonameId": 624795, "fcl": "P", "name": "Nasavichi", "countryName": "Belarus", "fclName": "city, village,...", "fcode": "PPL", "adminName1": "Gomel", "countryCode": "BY", "population": 0, "fcodeName": "populated place"}, "geometry": {"coordinates": [29.5797, 52.2836], "type": "Point"}, "type": "feature"}]}