{"type": "FeatureCollection", "features": [{"properties": {"countryId": "2017370", "toponymName": "Lesnaya Opushka", "adminCode1": "72", "geonameId": 535784, "fcl": "P", "name": "Lesnaya Opushka", "countryName": "Russia", "fclName": "city, village,...", "fcode": "PPLX", "adminName1": "Tambov", "countryCode": "RU", "population": 0, "fcodeName": "section of populated place"}, "geometry": {"coordinates": [41.48117, 52.60643], "type": "Point"}, "type": "feature"}]}