{"type": "FeatureCollection", "features": [{"type": "Feature", "geometry": {"coordinates": [41.48117, 52.60643], "type": "Point"}, "properties": {"countryCode": "RU", "countryId": "2017370", "fcodeName": "section of populated place", "adminName1": "Tambov", "fclName": "city, village,...", "fcl": "P", "countryName": "Russia", "fcode": "PPLX", "geonameId": 535784, "population": 0, "adminCode1": "72", "name": "Lesnaya Opushka", "toponymName": "Lesnaya Opushka"}}]}