{"features": [{"properties": {"hgr_source_url": "http://babel.hathitrust.org/cgi/pt?id=uc1.b4583201;view=1up;seq=82", "fcl": "P", "fclName": "city, village,...", "hgr_partof_id": 133.0, "hgr_alt_name": null, "fcodeName": "section of populated place", "hgr_ru_uezd": "\u0428\u0430\u0442\u0441\u043a\u043e\u043c\u044a \u0443\u0463\u0437\u0434\u0463", "hgr_partof_prov_name": "\u0422\u0430\u043c\u0431\u043e\u0432\u0441\u043a\u043e\u0435 \u041d\u0430\u043c\u0463\u0441\u0442\u043d\u0438\u0447\u0435\u0441\u0442\u0432\u043e", "hgr_name": "\u041e\u043f\u0443\u0448\u043a\u0430", "population": 0, "adminCode1": "72", "fcode": "PPLX", "geonameId": 535784, "hgr_text": "\u041e\u041f\u0423\u0428\u041a\u0410, \u043e\u0442\u0447\u0438\u043d\u0430 \u0440\u0430\u0437\u043d\u044b\u0445\u044a \u0413\u043e\u0441\u043f\u043e\u0434\u044a \u0422\u0430\u043c\u0431\u043e\u0432\u0441\u043a\u0430\u0433\u043e \u041d\u0430\u043c\u0463\u0441\u0442\u043d\u0438\u0447\u0435\u0441\u0442\u0432\u0430 \u0432\u044a \u0428\u0430\u0442\u0441\u043a\u043e\u043c\u044a \u0443\u0463\u0437\u0434\u0463. \u0417\u0434\u0463\u0441\u044c \u0431\u044b\u0432\u0430\u0435\u0442\u044a \u0432\u044a \u0433\u043e\u0434\u0443 \u044f\u0440\u043c\u0430\u0440\u043a\u0430 8 \u0406\u044e\u043b\u044f; \u0442\u043e\u0440\u0433\u0443\u044e\u0442\u044a \u0440\u0430\u0437\u043d\u044b\u043c\u0438 \u0442\u043e\u0432\u0430\u0440\u0430\u043c\u0438 , \u043a\u0430\u043a\u044a - \u0442\u043e \u043f\u0435\u043d\u044c\u043a\u043e\u044e , \u0440\u0430\u0437\u043d\u044b\u043c\u044a \u0445\u043e\u043b\u0441\u0442\u043e\u043c\u044a \u043c\u0435\u0434\u043e\u043c\u044a, \u0441\u0430\u043b\u043e\u043c\u044a \u0438 \u043f\u0440\u043e\u0447\u0438\u043c\u044a.", "hgr_type": "\u043e\u0442\u0447\u0438\u043d\u0430", "hgr_name_modern_sp": "\u041e\u043f\u0443\u0448\u043a\u0430", "hgr_page": 83, "hgr_uezd_modern_sp": "\u0428\u0430\u0442\u0441\u043a\u043e\u043c \u0443\u0435\u0437\u0434\u0435", "toponymName": "Lesnaya Opushka", "countryCode": "RU", "hgr_html_text": "\u041e\u041f\u0423\u0428\u041a\u0410, </span><span class=\"font0\" style=\"font-style:italic;\">\u043e\u0442\u0447\u0438\u043d\u0430</span><span class=\"font0\"> \u0440\u0430\u0437\u043d\u044b\u0445\u044a \u0413\u043e\u0441\u043f\u043e\u0434\u044a \u0422\u0430\u043c\u0431\u043e\u0432\u0441\u043a\u0430\u0433\u043e \u041d\u0430\u043c\u0463\u0441\u0442\u043d\u0438\u0447\u0435\u0441\u0442\u0432\u0430 \u0432\u044a \u0428\u0430\u0442\u0441\u043a\u043e\u043c\u044a \u0443\u0463\u0437\u0434\u0463. \u0417\u0434\u0463\u0441\u044c \u0431\u044b\u0432\u0430\u0435\u0442\u044a \u0432\u044a \u0433\u043e\u0434\u0443 \u044f\u0440\u043c\u0430\u0440\u043a\u0430 8 \u0406\u044e\u043b\u044f; \u0442\u043e\u0440\u0433\u0443\u044e\u0442\u044a \u0440\u0430\u0437\u043d\u044b\u043c\u0438 \u0442\u043e\u0432\u0430\u0440\u0430\u043c\u0438 , \u043a\u0430\u043a\u044a - \u0442\u043e \u043f\u0435\u043d\u044c\u043a\u043e\u044e , \u0440\u0430\u0437\u043d\u044b\u043c\u044a \u0445\u043e\u043b\u0441\u0442\u043e\u043c\u044a \u043c\u0435\u0434\u043e\u043c\u044a, \u0441\u0430\u043b\u043e\u043c\u044a \u0438 \u043f\u0440\u043e\u0447\u0438\u043c\u044a.</span>", "hgr_prov_stem": "\u0442\u0430\u043c\u0431\u043e\u0432\u0441\u043a", "countryName": "Russia", "hgr_uezd_stem": "\u0448\u0430\u0442\u0441\u043a", "adminName1": "Tambov", "name": "Lesnaya Opushka", "hgr_admin_hierarchy": "\u0442\u0430\u043c\u0431\u043e\u0432\u0441\u043a|\u0448\u0430\u0442\u0441\u043a", "hgr_prov_modern_sp": "\u0422\u0430\u043c\u0431\u043e\u0432\u0441\u043a\u043e\u0433\u043e \u041d\u0430\u043c\u0435\u0441\u0442\u043d\u0438\u0447\u0435\u0441\u0442\u0432\u0430", "hgr_admin1_partof": 32.0, "countryId": "2017370", "hgr_admin2_partof": 133.0, "hgr_ru_prov": "\u0422\u0430\u043c\u0431\u043e\u0432\u0441\u043a\u0430\u0433\u043e \u041d\u0430\u043c\u0463\u0441\u0442\u043d\u0438\u0447\u0435\u0441\u0442\u0432\u0430"}, "type": "Feature", "geometry": {"coordinates": [41.48117, 52.60643], "type": "Point"}}], "type": "FeatureCollection"}