{"type": "FeatureCollection", "features": [{"properties": {"countryId": "2017370", "toponymName": "Ostashkov", "adminCode1": "77", "geonameId": 514259, "fcl": "P", "name": "Ostashkov", "countryName": "Russia", "fclName": "city, village,...", "fcode": "PPL", "adminName1": "Tverskaya", "countryCode": "RU", "population": 19563, "fcodeName": "populated place"}, "geometry": {"coordinates": [33.10753, 57.14667], "type": "Point"}, "type": "feature"}]}