{"type": "FeatureCollection", "features": [{"type": "Feature", "geometry": {"coordinates": [33.76977, 49.54487], "type": "Point"}, "properties": {"countryCode": "UA", "countryId": "690791", "fcodeName": "populated place", "adminName1": "Poltava", "fclName": "city, village,...", "fcl": "P", "countryName": "Ukraine", "fcode": "PPL", "geonameId": 698250, "population": 0, "adminCode1": "18", "name": "Ostap'ye", "toponymName": "Ostap\u2019ye"}}]}