{"features": [{"properties": {"fcl": "P", "geonameId": 514259, "countryId": "2017370", "fcode": "PPL", "name": "Ostashkov", "countryName": "Russia", "population": 19563, "fclName": "city, village,...", "adminName1": "Tverskaya", "adminCode1": "77", "fcodeName": "populated place", "countryCode": "RU", "toponymName": "Ostashkov"}, "geometry": {"coordinates": [33.10753, 57.14667], "type": "Point"}, "type": "Feature"}], "type": "FeatureCollection"}