{"type": "FeatureCollection", "features": [{"type": "Feature", "geometry": {"coordinates": [33.10753, 57.14667], "type": "Point"}, "properties": {"countryCode": "RU", "countryId": "2017370", "fcodeName": "populated place", "adminName1": "Tverskaya", "fclName": "city, village,...", "fcl": "P", "countryName": "Russia", "fcode": "PPL", "geonameId": 514259, "population": 19563, "adminCode1": "77", "name": "Ostashkov", "toponymName": "Ostashkov"}}]}