{"type": "FeatureCollection", "features": [{"properties": {"countryId": "690791", "toponymName": "Ostap\u2019ye", "adminCode1": "18", "geonameId": 698250, "fcl": "P", "name": "Ostap'ye", "countryName": "Ukraine", "fclName": "city, village,...", "fcode": "PPL", "adminName1": "Poltava", "countryCode": "UA", "population": 0, "fcodeName": "populated place"}, "geometry": {"coordinates": [33.76977, 49.54487], "type": "Point"}, "type": "feature"}]}