{"features": [{"properties": {"hgr_name_modern_sp": "\u041f\u0435\u0440\u0435\u043c\u044b\u0448\u043b\u044c", "countryCode": "RU", "hgr_admin_hierarchy": "\u043a\u0430\u043b\u0443\u0436\u0441\u043a", "fcl": "P", "toponymName": "Peremyshl\u2019", "countryName": "Russia", "adminCode1": "25", "fcodeName": "populated place", "population": 3199, "hgr_partof_id": 12.0, "hgr_page": 86, "hgr_html_text": "\u041f\u0415\u0420\u0415\u041c\u042b\u0428\u041b\u042c , </span><span class=\"font0\" style=\"font-style:italic;\">\u0433\u043e\u0440\u043e\u0434\u044a</span><span class=\"font0\"> \u041a\u0430\u043b\u0443\u0436\u0441\u043a\u0430\u0433\u043e \u041d\u0430\u043c\u0463\u0441\u0442\u043d\u0438\u0447\u0435\u0441\u0442\u0432\u0430. \u0417\u0434\u0463\u0441\u044c \u0431\u044b\u0432\u0430\u0435\u0442\u044a \u0433\u043e\u0434\u043e\u0432\u0430\u044f \u044f\u0440\u043c\u0430\u0440\u043a\u0430 \u0441\u0432\u0435\u0440\u0445\u044a \u043e\u0431\u044b\u043a\u043d\u043e\u0432\u0435\u043d\u043d\u044b\u0445\u044a \u0442\u043e\u0440\u0433\u043e\u0432\u044a \u0432\u044a \u0434\u0435\u0441\u044f\u0442\u0443\u044e \u043f\u044f\u0442\u043d\u0438\u0446\u0443 \u043f\u043e \u041f\u0430\u0441\u0445\u0463; \u043f\u0440\u0438\u0432\u043e\u0437\u044f\u0442\u044a \u043d\u0430 \u043f\u0440\u043e\u0434\u0430\u0436\u0443 \u0445\u0434\u0463\u0431\u044a, \u043f\u0435\u043d\u044c\u043a\u0443 , \u0445\u043c\u0463\u043b\u044c \u0438 \u043f\u0440\u043e\u0447\u0435\u0435.</span>", "UPDATE_SCRIPT": "python add_town_by_geoname_id.py \u041f\u0435\u0440\u0435\u043c\u044b\u0448\u043b\u044c_519.geojson 511400", "hgr_text": "\u041f\u0415\u0420\u0415\u041c\u042b\u0428\u041b\u042c , \u0433\u043e\u0440\u043e\u0434\u044a \u041a\u0430\u043b\u0443\u0436\u0441\u043a\u0430\u0433\u043e \u041d\u0430\u043c\u0463\u0441\u0442\u043d\u0438\u0447\u0435\u0441\u0442\u0432\u0430. \u0417\u0434\u0463\u0441\u044c \u0431\u044b\u0432\u0430\u0435\u0442\u044a \u0433\u043e\u0434\u043e\u0432\u0430\u044f \u044f\u0440\u043c\u0430\u0440\u043a\u0430 \u0441\u0432\u0435\u0440\u0445\u044a \u043e\u0431\u044b\u043a\u043d\u043e\u0432\u0435\u043d\u043d\u044b\u0445\u044a \u0442\u043e\u0440\u0433\u043e\u0432\u044a \u0432\u044a \u0434\u0435\u0441\u044f\u0442\u0443\u044e \u043f\u044f\u0442\u043d\u0438\u0446\u0443 \u043f\u043e \u041f\u0430\u0441\u0445\u0463; \u043f\u0440\u0438\u0432\u043e\u0437\u044f\u0442\u044a \u043d\u0430 \u043f\u0440\u043e\u0434\u0430\u0436\u0443 \u0445\u0434\u0463\u0431\u044a, \u043f\u0435\u043d\u044c\u043a\u0443 , \u0445\u043c\u0463\u043b\u044c \u0438 \u043f\u0440\u043e\u0447\u0435\u0435.", "hgr_prov_modern_sp": "\u041a\u0430\u043b\u0443\u0436\u0441\u043a\u043e\u0433\u043e \u041d\u0430\u043c\u0435\u0441\u0442\u043d\u0438\u0447\u0435\u0441\u0442\u0432\u0430", "hgr_name": "\u041f\u0435\u0440\u0435\u043c\u044b\u0448\u043b\u044c", "name": "Peremyshl'", "hgr_ru_uezd": "not_in_text", "hgr_source_url": "http://babel.hathitrust.org/cgi/pt?id=uc1.b4583201;view=1up;seq=85", "countryId": "2017370", "hgr_ru_prov": "\u041a\u0430\u043b\u0443\u0436\u0441\u043a\u0430\u0433\u043e \u041d\u0430\u043c\u0463\u0441\u0442\u043d\u0438\u0447\u0435\u0441\u0442\u0432\u0430", "hgr_uezd_stem": "\u043d\u043e\u0442_\u0438\u043d_\u0442\u0435x\u0442", "hgr_admin1_partof": 12.0, "hgr_alt_name": null, "adminName1": "Kaluga", "hgr_admin2_partof": null, "fcode": "PPL", "fclName": "city, village,...", "hgr_prov_stem": "\u043a\u0430\u043b\u0443\u0436\u0441\u043a", "geonameId": 511400, "hgr_type": "\u0433\u043e\u0440\u043e\u0434\u044a", "hgr_uezd_modern_sp": "not_\u0438n_text"}, "geometry": {"coordinates": [36.16063, 54.26313], "type": "Point"}, "type": "Feature"}], "type": "FeatureCollection"}