{"type": "FeatureCollection", "features": [{"type": "Feature", "geometry": {"coordinates": [45.00464, 53.20066], "type": "Point"}, "properties": {"countryCode": "RU", "countryId": "2017370", "fcodeName": "seat of a first-order administrative division", "adminName1": "Penza", "fclName": "city, village,...", "fcl": "P", "countryName": "Russia", "fcode": "PPLA", "geonameId": 511565, "population": 512602, "adminCode1": "57", "name": "Penza", "toponymName": "Penza"}}, {"type": "Feature", "geometry": {"coordinates": [46.58333, 53.13333], "type": "Point"}, "properties": {"countryCode": "RU", "countryId": "2017370", "fcodeName": "populated place", "adminName1": "Penza", "fclName": "city, village,...", "fcl": "P", "countryName": "Russia", "fcode": "PPL", "geonameId": 831165, "population": 62139, "adminCode1": "57", "name": "Zarechnyy", "toponymName": "Zarechnyy"}}]}