{"type": "FeatureCollection", "features": [{"properties": {"countryId": "2017370", "toponymName": "Peremyshl\u2019", "adminCode1": "25", "geonameId": 511400, "fcl": "P", "name": "Peremyshl'", "countryName": "Russia", "fclName": "city, village,...", "fcode": "PPL", "adminName1": "Kaluga", "countryCode": "RU", "population": 3199, "fcodeName": "populated place"}, "geometry": {"coordinates": [36.16063, 54.26313], "type": "Point"}, "type": "feature"}]}