{"type": "FeatureCollection", "features": [{"type": "Feature", "geometry": {"coordinates": [36.16063, 54.26313], "type": "Point"}, "properties": {"countryCode": "RU", "countryId": "2017370", "fcodeName": "populated place", "adminName1": "Kaluga", "fclName": "city, village,...", "fcl": "P", "countryName": "Russia", "fcode": "PPL", "geonameId": 511400, "population": 3199, "adminCode1": "25", "name": "Peremyshl'", "toponymName": "Peremyshl\u2019"}}]}