{"type": "FeatureCollection", "features": [{"properties": {"countryId": "2017370", "toponymName": "Penza", "adminCode1": "57", "geonameId": 511565, "fcl": "P", "name": "Penza", "countryName": "Russia", "fclName": "city, village,...", "fcode": "PPLA", "adminName1": "Penza", "countryCode": "RU", "population": 512602, "fcodeName": "seat of a first-order administrative division"}, "geometry": {"coordinates": [45.00464, 53.20066], "type": "Point"}, "type": "feature"}, {"properties": {"countryId": "2017370", "toponymName": "Zarechnyy", "adminCode1": "57", "geonameId": 831165, "fcl": "P", "name": "Zarechnyy", "countryName": "Russia", "fclName": "city, village,...", "fcode": "PPL", "adminName1": "Penza", "countryCode": "RU", "population": 62139, "fcodeName": "populated place"}, "geometry": {"coordinates": [46.58333, 53.13333], "type": "Point"}, "type": "feature"}]}