{"type": "FeatureCollection", "features": [{"type": "Feature", "geometry": {"coordinates": [31.04966, 49.77022], "type": "Point"}, "properties": {"countryCode": "UA", "countryId": "690791", "fcodeName": "populated place", "adminName1": "Kiev", "fclName": "city, village,...", "fcl": "P", "countryName": "Ukraine", "fcode": "PPL", "geonameId": 696415, "population": 0, "adminCode1": "13", "name": "Potok", "toponymName": "Potok"}}]}