{"type": "FeatureCollection", "features": [{"properties": {"countryId": "690791", "toponymName": "Potok", "adminCode1": "13", "geonameId": 696415, "fcl": "P", "name": "Potok", "countryName": "Ukraine", "fclName": "city, village,...", "fcode": "PPL", "adminName1": "Kiev", "countryCode": "UA", "population": 0, "fcodeName": "populated place"}, "geometry": {"coordinates": [31.04966, 49.77022], "type": "Point"}, "type": "feature"}]}