{"features": [{"properties": {"fcl": "P", "geonameId": 696415, "countryId": "690791", "fcode": "PPL", "name": "Potok", "countryName": "Ukraine", "population": 0, "fclName": "city, village,...", "adminName1": "Kiev", "adminCode1": "13", "fcodeName": "populated place", "countryCode": "UA", "toponymName": "Potok"}, "geometry": {"coordinates": [31.04966, 49.77022], "type": "Point"}, "type": "Feature"}], "type": "FeatureCollection"}