{"type": "FeatureCollection", "features": [{"properties": {"countryId": "2017370", "toponymName": "Putyatino", "adminCode1": "62", "geonameId": 503682, "fcl": "P", "name": "Putyatino", "countryName": "Russia", "fclName": "city, village,...", "fcode": "PPL", "adminName1": "Rjazan", "countryCode": "RU", "population": 3044, "fcodeName": "populated place"}, "geometry": {"coordinates": [41.1169, 54.15998], "type": "Point"}, "type": "feature"}, {"properties": {"countryId": "2017370", "toponymName": "Putyatino", "adminCode1": "43", "geonameId": 503684, "fcl": "P", "name": "Putyatino", "countryName": "Russia", "fclName": "city, village,...", "fcode": "PPL", "adminName1": "Lipetsk", "countryCode": "RU", "population": 0, "fcodeName": "populated place"}, "geometry": {"coordinates": [39.74936, 53.04596], "type": "Point"}, "type": "feature"}, {"properties": {"countryId": "2017370", "toponymName": "Putyatino", "adminCode1": "21", "geonameId": 7042683, "fcl": "P", "name": "Putyatino", "countryName": "Russia", "fclName": "city, village,...", "fcode": "PPL", "adminName1": "Ivanovo", "countryCode": "RU", "population": 0, "fcodeName": "populated place"}, "geometry": {"coordinates": [40.2878, 56.62629], "type": "Point"}, "type": "feature"}]}