{"type": "FeatureCollection", "features": [{"type": "Feature", "geometry": {"coordinates": [41.1169, 54.15998], "type": "Point"}, "properties": {"countryCode": "RU", "countryId": "2017370", "fcodeName": "populated place", "adminName1": "Rjazan", "fclName": "city, village,...", "fcl": "P", "countryName": "Russia", "fcode": "PPL", "geonameId": 503682, "population": 3044, "adminCode1": "62", "name": "Putyatino", "toponymName": "Putyatino"}}, {"type": "Feature", "geometry": {"coordinates": [39.74936, 53.04596], "type": "Point"}, "properties": {"countryCode": "RU", "countryId": "2017370", "fcodeName": "populated place", "adminName1": "Lipetsk", "fclName": "city, village,...", "fcl": "P", "countryName": "Russia", "fcode": "PPL", "geonameId": 503684, "population": 0, "adminCode1": "43", "name": "Putyatino", "toponymName": "Putyatino"}}, {"type": "Feature", "geometry": {"coordinates": [40.2878, 56.62629], "type": "Point"}, "properties": {"countryCode": "RU", "countryId": "2017370", "fcodeName": "populated place", "adminName1": "Ivanovo", "fclName": "city, village,...", "fcl": "P", "countryName": "Russia", "fcode": "PPL", "geonameId": 7042683, "population": 0, "adminCode1": "21", "name": "Putyatino", "toponymName": "Putyatino"}}]}