{"features": [{"type": "Feature", "geometry": {"coordinates": [37.59472, 49.75083], "type": "Point"}, "properties": {"hgr_name_modern_sp": "\u0420\u0430\u0442\u043a\u043e\u0432\u043a\u0430", "hgr_uezd_stem": "\u0438\u0437\u044e\u043c", "hgr_admin_hierarchy": "\u0445\u0430\u0440\u044c\u043a\u043e\u0432\u0441\u043a|\u0438\u0437\u044e\u043c", "hgr_admin1_partof": 37.0, "toponymName": "Rad\u2019kivka", "hgr_html_text": "\u0420\u0410\u0422\u041a\u041e\u0412\u041a\u0410, </span><span class=\"font0\" style=\"font-style:italic;\">\u0441\u043b\u043e\u0431\u043e\u0434\u0430</span><span class=\"font0\"> \u0425\u0430\u0440\u044c\u043a\u043e\u0432\u0441\u043a\u0430\u0433\u043e \u041d\u0430\u043c\u0463\u0441\u0442\u043d\u0438\u0447\u0435\u0441\u0442\u0432\u0430 \u0432\u044a \u0443\u0463\u0437\u0434\u0463 \u0433\u043e\u0440\u043e\u0434\u0430 \u0418\u0437\u044e\u043c\u0430. \u0412\u044a \u043e\u043d\u043e\u0439 \u0431\u044b\u0432\u0430\u044e\u0442\u044a \u0432\u044a \u0433\u043e\u0434\u0443 \u0442\u0440\u0438 \u044f\u0440\u043c\u0430\u0440\u043a\u0438: \u041f\u0435\u0440\u0432\u0430\u044f \u043d\u0430 \u0412\u043e\u0437\u043d\u0435\u0441\u0435\u043d\u0456\u0435 \u0413\u043e\u0441\u043f\u043e\u0434\u043d\u0435 , \u0432\u0442\u043e\u0440\u0430\u044f \u0410\u0432\u0433\u0443\u0441\u0442\u0430 \u0431 , \u043d\u0430 \u041f\u0440\u0435\u043e\u0431\u0440\u0430\u0436\u0435\u043d\u0456\u0435 , \u0442\u0440\u0435\u0442\u0456\u044f \u041e\u043a\u0442\u044f\u0431\u0440\u044f 1, \u0432\u044a \u0434\u0435\u043d\u044c \u041f\u043e\u043a\u0440\u043e\u0432\u0430. \u041a\u0443\u043f\u0446\u044b \u043d\u0430 \u043e\u043d\u044b\u044f \u043f\u0440\u0456\u0463\u0437\u0436\u0430\u044e\u0442\u044a \u0438\u0437\u044a \u0440\u0430\u0437\u043d\u044b\u0445\u044a \u0433\u043e\u0440\u043e\u0434\u043e\u0432\u044a \u0441\u044a \u0448\u0435\u043b\u043a\u043e\u0432\u044b\u043c\u0438 , \u0431\u0443\u043c\u0430\u0436\u043d\u044b\u043c\u0438 , \u0433\u0430\u0440\u0443\u0441\u043d\u044b\u043c\u0438 \u0438 \u043f\u0440\u043e\u0447\u0438\u043c\u0438 \u0442\u043e\u0432\u0430\u0440\u0430\u043c\u0438.</span>", "adminCode1": "07", "fcodeName": "populated place", "fcode": "PPL", "hgr_partof_id": 69.0, "hgr_page": 94, "countryName": "Ukraine", "hgr_text": "\u0420\u0410\u0422\u041a\u041e\u0412\u041a\u0410, \u0441\u043b\u043e\u0431\u043e\u0434\u0430 \u0425\u0430\u0440\u044c\u043a\u043e\u0432\u0441\u043a\u0430\u0433\u043e \u041d\u0430\u043c\u0463\u0441\u0442\u043d\u0438\u0447\u0435\u0441\u0442\u0432\u0430 \u0432\u044a \u0443\u0463\u0437\u0434\u0463 \u0433\u043e\u0440\u043e\u0434\u0430 \u0418\u0437\u044e\u043c\u0430. \u0412\u044a \u043e\u043d\u043e\u0439 \u0431\u044b\u0432\u0430\u044e\u0442\u044a \u0432\u044a \u0433\u043e\u0434\u0443 \u0442\u0440\u0438 \u044f\u0440\u043c\u0430\u0440\u043a\u0438: \u041f\u0435\u0440\u0432\u0430\u044f \u043d\u0430 \u0412\u043e\u0437\u043d\u0435\u0441\u0435\u043d\u0456\u0435 \u0413\u043e\u0441\u043f\u043e\u0434\u043d\u0435 , \u0432\u0442\u043e\u0440\u0430\u044f \u0410\u0432\u0433\u0443\u0441\u0442\u0430 \u0431 , \u043d\u0430 \u041f\u0440\u0435\u043e\u0431\u0440\u0430\u0436\u0435\u043d\u0456\u0435 , \u0442\u0440\u0435\u0442\u0456\u044f \u041e\u043a\u0442\u044f\u0431\u0440\u044f 1, \u0432\u044a \u0434\u0435\u043d\u044c \u041f\u043e\u043a\u0440\u043e\u0432\u0430. \u041a\u0443\u043f\u0446\u044b \u043d\u0430 \u043e\u043d\u044b\u044f \u043f\u0440\u0456\u0463\u0437\u0436\u0430\u044e\u0442\u044a \u0438\u0437\u044a \u0440\u0430\u0437\u043d\u044b\u0445\u044a \u0433\u043e\u0440\u043e\u0434\u043e\u0432\u044a \u0441\u044a \u0448\u0435\u043b\u043a\u043e\u0432\u044b\u043c\u0438 , \u0431\u0443\u043c\u0430\u0436\u043d\u044b\u043c\u0438 , \u0433\u0430\u0440\u0443\u0441\u043d\u044b\u043c\u0438 \u0438 \u043f\u0440\u043e\u0447\u0438\u043c\u0438 \u0442\u043e\u0432\u0430\u0440\u0430\u043c\u0438.", "hgr_prov_modern_sp": "\u0425\u0430\u0440\u044c\u043a\u043e\u0432\u0441\u043a\u043e\u0433\u043e \u041d\u0430\u043c\u0435\u0441\u0442\u043d\u0438\u0447\u0435\u0441\u0442\u0432\u0430", "hgr_name": "\u0420\u0430\u0442\u043a\u043e\u0432\u043a\u0430", "name": "Rad\u2019kivka", "hgr_ru_uezd": "\u0418\u0437\u044e\u043c\u0430", "population": 0, "countryId": "690791", "hgr_ru_prov": "\u0425\u0430\u0440\u044c\u043a\u043e\u0432\u0441\u043a\u0430\u0433\u043e \u041d\u0430\u043c\u0463\u0441\u0442\u043d\u0438\u0447\u0435\u0441\u0442\u0432\u0430", "hgr_source_url": "http://babel.hathitrust.org/cgi/pt?id=uc1.b4583201;view=1up;seq=93", "fcl": "P", "hgr_alt_name": null, "adminName1": "Kharkiv", "hgr_admin2_partof": 69.0, "hgr_prov_stem": "\u0445\u0430\u0440\u044c\u043a\u043e\u0432\u0441\u043a", "fclName": "city, village,...", "countryCode": "UA", "geonameId": 813242, "hgr_type": "\u0441\u043b\u043e\u0431\u043e\u0434\u0430", "hgr_uezd_modern_sp": "\u0418\u0437\u044e\u043c\u0430"}}], "type": "FeatureCollection"}