{"type": "FeatureCollection", "features": [{"properties": {"countryId": "690791", "toponymName": "Rad\u2019kivka", "adminCode1": "07", "geonameId": 813242, "fcl": "P", "name": "Rad\u2019kivka", "countryName": "Ukraine", "fclName": "city, village,...", "fcode": "PPL", "adminName1": "Kharkiv", "countryCode": "UA", "population": 0, "fcodeName": "populated place"}, "geometry": {"coordinates": [37.59472, 49.75083], "type": "Point"}, "type": "feature"}]}