{"type": "FeatureCollection", "features": [{"type": "Feature", "geometry": {"coordinates": [37.59472, 49.75083], "type": "Point"}, "properties": {"countryCode": "UA", "countryId": "690791", "fcodeName": "populated place", "adminName1": "Kharkiv", "fclName": "city, village,...", "fcl": "P", "countryName": "Ukraine", "fcode": "PPL", "geonameId": 813242, "population": 0, "adminCode1": "07", "name": "Rad\u2019kivka", "toponymName": "Rad\u2019kivka"}}]}