{"type": "FeatureCollection", "features": [{"type": "Feature", "geometry": {"coordinates": [24.10589, 56.946], "type": "Point"}, "properties": {"countryCode": "LV", "countryId": "458258", "fcodeName": "capital of a political entity", "adminName1": "R\u012bga", "fclName": "city, village,...", "fcl": "P", "countryName": "Latvia", "fcode": "PPLC", "geonameId": 456172, "population": 742572, "adminCode1": "25", "name": "Riga", "toponymName": "Riga"}}, {"type": "Feature", "geometry": {"coordinates": [23.77038, 56.968], "type": "Point"}, "properties": {"countryCode": "LV", "countryId": "458258", "fcodeName": "seat of a first-order administrative division", "adminName1": "J\u016brmala", "fclName": "city, village,...", "fcl": "P", "countryName": "Latvia", "fcode": "PPLA", "geonameId": 459201, "population": 54088, "adminCode1": "13", "name": "J\u016brmala", "toponymName": "J\u016brmala"}}]}