{"type": "FeatureCollection", "features": [{"properties": {"countryId": "458258", "toponymName": "Riga", "adminCode1": "25", "geonameId": 456172, "fcl": "P", "name": "Riga", "countryName": "Latvia", "fclName": "city, village,...", "fcode": "PPLC", "adminName1": "R\u012bga", "countryCode": "LV", "population": 742572, "fcodeName": "capital of a political entity"}, "geometry": {"coordinates": [24.10589, 56.946], "type": "Point"}, "type": "feature"}, {"properties": {"countryId": "458258", "toponymName": "J\u016brmala", "adminCode1": "13", "geonameId": 459201, "fcl": "P", "name": "J\u016brmala", "countryName": "Latvia", "fclName": "city, village,...", "fcode": "PPLA", "adminName1": "J\u016brmala", "countryCode": "LV", "population": 54088, "fcodeName": "seat of a first-order administrative division"}, "geometry": {"coordinates": [23.77038, 56.968], "type": "Point"}, "type": "feature"}]}