{"type": "FeatureCollection", "features": [{"type": "Feature", "geometry": {"coordinates": [32.31206, 52.29781], "type": "Point"}, "properties": {"countryCode": "RU", "countryId": "2017370", "fcodeName": "populated place", "adminName1": "Brjansk", "fclName": "city, village,...", "fcl": "P", "countryName": "Russia", "fcode": "PPL", "geonameId": 516874, "population": 0, "adminCode1": "10", "name": "Novyy Ropsk", "toponymName": "Novyy Ropsk"}}, {"type": "Feature", "geometry": {"coordinates": [32.25882, 52.30876], "type": "Point"}, "properties": {"countryCode": "RU", "countryId": "2017370", "fcodeName": "populated place", "adminName1": "Brjansk", "fclName": "city, village,...", "fcl": "P", "countryName": "Russia", "fcode": "PPL", "geonameId": 487912, "population": 0, "adminCode1": "10", "name": "Staryy Ropsk", "toponymName": "Staryy Ropsk"}}]}