{"features": [{"properties": {"fcl": "P", "geonameId": 516874, "countryId": "2017370", "fcode": "PPL", "name": "Novyy Ropsk", "countryName": "Russia", "population": 0, "fclName": "city, village,...", "adminName1": "Brjansk", "adminCode1": "10", "fcodeName": "populated place", "countryCode": "RU", "toponymName": "Novyy Ropsk"}, "geometry": {"coordinates": [32.31206, 52.29781], "type": "Point"}, "type": "Feature"}, {"properties": {"fcl": "P", "geonameId": 487912, "countryId": "2017370", "fcode": "PPL", "name": "Staryy Ropsk", "countryName": "Russia", "population": 0, "fclName": "city, village,...", "adminName1": "Brjansk", "adminCode1": "10", "fcodeName": "populated place", "countryCode": "RU", "toponymName": "Staryy Ropsk"}, "geometry": {"coordinates": [32.25882, 52.30876], "type": "Point"}, "type": "Feature"}], "type": "FeatureCollection"}