{"type": "FeatureCollection", "features": [{"properties": {"countryId": "2017370", "toponymName": "Novyy Ropsk", "adminCode1": "10", "geonameId": 516874, "fcl": "P", "name": "Novyy Ropsk", "countryName": "Russia", "fclName": "city, village,...", "fcode": "PPL", "adminName1": "Brjansk", "countryCode": "RU", "population": 0, "fcodeName": "populated place"}, "geometry": {"coordinates": [32.31206, 52.29781], "type": "Point"}, "type": "feature"}, {"properties": {"countryId": "2017370", "toponymName": "Staryy Ropsk", "adminCode1": "10", "geonameId": 487912, "fcl": "P", "name": "Staryy Ropsk", "countryName": "Russia", "fclName": "city, village,...", "fcode": "PPL", "adminName1": "Brjansk", "countryCode": "RU", "population": 0, "fcodeName": "populated place"}, "geometry": {"coordinates": [32.25882, 52.30876], "type": "Point"}, "type": "feature"}]}