{"type": "FeatureCollection", "features": [{"type": "Feature", "geometry": {"coordinates": [34.6822, 51.5655], "type": "Point"}, "properties": {"countryCode": "RU", "countryId": "2017370", "fcodeName": "populated place", "adminName1": "Kursk", "fclName": "city, village,...", "fcl": "P", "countryName": "Russia", "fcode": "PPL", "geonameId": 695019, "population": 17007, "adminCode1": "41", "name": "Ryl'sk", "toponymName": "Ryl\u2019sk"}}]}