{"features": [{"properties": {"hgr_name_modern_sp": "\u0420\u044b\u043b\u044c\u0441\u043a", "countryCode": "RU", "hgr_admin_hierarchy": "\u043a\u0443\u0440\u0441\u043a", "fcl": "P", "toponymName": "Ryl\u2019sk", "countryName": "Russia", "adminCode1": "41", "fcodeName": "populated place", "population": 17007, "hgr_partof_id": 15.0, "hgr_page": 99, "hgr_html_text": "\u0420\u042b\u041b\u042c\u0421\u041a\u042a, </span><span class=\"font0\" style=\"font-style:italic;\">\u0433\u043e\u0440\u043e\u0434\u044a</span><span class=\"font0\"> \u041a\u0443\u0440\u0441\u043a\u0430\u0433\u043e \u041d\u0430\u043c\u0463\u0441\u0442\u043d\u0438\u0447\u0435\u0441\u0442\u0432\u0430. \u0412\u044a \u043d\u0435\u043c\u044a , \u043a\u0440\u043e\u043c\u0463 \u0435\u0436\u0435\u043d\u0435\u0434\u0463\u043b\u044c\u043d\u044b\u0445\u044a \u043f\u043e \u043f\u043e\u043d\u0435\u0434\u0463\u043b\u044c\u043d\u0438\u043a\u0430\u043c\u044a \u0438 \u043f\u044f\u0442\u043d\u0438\u0446\u0430\u043c\u044a \u0442\u043e\u0440\u0433\u043e\u0432\u044a \u0431\u044b\u0432\u0430\u0435\u0442\u044a \u0432\u044a \u0433\u043e\u0434\u044a \u0434\u0432\u0463 \u044f\u0440\u043c\u0430\u0440\u043a\u0438: \u043f\u0435\u0440\u0432\u0430\u044f \u0432\u044a \u0434\u0435\u0441\u044f\u0442\u0443\u044e \u043f\u044f\u0442\u043d\u0438\u0446\u0443 \u043f\u043e \u041f\u0430\u0441\u0445\u0463, \u0430 \u0432\u0442\u043e\u0440\u0430\u044f \u0432\u044a \u0434\u0435\u043d\u044c \u041a\u0430\u0437\u0430\u043d\u0441\u043a\u0456\u044f \u0411\u043e\u0433\u043e\u043c\u0430\u0442\u0435\u0440\u0438 \u0406\u044e\u043b\u044f 8 \u0447\u0438\u0441\u043b\u0430 , \u043f\u043e \u043e\u0434\u043d\u043e\u043c\u0443 \u0434\u043d\u044e \u043f\u0440\u043e\u0434\u043e\u043b\u0436\u0430\u044e\u0449\u0456\u044f\u0441\u044f, \u043d\u0430 \u043a\u043e\u0442\u043e\u0440\u044b\u044f \u0441\u044a\u0463\u0437\u0436\u0430\u044e\u0442\u0441\u044f \u0438\u0437\u044a \u043e\u043a\u043e\u043b\u044c\u043d\u044b\u0445\u044a \u043c\u0463\u0441\u0442\u044a \u0441\u044a \u043c\u0463\u043b\u043a\u0438\u043c\u0438 \u0442\u043e\u0432\u0430\u0440\u0430\u043c\u0438.</span>", "UPDATE_SCRIPT": "python add_town_by_geoname_id.py \u0420\u044b\u043b\u044c\u0441\u043a_593.geojson 695019", "hgr_text": "\u0420\u042b\u041b\u042c\u0421\u041a\u042a, \u0433\u043e\u0440\u043e\u0434\u044a \u041a\u0443\u0440\u0441\u043a\u0430\u0433\u043e \u041d\u0430\u043c\u0463\u0441\u0442\u043d\u0438\u0447\u0435\u0441\u0442\u0432\u0430. \u0412\u044a \u043d\u0435\u043c\u044a , \u043a\u0440\u043e\u043c\u0463 \u0435\u0436\u0435\u043d\u0435\u0434\u0463\u043b\u044c\u043d\u044b\u0445\u044a \u043f\u043e \u043f\u043e\u043d\u0435\u0434\u0463\u043b\u044c\u043d\u0438\u043a\u0430\u043c\u044a \u0438 \u043f\u044f\u0442\u043d\u0438\u0446\u0430\u043c\u044a \u0442\u043e\u0440\u0433\u043e\u0432\u044a \u0431\u044b\u0432\u0430\u0435\u0442\u044a \u0432\u044a \u0433\u043e\u0434\u044a \u0434\u0432\u0463 \u044f\u0440\u043c\u0430\u0440\u043a\u0438: \u043f\u0435\u0440\u0432\u0430\u044f \u0432\u044a \u0434\u0435\u0441\u044f\u0442\u0443\u044e \u043f\u044f\u0442\u043d\u0438\u0446\u0443 \u043f\u043e \u041f\u0430\u0441\u0445\u0463, \u0430 \u0432\u0442\u043e\u0440\u0430\u044f \u0432\u044a \u0434\u0435\u043d\u044c \u041a\u0430\u0437\u0430\u043d\u0441\u043a\u0456\u044f \u0411\u043e\u0433\u043e\u043c\u0430\u0442\u0435\u0440\u0438 \u0406\u044e\u043b\u044f 8 \u0447\u0438\u0441\u043b\u0430 , \u043f\u043e \u043e\u0434\u043d\u043e\u043c\u0443 \u0434\u043d\u044e \u043f\u0440\u043e\u0434\u043e\u043b\u0436\u0430\u044e\u0449\u0456\u044f\u0441\u044f, \u043d\u0430 \u043a\u043e\u0442\u043e\u0440\u044b\u044f \u0441\u044a\u0463\u0437\u0436\u0430\u044e\u0442\u0441\u044f \u0438\u0437\u044a \u043e\u043a\u043e\u043b\u044c\u043d\u044b\u0445\u044a \u043c\u0463\u0441\u0442\u044a \u0441\u044a \u043c\u0463\u043b\u043a\u0438\u043c\u0438 \u0442\u043e\u0432\u0430\u0440\u0430\u043c\u0438.", "hgr_prov_modern_sp": "\u041a\u0443\u0440\u0441\u043a\u043e\u0433\u043e \u041d\u0430\u043c\u0435\u0441\u0442\u043d\u0438\u0447\u0435\u0441\u0442\u0432\u0430", "hgr_name": "\u0420\u044b\u043b\u044c\u0441\u043a\u044a", "name": "Ryl'sk", "hgr_ru_uezd": "not_in_text", "hgr_source_url": "http://babel.hathitrust.org/cgi/pt?id=uc1.b4583201;view=1up;seq=98", "countryId": "2017370", "hgr_ru_prov": "\u041a\u0443\u0440\u0441\u043a\u0430\u0433\u043e \u041d\u0430\u043c\u0463\u0441\u0442\u043d\u0438\u0447\u0435\u0441\u0442\u0432\u0430", "hgr_uezd_stem": "\u043d\u043e\u0442_\u0438\u043d_\u0442\u0435x\u0442", "hgr_admin1_partof": 15.0, "hgr_alt_name": null, "adminName1": "Kursk", "hgr_admin2_partof": null, "fcode": "PPL", "fclName": "city, village,...", "hgr_prov_stem": "\u043a\u0443\u0440\u0441\u043a", "geonameId": 695019, "hgr_type": "\u0433\u043e\u0440\u043e\u0434\u044a", "hgr_uezd_modern_sp": "not_\u0438n_text"}, "geometry": {"coordinates": [34.6822, 51.5655], "type": "Point"}, "type": "Feature"}], "type": "FeatureCollection"}