{"features": [{"properties": {"fcl": "P", "geonameId": 695019, "countryId": "2017370", "fcode": "PPL", "name": "Ryl'sk", "countryName": "Russia", "population": 17007, "fclName": "city, village,...", "adminName1": "Kursk", "adminCode1": "41", "fcodeName": "populated place", "countryCode": "RU", "toponymName": "Ryl\u2019sk"}, "geometry": {"coordinates": [34.6822, 51.5655], "type": "Point"}, "type": "Feature"}], "type": "FeatureCollection"}