{"type": "FeatureCollection", "features": [{"properties": {"countryId": "2017370", "toponymName": "Ryl\u2019sk", "adminCode1": "41", "geonameId": 695019, "fcl": "P", "name": "Ryl'sk", "countryName": "Russia", "fclName": "city, village,...", "fcode": "PPL", "adminName1": "Kursk", "countryCode": "RU", "population": 17007, "fcodeName": "populated place"}, "geometry": {"coordinates": [34.6822, 51.5655], "type": "Point"}, "type": "feature"}]}