{"type": "FeatureCollection", "features": [{"properties": {"countryId": "2017370", "toponymName": "Starodub", "adminCode1": "10", "geonameId": 488852, "fcl": "P", "name": "Starodub", "countryName": "Russia", "fclName": "city, village,...", "fcode": "PPL", "adminName1": "Brjansk", "countryCode": "RU", "population": 18539, "fcodeName": "populated place"}, "geometry": {"coordinates": [32.76333, 52.58444], "type": "Point"}, "type": "feature"}, {"properties": {"countryId": "690791", "toponymName": "Novyy Starodub", "adminCode1": "10", "geonameId": 698869, "fcl": "P", "name": "Novyy Starodub", "countryName": "Ukraine", "fclName": "city, village,...", "fcode": "PPL", "adminName1": "Kirovohrad", "countryCode": "UA", "population": 4777, "fcodeName": "populated place"}, "geometry": {"coordinates": [33.17329, 48.5158], "type": "Point"}, "type": "feature"}]}