{"type": "FeatureCollection", "features": [{"type": "Feature", "geometry": {"coordinates": [32.76333, 52.58444], "type": "Point"}, "properties": {"countryCode": "RU", "countryId": "2017370", "fcodeName": "populated place", "adminName1": "Brjansk", "fclName": "city, village,...", "fcl": "P", "countryName": "Russia", "fcode": "PPL", "geonameId": 488852, "population": 18539, "adminCode1": "10", "name": "Starodub", "toponymName": "Starodub"}}, {"type": "Feature", "geometry": {"coordinates": [33.17329, 48.5158], "type": "Point"}, "properties": {"countryCode": "UA", "countryId": "690791", "fcodeName": "populated place", "adminName1": "Kirovohrad", "fclName": "city, village,...", "fcl": "P", "countryName": "Ukraine", "fcode": "PPL", "geonameId": 698869, "population": 4777, "adminCode1": "10", "name": "Novyy Starodub", "toponymName": "Novyy Starodub"}}]}