{"features": [{"properties": {"fcl": "P", "geonameId": 488852, "countryId": "2017370", "fcode": "PPL", "name": "Starodub", "countryName": "Russia", "population": 18539, "fclName": "city, village,...", "adminName1": "Brjansk", "adminCode1": "10", "fcodeName": "populated place", "countryCode": "RU", "toponymName": "Starodub"}, "geometry": {"coordinates": [32.76333, 52.58444], "type": "Point"}, "type": "Feature"}, {"properties": {"fcl": "P", "geonameId": 698869, "countryId": "690791", "fcode": "PPL", "name": "Novyy Starodub", "countryName": "Ukraine", "population": 4777, "fclName": "city, village,...", "adminName1": "Kirovohrad", "adminCode1": "10", "fcodeName": "populated place", "countryCode": "UA", "toponymName": "Novyy Starodub"}, "geometry": {"coordinates": [33.17329, 48.5158], "type": "Point"}, "type": "Feature"}], "type": "FeatureCollection"}