{"type": "FeatureCollection", "features": [{"properties": {"countryId": "2017370", "toponymName": "Syzran\u2019", "adminCode1": "65", "geonameId": 484972, "fcl": "P", "name": "Syzran'", "countryName": "Russia", "fclName": "city, village,...", "fcode": "PPL", "adminName1": "Samara", "countryCode": "RU", "population": 189338, "fcodeName": "populated place"}, "geometry": {"coordinates": [48.4681, 53.1585], "type": "Point"}, "type": "feature"}, {"properties": {"countryId": "2017370", "toponymName": "Nizhnyaya Syzran\u2019", "adminCode1": "65", "geonameId": 520220, "fcl": "P", "name": "Nizhnyaya Syzran\u2019", "countryName": "Russia", "fclName": "city, village,...", "fcode": "PPL", "adminName1": "Samara", "countryCode": "RU", "population": 0, "fcodeName": "populated place"}, "geometry": {"coordinates": [48.56028, 53.0775], "type": "Point"}, "type": "feature"}, {"properties": {"countryId": "2017370", "toponymName": "Verkhnyaya Syzran\u2019", "adminCode1": "65", "geonameId": 474488, "fcl": "P", "name": "Verkhnyaya Syzran\u2019", "countryName": "Russia", "fclName": "city, village,...", "fcode": "PPL", "adminName1": "Samara", "countryCode": "RU", "population": 0, "fcodeName": "populated place"}, "geometry": {"coordinates": [48.6, 53.1], "type": "Point"}, "type": "feature"}]}