{"type": "FeatureCollection", "features": [{"type": "Feature", "geometry": {"coordinates": [48.4681, 53.1585], "type": "Point"}, "properties": {"countryCode": "RU", "countryId": "2017370", "fcodeName": "populated place", "adminName1": "Samara", "fclName": "city, village,...", "fcl": "P", "countryName": "Russia", "fcode": "PPL", "geonameId": 484972, "population": 189338, "adminCode1": "65", "name": "Syzran'", "toponymName": "Syzran\u2019"}}, {"type": "Feature", "geometry": {"coordinates": [48.56028, 53.0775], "type": "Point"}, "properties": {"countryCode": "RU", "countryId": "2017370", "fcodeName": "populated place", "adminName1": "Samara", "fclName": "city, village,...", "fcl": "P", "countryName": "Russia", "fcode": "PPL", "geonameId": 520220, "population": 0, "adminCode1": "65", "name": "Nizhnyaya Syzran\u2019", "toponymName": "Nizhnyaya Syzran\u2019"}}, {"type": "Feature", "geometry": {"coordinates": [48.6, 53.1], "type": "Point"}, "properties": {"countryCode": "RU", "countryId": "2017370", "fcodeName": "populated place", "adminName1": "Samara", "fclName": "city, village,...", "fcl": "P", "countryName": "Russia", "fcode": "PPL", "geonameId": 474488, "population": 0, "adminCode1": "65", "name": "Verkhnyaya Syzran\u2019", "toponymName": "Verkhnyaya Syzran\u2019"}}]}