{"features": [{"properties": {"fcl": "P", "geonameId": 484139, "countryId": "2017370", "fcode": "PPL", "name": "Tatarsk", "countryName": "Russia", "population": 0, "fclName": "city, village,...", "adminName1": "Smolensk", "adminCode1": "69", "fcodeName": "populated place", "countryCode": "RU", "toponymName": "Tatarsk"}, "geometry": {"coordinates": [31.56222, 54.25204], "type": "Point"}, "type": "Feature"}, {"properties": {"fcl": "P", "geonameId": 620955, "countryId": "630336", "fcode": "PPL", "name": "Tatarsk", "countryName": "Belarus", "population": 0, "fclName": "city, village,...", "adminName1": "Vitsyebskaya Voblasts\u02bc", "adminCode1": "07", "fcodeName": "populated place", "countryCode": "BY", "toponymName": "Tatarsk"}, "geometry": {"coordinates": [30.3256, 54.488], "type": "Point"}, "type": "Feature"}], "type": "FeatureCollection"}