{"type": "FeatureCollection", "features": [{"properties": {"countryId": "2017370", "toponymName": "Tatarsk", "adminCode1": "69", "geonameId": 484139, "fcl": "P", "name": "Tatarsk", "countryName": "Russia", "fclName": "city, village,...", "fcode": "PPL", "adminName1": "Smolensk", "countryCode": "RU", "population": 0, "fcodeName": "populated place"}, "geometry": {"coordinates": [31.56222, 54.25204], "type": "Point"}, "type": "feature"}, {"properties": {"countryId": "630336", "toponymName": "Tatarsk", "adminCode1": "07", "geonameId": 620955, "fcl": "P", "name": "Tatarsk", "countryName": "Belarus", "fclName": "city, village,...", "fcode": "PPL", "adminName1": "Vitsyebskaya Voblasts\u02bc", "countryCode": "BY", "population": 0, "fcodeName": "populated place"}, "geometry": {"coordinates": [30.3256, 54.488], "type": "Point"}, "type": "feature"}]}