{"type": "FeatureCollection", "features": [{"type": "Feature", "geometry": {"coordinates": [31.56222, 54.25204], "type": "Point"}, "properties": {"countryCode": "RU", "countryId": "2017370", "fcodeName": "populated place", "adminName1": "Smolensk", "fclName": "city, village,...", "fcl": "P", "countryName": "Russia", "fcode": "PPL", "geonameId": 484139, "population": 0, "adminCode1": "69", "name": "Tatarsk", "toponymName": "Tatarsk"}}, {"type": "Feature", "geometry": {"coordinates": [30.3256, 54.488], "type": "Point"}, "properties": {"countryCode": "BY", "countryId": "630336", "fcodeName": "populated place", "adminName1": "Vitsyebskaya Voblasts\u02bc", "fclName": "city, village,...", "fcl": "P", "countryName": "Belarus", "fcode": "PPL", "geonameId": 620955, "population": 0, "adminCode1": "07", "name": "Tatarsk", "toponymName": "Tatarsk"}}]}