{"features": [{"properties": {"fcl": "P", "geonameId": 1489530, "countryId": "2017370", "fcode": "PPL", "name": "Tobol'sk", "countryName": "Russia", "population": 113800, "fclName": "city, village,...", "adminName1": "Tjumen", "adminCode1": "78", "fcodeName": "populated place", "countryCode": "RU", "toponymName": "Tobol\u2019sk"}, "geometry": {"coordinates": [68.25457, 58.19807], "type": "Point"}, "type": "Feature"}], "type": "FeatureCollection"}