{"type": "FeatureCollection", "features": [{"properties": {"countryId": "2017370", "toponymName": "Tobol\u2019sk", "adminCode1": "78", "geonameId": 1489530, "fcl": "P", "name": "Tobol'sk", "countryName": "Russia", "fclName": "city, village,...", "fcode": "PPL", "adminName1": "Tjumen", "countryCode": "RU", "population": 113800, "fcodeName": "populated place"}, "geometry": {"coordinates": [68.25457, 58.19807], "type": "Point"}, "type": "feature"}]}