{"type": "FeatureCollection", "features": [{"type": "Feature", "geometry": {"coordinates": [68.25457, 58.19807], "type": "Point"}, "properties": {"countryCode": "RU", "countryId": "2017370", "fcodeName": "populated place", "adminName1": "Tjumen", "fclName": "city, village,...", "fcl": "P", "countryName": "Russia", "fcode": "PPL", "geonameId": 1489530, "population": 113800, "adminCode1": "78", "name": "Tobol'sk", "toponymName": "Tobol\u2019sk"}}]}