{"type": "FeatureCollection", "features": [{"geometry": {"coordinates": [35.69636, 54.51837], "type": "Point"}, "properties": {"adminCode1": "25", "population": 0, "countryId": "2017370", "fcl": "P", "countryCode": "RU", "toponymName": "Utesh\u00ebvo", "geonameId": 477746, "fclName": "city, village,...", "adminName1": "Kaluga", "fcode": "PPL", "fcodeName": "populated place", "name": "Utesh\u00ebvo", "countryName": "Russia"}, "type": "Feature"}, {"geometry": {"coordinates": [35.69583, 54.93278], "type": "Point"}, "properties": {"adminCode1": "25", "population": 0, "countryId": "2017370", "fcl": "P", "countryCode": "RU", "toponymName": "Uteshevo", "geonameId": 815697, "fclName": "city, village,...", "adminName1": "Kaluga", "fcode": "PPL", "fcodeName": "populated place", "name": "Uteshevo", "countryName": "Russia"}, "type": "Feature"}]}