{"type": "FeatureCollection", "features": [{"geometry": {"coordinates": [44.4937, 52.8628], "type": "Point"}, "properties": {"adminCode1": "57", "population": 0, "countryId": "2017370", "fcl": "P", "countryCode": "RU", "toponymName": "Khop\u00ebr", "geonameId": 6845881, "fclName": "city, village,...", "adminName1": "Penza", "fcode": "PPL", "fcodeName": "populated place", "name": "Khop\u00ebr", "countryName": "Russia"}, "type": "Feature"}, {"geometry": {"coordinates": [42.96939, 51.4987], "type": "Point"}, "properties": {"adminCode1": "67", "population": 0, "countryId": "2017370", "fcl": "P", "countryCode": "RU", "toponymName": "Staryy Khop\u00ebr", "geonameId": 487968, "fclName": "city, village,...", "adminName1": "Saratov", "fcode": "PPL", "fcodeName": "populated place", "name": "Staryy Khop\u00ebr", "countryName": "Russia"}, "type": "Feature"}]}