{"features": [{"geometry": {"type": "Point", "coordinates": [44.4937, 52.8628]}, "properties": {"adminCode1": "57", "fclName": "city, village,...", "fcodeName": "populated place", "fcode": "PPL", "fcl": "P", "adminName1": "Penza", "population": 0, "geonameId": 6845881, "countryName": "Russia", "toponymName": "Khop\u00ebr", "countryCode": "RU", "countryId": "2017370", "name": "Khop\u00ebr"}, "type": "Feature"}, {"geometry": {"type": "Point", "coordinates": [42.96939, 51.4987]}, "properties": {"adminCode1": "67", "fclName": "city, village,...", "fcodeName": "populated place", "fcode": "PPL", "fcl": "P", "adminName1": "Saratov", "population": 0, "geonameId": 487968, "countryName": "Russia", "toponymName": "Staryy Khop\u00ebr", "countryCode": "RU", "countryId": "2017370", "name": "Staryy Khop\u00ebr"}, "type": "Feature"}], "type": "FeatureCollection"}