{"type": "FeatureCollection", "features": [{"properties": {"countryId": "690791", "toponymName": "Khotin\u2019", "adminCode1": "21", "geonameId": 706253, "fcl": "P", "name": "Khotin'", "countryName": "Ukraine", "fclName": "city, village,...", "fcode": "PPL", "adminName1": "Sumy", "countryCode": "UA", "population": 0, "fcodeName": "populated place"}, "geometry": {"coordinates": [34.77089, 51.08113], "type": "Point"}, "type": "feature"}]}