{"type": "FeatureCollection", "features": [{"properties": {"adminName1": "Penza", "population": 0, "countryId": "2017370", "toponymName": "Khop\u00ebr", "countryCode": "RU", "adminCode1": "57", "name": "Khop\u00ebr", "geonameId": 6845881, "fcode": "PPL", "fcl": "P", "fcodeName": "populated place", "fclName": "city, village,...", "countryName": "Russia"}, "type": "Feature", "geometry": {"type": "Point", "coordinates": [44.4937, 52.8628]}}, {"properties": {"adminName1": "Saratov", "population": 0, "countryId": "2017370", "toponymName": "Staryy Khop\u00ebr", "countryCode": "RU", "adminCode1": "67", "name": "Staryy Khop\u00ebr", "geonameId": 487968, "fcode": "PPL", "fcl": "P", "fcodeName": "populated place", "fclName": "city, village,...", "countryName": "Russia"}, "type": "Feature", "geometry": {"type": "Point", "coordinates": [42.96939, 51.4987]}}]}