{"features": [{"properties": {"hgr_name_modern_sp": "\u0425\u043e\u0442\u0435\u043d\u044c", "countryCode": "UA", "hgr_admin_hierarchy": "\u0445\u0430\u0440\u044c\u043a\u043e\u0432\u0441\u043a|\u0441\u0443\u043c\u0441\u043a", "fcl": "P", "toponymName": "Khotin\u2019", "countryName": "Ukraine", "adminCode1": "21", "fcodeName": "populated place", "population": 0, "hgr_partof_id": 284.0, "hgr_page": 124, "hgr_html_text": "\u0425\u041e\u0422\u0415\u041d\u042c , </span><span class=\"font0\" style=\"font-style:italic;\">\u0441\u0435\u043b\u043e</span><span class=\"font0\"> \u0425\u0430\u0440\u044c\u043a\u043e\u0432\u0441\u043a\u0430\u0433\u043e \u041d\u0430\u043c\u0463\u0441\u0442\u043d\u0438\u0447\u0435\u0441\u0442\u0432\u0430 \u0432\u044a \u0421\u0443\u043c\u0441\u043a\u043e\u043c\u044a \u0443\u0463\u0437\u0434\u0463. \u0412\u044a \u043e\u043d\u043e\u043c\u044a \u0431\u044b\u0432\u0430\u044e\u0442\u044a \u0432\u044a \u0433\u043e\u0434\u0443 \u0442\u0440\u0438 \u044f\u0440\u043c\u0430\u0440\u043a\u0438; \u043d\u0430 \u043a\u043e\u0442\u043e\u0440\u044b\u044f \u043a\u0443\u043f\u0446\u044b \u043f\u0440\u0456\u0463\u0437\u0436\u0430\u044e\u0442\u044a \u0441\u044a \u043c\u0463\u0434\u043e\u0447\u043d\u044b\u043c\u0438 \u0442\u043e\u0432\u0430\u0440\u0430\u043c\u0438 \u0438 \u0433\u043e\u0440\u044f\u0447\u0438\u043c\u044a \u0432\u0438\u0434\u043e\u043c\u044a.</span>", "UPDATE_SCRIPT": "python add_town_by_geoname_id.py \u0425\u043e\u0442\u0435\u043d\u044c_742.geojson 706253", "hgr_text": "\u0425\u041e\u0422\u0415\u041d\u042c , \u0441\u0435\u043b\u043e \u0425\u0430\u0440\u044c\u043a\u043e\u0432\u0441\u043a\u0430\u0433\u043e \u041d\u0430\u043c\u0463\u0441\u0442\u043d\u0438\u0447\u0435\u0441\u0442\u0432\u0430 \u0432\u044a \u0421\u0443\u043c\u0441\u043a\u043e\u043c\u044a \u0443\u0463\u0437\u0434\u0463. \u0412\u044a \u043e\u043d\u043e\u043c\u044a \u0431\u044b\u0432\u0430\u044e\u0442\u044a \u0432\u044a \u0433\u043e\u0434\u0443 \u0442\u0440\u0438 \u044f\u0440\u043c\u0430\u0440\u043a\u0438; \u043d\u0430 \u043a\u043e\u0442\u043e\u0440\u044b\u044f \u043a\u0443\u043f\u0446\u044b \u043f\u0440\u0456\u0463\u0437\u0436\u0430\u044e\u0442\u044a \u0441\u044a \u043c\u0463\u0434\u043e\u0447\u043d\u044b\u043c\u0438 \u0442\u043e\u0432\u0430\u0440\u0430\u043c\u0438 \u0438 \u0433\u043e\u0440\u044f\u0447\u0438\u043c\u044a \u0432\u0438\u0434\u043e\u043c\u044a.", "hgr_prov_modern_sp": "\u0425\u0430\u0440\u044c\u043a\u043e\u0432\u0441\u043a\u043e\u0433\u043e \u041d\u0430\u043c\u0435\u0441\u0442\u043d\u0438\u0447\u0435\u0441\u0442\u0432\u0430", "hgr_name": "\u0425\u043e\u0442\u0435\u043d\u044c", "name": "Khotin'", "hgr_ru_uezd": "\u0421\u0443\u043c\u0441\u043a\u043e\u043c\u044a \u0443\u0463\u0437\u0434\u0463", "hgr_source_url": "http://babel.hathitrust.org/cgi/pt?id=uc1.b4583201;view=1up;seq=123", "countryId": "690791", "hgr_ru_prov": "\u0425\u0430\u0440\u044c\u043a\u043e\u0432\u0441\u043a\u0430\u0433\u043e \u041d\u0430\u043c\u0463\u0441\u0442\u043d\u0438\u0447\u0435\u0441\u0442\u0432\u0430", "hgr_uezd_stem": "\u0441\u0443\u043c\u0441\u043a", "hgr_admin1_partof": 37.0, "hgr_alt_name": null, "adminName1": "Sumy", "hgr_admin2_partof": 284.0, "fcode": "PPL", "fclName": "city, village,...", "hgr_prov_stem": "\u0445\u0430\u0440\u044c\u043a\u043e\u0432\u0441\u043a", "geonameId": 706253, "hgr_type": "\u0441\u0435\u043b\u043e", "hgr_uezd_modern_sp": "\u0421\u0443\u043c\u0441\u043a\u043e\u043c \u0443\u0435\u0437\u0434\u0435"}, "geometry": {"coordinates": [34.77089, 51.08113], "type": "Point"}, "type": "Feature"}], "type": "FeatureCollection"}