{"type": "FeatureCollection", "features": [{"type": "Feature", "geometry": {"coordinates": [34.77089, 51.08113], "type": "Point"}, "properties": {"countryCode": "UA", "countryId": "690791", "fcodeName": "populated place", "adminName1": "Sumy", "fclName": "city, village,...", "fcl": "P", "countryName": "Ukraine", "fcode": "PPL", "geonameId": 706253, "population": 0, "adminCode1": "21", "name": "Khotin'", "toponymName": "Khotin\u2019"}}]}