{"type": "FeatureCollection", "features": [{"type": "Feature", "geometry": {"coordinates": [44.4937, 52.8628], "type": "Point"}, "properties": {"countryCode": "RU", "countryId": "2017370", "fcodeName": "populated place", "adminName1": "Penza", "fclName": "city, village,...", "fcl": "P", "countryName": "Russia", "fcode": "PPL", "geonameId": 6845881, "population": 0, "adminCode1": "57", "name": "Khop\u00ebr", "toponymName": "Khop\u00ebr"}}, {"type": "Feature", "geometry": {"coordinates": [42.96939, 51.4987], "type": "Point"}, "properties": {"countryCode": "RU", "countryId": "2017370", "fcodeName": "populated place", "adminName1": "Saratov", "fclName": "city, village,...", "fcl": "P", "countryName": "Russia", "fcode": "PPL", "geonameId": 487968, "population": 0, "adminCode1": "67", "name": "Staryy Khop\u00ebr", "toponymName": "Staryy Khop\u00ebr"}}]}