{"features": [{"properties": {"fcl": "P", "geonameId": 6845881, "countryId": "2017370", "fcode": "PPL", "name": "Khop\u00ebr", "countryName": "Russia", "population": 0, "fclName": "city, village,...", "adminName1": "Penza", "adminCode1": "57", "fcodeName": "populated place", "countryCode": "RU", "toponymName": "Khop\u00ebr"}, "geometry": {"coordinates": [44.4937, 52.8628], "type": "Point"}, "type": "Feature"}, {"properties": {"fcl": "P", "geonameId": 487968, "countryId": "2017370", "fcode": "PPL", "name": "Staryy Khop\u00ebr", "countryName": "Russia", "population": 0, "fclName": "city, village,...", "adminName1": "Saratov", "adminCode1": "67", "fcodeName": "populated place", "countryCode": "RU", "toponymName": "Staryy Khop\u00ebr"}, "geometry": {"coordinates": [42.96939, 51.4987], "type": "Point"}, "type": "Feature"}], "type": "FeatureCollection"}