{"type": "FeatureCollection", "features": [{"properties": {"countryId": "2017370", "toponymName": "Khop\u00ebr", "adminCode1": "57", "geonameId": 6845881, "fcl": "P", "name": "Khop\u00ebr", "countryName": "Russia", "fclName": "city, village,...", "fcode": "PPL", "adminName1": "Penza", "countryCode": "RU", "population": 0, "fcodeName": "populated place"}, "geometry": {"coordinates": [44.4937, 52.8628], "type": "Point"}, "type": "feature"}, {"properties": {"countryId": "2017370", "toponymName": "Staryy Khop\u00ebr", "adminCode1": "67", "geonameId": 487968, "fcl": "P", "name": "Staryy Khop\u00ebr", "countryName": "Russia", "fclName": "city, village,...", "fcode": "PPL", "adminName1": "Saratov", "countryCode": "RU", "population": 0, "fcodeName": "populated place"}, "geometry": {"coordinates": [42.96939, 51.4987], "type": "Point"}, "type": "feature"}]}