{"type": "FeatureCollection", "features": [{"type": "Feature", "geometry": {"coordinates": [30.9179, 52.9164], "type": "Point"}, "properties": {"countryCode": "BY", "countryId": "630336", "fcodeName": "populated place", "adminName1": "Gomel", "fclName": "city, village,...", "fcl": "P", "countryName": "Belarus", "fcode": "PPL", "geonameId": 629390, "population": 7600, "adminCode1": "02", "name": "Chachersk", "toponymName": "Chachersk"}}]}