{"type": "FeatureCollection", "features": [{"type": "Feature", "geometry": {"coordinates": [36.9145, 53.45232], "type": "Point"}, "properties": {"countryCode": "RU", "countryId": "2017370", "fcodeName": "populated place", "adminName1": "Tula", "fclName": "city, village,...", "fcl": "P", "countryName": "Russia", "fcode": "PPL", "geonameId": 569116, "population": 6689, "adminCode1": "76", "name": "Chern'", "toponymName": "Chern\u2019"}}, {"type": "Feature", "geometry": {"coordinates": [35.85475, 53.47326], "type": "Point"}, "properties": {"countryCode": "RU", "countryId": "2017370", "fcodeName": "populated place", "adminName1": "Orjol", "fclName": "city, village,...", "fcl": "P", "countryName": "Russia", "fcode": "PPL", "geonameId": 531711, "population": 0, "adminCode1": "56", "name": "Chern\u2019 Pal\u2019chikovo", "toponymName": "Chern\u2019 Pal\u2019chikovo"}}, {"type": "Feature", "geometry": {"coordinates": [35.8539, 53.35256], "type": "Point"}, "properties": {"countryCode": "RU", "countryId": "2017370", "fcodeName": "populated place", "adminName1": "Orjol", "fclName": "city, village,...", "fcl": "P", "countryName": "Russia", "fcode": "PPL", "geonameId": 575175, "population": 0, "adminCode1": "56", "name": "Bol\u2019shaya Chern\u2019", "toponymName": "Bol\u2019shaya Chern\u2019"}}]}