{"features": [{"properties": {"fcl": "P", "geonameId": 629390, "countryId": "630336", "fcode": "PPL", "name": "Chachersk", "countryName": "Belarus", "population": 7600, "fclName": "city, village,...", "adminName1": "Gomel", "adminCode1": "02", "fcodeName": "populated place", "countryCode": "BY", "toponymName": "Chachersk"}, "geometry": {"coordinates": [30.9179, 52.9164], "type": "Point"}, "type": "Feature"}], "type": "FeatureCollection"}