{"type": "FeatureCollection", "features": [{"properties": {"countryId": "630336", "toponymName": "Chachersk", "adminCode1": "02", "geonameId": 629390, "fcl": "P", "name": "Chachersk", "countryName": "Belarus", "fclName": "city, village,...", "fcode": "PPL", "adminName1": "Gomel", "countryCode": "BY", "population": 7600, "fcodeName": "populated place"}, "geometry": {"coordinates": [30.9179, 52.9164], "type": "Point"}, "type": "feature"}]}