{"type": "FeatureCollection", "features": [{"properties": {"countryId": "2017370", "toponymName": "Chern\u2019", "adminCode1": "76", "geonameId": 569116, "fcl": "P", "name": "Chern'", "countryName": "Russia", "fclName": "city, village,...", "fcode": "PPL", "adminName1": "Tula", "countryCode": "RU", "population": 6689, "fcodeName": "populated place"}, "geometry": {"coordinates": [36.9145, 53.45232], "type": "Point"}, "type": "feature"}, {"properties": {"countryId": "2017370", "toponymName": "Chern\u2019 Pal\u2019chikovo", "adminCode1": "56", "geonameId": 531711, "fcl": "P", "name": "Chern\u2019 Pal\u2019chikovo", "countryName": "Russia", "fclName": "city, village,...", "fcode": "PPL", "adminName1": "Orjol", "countryCode": "RU", "population": 0, "fcodeName": "populated place"}, "geometry": {"coordinates": [35.85475, 53.47326], "type": "Point"}, "type": "feature"}, {"properties": {"countryId": "2017370", "toponymName": "Bol\u2019shaya Chern\u2019", "adminCode1": "56", "geonameId": 575175, "fcl": "P", "name": "Bol\u2019shaya Chern\u2019", "countryName": "Russia", "fclName": "city, village,...", "fcode": "PPL", "adminName1": "Orjol", "countryCode": "RU", "population": 0, "fcodeName": "populated place"}, "geometry": {"coordinates": [35.8539, 53.35256], "type": "Point"}, "type": "feature"}]}