{"features": [{"type": "Feature", "geometry": {"coordinates": [30.9179, 52.9164], "type": "Point"}, "properties": {"hgr_name_modern_sp": "\u0427\u0435\u0447\u0435\u0440\u0441\u043a", "hgr_uezd_stem": "\u0440\u043e\u0433\u0430\u0447\u0435\u0432", "hgr_admin_hierarchy": "\u043c\u043e\u0433\u0438\u043b\u0435\u0432\u0441\u043a|\u0440\u043e\u0433\u0430\u0447\u0435\u0432", "hgr_admin1_partof": 16.0, "toponymName": "Chachersk", "hgr_html_text": "\u0427\u0415\u0427\u0415\u0420\u0421\u041a\u042a, </span><span class=\"font0\" style=\"font-style:italic;\">\u043c\u0463\u0441\u0442\u0435\u0447\u043a\u043e</span><span class=\"font0\"> \u041c\u043e\u0433\u0438\u043b\u0435\u0432\u0441\u043a\u0430\u0433\u043e \u041d\u0430\u043c\u0463\u0441\u0442\u043d\u0438\u0447\u0435\u0441\u0442\u0432\u0430 \u0432\u044a \u0443\u0463\u0437\u0434\u0463 \u0433\u043e\u0440\u043e\u0434\u0430 \u0420\u043e\u0433\u0430\u0447\u0435\u0432\u0430. \u0417\u0434\u0463\u0441\u044c \u0431\u044b\u0432\u0430\u0435\u0442\u044a \u0432\u044a \u0433\u043e\u0434\u0443 \u0442\u0440\u0438 \u044f\u0440\u043c\u0430\u0440\u043a\u0438: \u043f\u0435\u0440\u0432\u0430\u044f \u0413\u0435\u043d\u0432\u0430\u0440\u044f 8, \u0432\u0442\u043e\u0440\u0430\u044f \u0421\u0435\u043d\u0442\u044f\u0431\u0440\u044f 8, \u0442\u0440\u0435\u0442\u0456\u044f \u0432\u044a \u0434\u0435\u043d\u044c \u0412\u043e\u0437\u043d\u0435\u0441\u0435\u043d\u0456\u044f.</span>", "adminCode1": "02", "fcodeName": "populated place", "fcode": "PPL", "hgr_partof_id": 113.0, "hgr_page": 127, "countryName": "Belarus", "hgr_text": "\u0427\u0415\u0427\u0415\u0420\u0421\u041a\u042a, \u043c\u0463\u0441\u0442\u0435\u0447\u043a\u043e \u041c\u043e\u0433\u0438\u043b\u0435\u0432\u0441\u043a\u0430\u0433\u043e \u041d\u0430\u043c\u0463\u0441\u0442\u043d\u0438\u0447\u0435\u0441\u0442\u0432\u0430 \u0432\u044a \u0443\u0463\u0437\u0434\u0463 \u0433\u043e\u0440\u043e\u0434\u0430 \u0420\u043e\u0433\u0430\u0447\u0435\u0432\u0430. \u0417\u0434\u0463\u0441\u044c \u0431\u044b\u0432\u0430\u0435\u0442\u044a \u0432\u044a \u0433\u043e\u0434\u0443 \u0442\u0440\u0438 \u044f\u0440\u043c\u0430\u0440\u043a\u0438: \u043f\u0435\u0440\u0432\u0430\u044f \u0413\u0435\u043d\u0432\u0430\u0440\u044f 8, \u0432\u0442\u043e\u0440\u0430\u044f \u0421\u0435\u043d\u0442\u044f\u0431\u0440\u044f 8, \u0442\u0440\u0435\u0442\u0456\u044f \u0432\u044a \u0434\u0435\u043d\u044c \u0412\u043e\u0437\u043d\u0435\u0441\u0435\u043d\u0456\u044f.", "hgr_prov_modern_sp": "\u041c\u043e\u0433\u0438\u043b\u0435\u0432\u0441\u043a\u043e\u0433\u043e \u041d\u0430\u043c\u0435\u0441\u0442\u043d\u0438\u0447\u0435\u0441\u0442\u0432\u0430", "hgr_name": "\u0427\u0435\u0447\u0435\u0440\u0441\u043a\u044a", "name": "Chachersk", "hgr_ru_uezd": "\u0420\u043e\u0433\u0430\u0447\u0435\u0432\u0430", "population": 7600, "countryId": "630336", "hgr_ru_prov": "\u041c\u043e\u0433\u0438\u043b\u0435\u0432\u0441\u043a\u0430\u0433\u043e \u041d\u0430\u043c\u0463\u0441\u0442\u043d\u0438\u0447\u0435\u0441\u0442\u0432\u0430", "hgr_source_url": "http://babel.hathitrust.org/cgi/pt?id=uc1.b4583201;view=1up;seq=126", "fcl": "P", "hgr_alt_name": null, "adminName1": "Gomel", "hgr_admin2_partof": 113.0, "hgr_prov_stem": "\u043c\u043e\u0433\u0438\u043b\u0435\u0432\u0441\u043a", "fclName": "city, village,...", "countryCode": "BY", "geonameId": 629390, "hgr_type": "\u043c\u0463\u0441\u0442\u0435\u0447\u043a\u043e", "hgr_uezd_modern_sp": "\u0420\u043e\u0433\u0430\u0447\u0435\u0432\u0430"}}], "type": "FeatureCollection"}