{"type": "FeatureCollection", "features": [{"type": "Feature", "geometry": {"coordinates": [34.58107, 50.3766], "type": "Point"}, "properties": {"countryCode": "UA", "countryId": "690791", "fcodeName": "populated place", "adminName1": "Sumy", "fclName": "city, village,...", "fcl": "P", "countryName": "Ukraine", "fcode": "PPL", "geonameId": 710353, "population": 0, "adminCode1": "21", "name": "Chupakhovka", "toponymName": "Chupakhivka"}}]}