{"type": "FeatureCollection", "features": [{"properties": {"countryId": "690791", "toponymName": "Chupakhivka", "adminCode1": "21", "geonameId": 710353, "fcl": "P", "name": "Chupakhovka", "countryName": "Ukraine", "fclName": "city, village,...", "fcode": "PPL", "adminName1": "Sumy", "countryCode": "UA", "population": 0, "fcodeName": "populated place"}, "geometry": {"coordinates": [34.58107, 50.3766], "type": "Point"}, "type": "feature"}]}