{"type": "FeatureCollection", "features": [{"type": "Feature", "geometry": {"coordinates": [34.58107, 50.3766], "type": "Point"}, "properties": {"countryCode": "UA", "countryId": "690791", "fcodeName": "populated place", "adminName1": "Sumy", "fclName": "city, village,...", "fcl": "P", "countryName": "Ukraine", "fcode": "PPL", "geonameId": 710353, "population": 0, "adminCode1": "21", "name": "Chupakhovka", "toponymName": "Chupakhivka"}}]}{"features": [{"properties": {"hgr_partof_id": null, "population": 0, "hgr_alt_name": null, "geonameId": 710353, "hgr_uezd_stem": "\u043d\u043e\u0442_\u0438\u043d_\u0442\u0435x\u0442", "hgr_prov_modern_sp": "not_\u0438n_text", "adminCode1": "21", "hgr_prov_stem": "\u043d\u043e\u0442_\u0438\u043d_\u0442\u0435x\u0442", "hgr_text": "\u0427\u0423\u041f\u0410\u0425\u041e\u0412\u041a\u0410, \u0441\u043b\u043e\u0431\u043e\u0434\u0430 \u043e\u043a\u043e\u043b\u043e \u0431\u044b\u0432\u0448\u0430\u0433\u043e \u0433\u043e\u0440\u043e\u0434\u043a\u0430 \u0410\u043b\u0435\u0448\u043d\u0438. \u0412\u044a \u043e\u043d\u043e\u0439 \u0431\u044b\u0432\u0430\u044e\u0442\u044a \u0442\u0440\u0438 \u044f\u0440\u043c\u0430\u0440\u043a\u0438 : \u043f\u0435\u0440\u0432\u0430\u044f \u0410\u043f\u0440\u0463\u043b\u044f 23, \u0432\u0442\u043e\u0440\u0430\u044f \u0421\u0435\u043d\u0442\u044f\u0431\u0440\u044f 8, \u0442\u0440\u0435\u0442\u0456\u044f \u041d\u043e\u044f\u0431\u0440\u044f 21 \u0434\u043d\u044f. \u041d\u0430 \u043e\u043d\u044b\u044f \u043f\u0440\u0456\u0463\u0437\u0436\u0430\u044e\u0442\u044a \u043a\u0443\u043f\u0446\u044b \u0438\u0437\u044a \u0431\u043b\u0438\u0437\u044a \u043b\u0435\u0436\u0430\u0449\u0438\u0445\u044a \u0433\u043e\u0440\u043e\u0434\u043e\u0432\u044a; \u0442\u043e\u0440\u0433\u0443\u044e\u0442\u044a \u0441\u0443\u043a\u043d\u0430\u043c\u0438 , \u0448\u0435\u043b\u043a\u043e\u0432\u044b\u043c\u0438 , \u0431\u0443\u043c\u0430\u0436\u043d\u044b\u043c\u0438 \u0438 \u043d\u0430\u0431\u043e\u0439\u0447\u0430\u0442\u044b\u043c\u0438 \u0442\u043e\u0432\u0430\u0440\u0430\u043c\u0438 , \u0436\u0435\u043b\u0463\u0437\u043e\u043c\u044a , \u043f\u043e\u043b\u043e\u0442\u043d\u043e\u043c\u044a, \u043f\u043e\u0441\u0443\u0434\u043e\u044e \u0438 \u043f\u0440\u043e\u0447\u0438\u043c\u044a.", "fcode": "PPL", "hgr_ru_uezd": "not_in_text", "name": "Chupakhovka", "hgr_html_text": "\u0427\u0423\u041f\u0410\u0425\u041e\u0412\u041a\u0410, </span><span class=\"font0\" style=\"font-style:italic;\">\u0441\u043b\u043e\u0431\u043e\u0434\u0430</span><span class=\"font0\"> \u043e\u043a\u043e\u043b\u043e \u0431\u044b\u0432\u0448\u0430\u0433\u043e \u0433\u043e\u0440\u043e\u0434\u043a\u0430 \u0410\u043b\u0435\u0448\u043d\u0438. \u0412\u044a \u043e\u043d\u043e\u0439 \u0431\u044b\u0432\u0430\u044e\u0442\u044a \u0442\u0440\u0438 \u044f\u0440\u043c\u0430\u0440\u043a\u0438 : \u043f\u0435\u0440\u0432\u0430\u044f \u0410\u043f\u0440\u0463\u043b\u044f 23, \u0432\u0442\u043e\u0440\u0430\u044f \u0421\u0435\u043d\u0442\u044f\u0431\u0440\u044f 8, \u0442\u0440\u0435\u0442\u0456\u044f \u041d\u043e\u044f\u0431\u0440\u044f 21 \u0434\u043d\u044f. \u041d\u0430 \u043e\u043d\u044b\u044f \u043f\u0440\u0456\u0463\u0437\u0436\u0430\u044e\u0442\u044a \u043a\u0443\u043f\u0446\u044b \u0438\u0437\u044a \u0431\u043b\u0438\u0437\u044a \u043b\u0435\u0436\u0430\u0449\u0438\u0445\u044a \u0433\u043e\u0440\u043e\u0434\u043e\u0432\u044a; \u0442\u043e\u0440\u0433\u0443\u044e\u0442\u044a \u0441\u0443\u043a\u043d\u0430\u043c\u0438 , \u0448\u0435\u043b\u043a\u043e\u0432\u044b\u043c\u0438 , \u0431\u0443\u043c\u0430\u0436\u043d\u044b\u043c\u0438 \u0438 \u043d\u0430\u0431\u043e\u0439\u0447\u0430\u0442\u044b\u043c\u0438 \u0442\u043e\u0432\u0430\u0440\u0430\u043c\u0438 , \u0436\u0435\u043b\u0463\u0437\u043e\u043c\u044a , \u043f\u043e\u043b\u043e\u0442\u043d\u043e\u043c\u044a, \u043f\u043e\u0441\u0443\u0434\u043e\u044e \u0438 \u043f\u0440\u043e\u0447\u0438\u043c\u044a.</span>", "countryName": "Ukraine", "toponymName": "Chupakhivka", "hgr_uezd_modern_sp": "not_\u0438n_text", "hgr_ru_prov": "not_in_text", "hgr_admin_hierarchy": "\u043d\u043e\u0442_\u0438\u043d_\u0442\u0435x\u0442", "hgr_admin2_partof": null, "countryId": "690791", "fcodeName": "populated place", "countryCode": "UA", "hgr_page": 128, "fcl": "P", "hgr_partof_prov_name": "None", "hgr_name": "\u0427\u0443\u043f\u0430\u0445\u043e\u0432\u043a\u0430", "hgr_source_url": "http://babel.hathitrust.org/cgi/pt?id=uc1.b4583201;view=1up;seq=127", "adminName1": "Sumy", "hgr_type": "\u0441\u043b\u043e\u0431\u043e\u0434\u0430", "hgr_name_modern_sp": "\u0427\u0443\u043f\u0430\u0445\u043e\u0432\u043a\u0430", "fclName": "city, village,...", "hgr_admin1_partof": null}, "geometry": {"coordinates": [34.58107, 50.3766], "type": "Point"}, "type": "Feature"}], "type": "FeatureCollection"}