{"features": [{"properties": {"fcl": "P", "geonameId": 1492517, "countryId": "2017370", "fcode": "PPL", "name": "Shadrinsk", "countryName": "Russia", "population": 79479, "fclName": "city, village,...", "adminName1": "Kurgan", "adminCode1": "40", "fcodeName": "populated place", "countryCode": "RU", "toponymName": "Shadrinsk"}, "geometry": {"coordinates": [63.6335, 56.0852], "type": "Point"}, "type": "Feature"}, {"properties": {"fcl": "P", "geonameId": 8059303, "countryId": "2017370", "fcode": "PPL", "name": "Shadrinsk", "countryName": "Russia", "population": 0, "fclName": "city, village,...", "adminName1": "Bashkortostan", "adminCode1": "08", "fcodeName": "populated place", "countryCode": "RU", "toponymName": "Shadrinsk"}, "geometry": {"coordinates": [59.3258, 55.5781], "type": "Point"}, "type": "Feature"}], "type": "FeatureCollection"}