{"type": "FeatureCollection", "features": [{"type": "Feature", "geometry": {"coordinates": [63.6335, 56.0852], "type": "Point"}, "properties": {"countryCode": "RU", "countryId": "2017370", "fcodeName": "populated place", "adminName1": "Kurgan", "fclName": "city, village,...", "fcl": "P", "countryName": "Russia", "fcode": "PPL", "geonameId": 1492517, "population": 79479, "adminCode1": "40", "name": "Shadrinsk", "toponymName": "Shadrinsk"}}, {"type": "Feature", "geometry": {"coordinates": [59.3258, 55.5781], "type": "Point"}, "properties": {"countryCode": "RU", "countryId": "2017370", "fcodeName": "populated place", "adminName1": "Bashkortostan", "fclName": "city, village,...", "fcl": "P", "countryName": "Russia", "fcode": "PPL", "geonameId": 8059303, "population": 0, "adminCode1": "08", "name": "Shadrinsk", "toponymName": "Shadrinsk"}}]}