{"type": "FeatureCollection", "features": [{"properties": {"countryId": "2017370", "toponymName": "Shadrinsk", "adminCode1": "40", "geonameId": 1492517, "fcl": "P", "name": "Shadrinsk", "countryName": "Russia", "fclName": "city, village,...", "fcode": "PPL", "adminName1": "Kurgan", "countryCode": "RU", "population": 79479, "fcodeName": "populated place"}, "geometry": {"coordinates": [63.6335, 56.0852], "type": "Point"}, "type": "feature"}, {"properties": {"countryId": "2017370", "toponymName": "Shadrinsk", "adminCode1": "08", "geonameId": 8059303, "fcl": "P", "name": "Shadrinsk", "countryName": "Russia", "fclName": "city, village,...", "fcode": "PPL", "adminName1": "Bashkortostan", "countryCode": "RU", "population": 0, "fcodeName": "populated place"}, "geometry": {"coordinates": [59.3258, 55.5781], "type": "Point"}, "type": "feature"}]}