{"type": "FeatureCollection", "features": [{"type": "Feature", "geometry": {"coordinates": [30.2877, 54.2131], "type": "Point"}, "properties": {"countryCode": "BY", "countryId": "630336", "fcodeName": "seat of a second-order administrative division", "adminName1": "Mahilyowskaya Voblasts\u02bc", "fclName": "city, village,...", "fcl": "P", "countryName": "Belarus", "fcode": "PPLA2", "geonameId": 622034, "population": 13485, "adminCode1": "06", "name": "Shklow", "toponymName": "Shklow"}}, {"type": "Feature", "geometry": {"coordinates": [30.248, 54.2128], "type": "Point"}, "properties": {"countryCode": "BY", "countryId": "630336", "fcodeName": "populated place", "adminName1": "Mahilyowskaya Voblasts\u02bc", "fclName": "city, village,...", "fcl": "P", "countryName": "Belarus", "fcode": "PPL", "geonameId": 8281122, "population": 0, "adminCode1": "06", "name": "Malyy Staryy Shklov", "toponymName": "Malyy Staryy Shklov"}}, {"type": "Feature", "geometry": {"coordinates": [30.2487, 54.2019], "type": "Point"}, "properties": {"countryCode": "BY", "countryId": "630336", "fcodeName": "populated place", "adminName1": "Mahilyowskaya Voblasts\u02bc", "fclName": "city, village,...", "fcl": "P", "countryName": "Belarus", "fcode": "PPL", "geonameId": 8281121, "population": 0, "adminCode1": "06", "name": "Bol\u2019shoy Staryy Shklov", "toponymName": "Bol\u2019shoy Staryy Shklov"}}, {"type": "Feature", "geometry": {"coordinates": [30.3195, 54.1973], "type": "Point"}, "properties": {"countryCode": "BY", "countryId": "630336", "fcodeName": "populated place", "adminName1": "Mahilyowskaya Voblasts\u02bc", "fclName": "city, village,...", "fcl": "P", "countryName": "Belarus", "fcode": "PPL", "geonameId": 619127, "population": 0, "adminCode1": "06", "name": "Maloye Zarechcha", "toponymName": "Maloye Zarechcha"}}]}