{"type": "FeatureCollection", "features": [{"properties": {"countryId": "630336", "toponymName": "Shklow", "adminCode1": "06", "geonameId": 622034, "fcl": "P", "name": "Shklow", "countryName": "Belarus", "fclName": "city, village,...", "fcode": "PPLA2", "adminName1": "Mahilyowskaya Voblasts\u02bc", "countryCode": "BY", "population": 13485, "fcodeName": "seat of a second-order administrative division"}, "geometry": {"coordinates": [30.2877, 54.2131], "type": "Point"}, "type": "feature"}, {"properties": {"countryId": "630336", "toponymName": "Malyy Staryy Shklov", "adminCode1": "06", "geonameId": 8281122, "fcl": "P", "name": "Malyy Staryy Shklov", "countryName": "Belarus", "fclName": "city, village,...", "fcode": "PPL", "adminName1": "Mahilyowskaya Voblasts\u02bc", "countryCode": "BY", "population": 0, "fcodeName": "populated place"}, "geometry": {"coordinates": [30.248, 54.2128], "type": "Point"}, "type": "feature"}, {"properties": {"countryId": "630336", "toponymName": "Bol\u2019shoy Staryy Shklov", "adminCode1": "06", "geonameId": 8281121, "fcl": "P", "name": "Bol\u2019shoy Staryy Shklov", "countryName": "Belarus", "fclName": "city, village,...", "fcode": "PPL", "adminName1": "Mahilyowskaya Voblasts\u02bc", "countryCode": "BY", "population": 0, "fcodeName": "populated place"}, "geometry": {"coordinates": [30.2487, 54.2019], "type": "Point"}, "type": "feature"}, {"properties": {"countryId": "630336", "toponymName": "Maloye Zarechcha", "adminCode1": "06", "geonameId": 619127, "fcl": "P", "name": "Maloye Zarechcha", "countryName": "Belarus", "fclName": "city, village,...", "fcode": "PPL", "adminName1": "Mahilyowskaya Voblasts\u02bc", "countryCode": "BY", "population": 0, "fcodeName": "populated place"}, "geometry": {"coordinates": [30.3195, 54.1973], "type": "Point"}, "type": "feature"}]}