{"features": [{"properties": {"fcl": "P", "geonameId": 622034, "countryId": "630336", "fcode": "PPLA2", "name": "Shklow", "countryName": "Belarus", "population": 13485, "fclName": "city, village,...", "adminName1": "Mahilyowskaya Voblasts\u02bc", "adminCode1": "06", "fcodeName": "seat of a second-order administrative division", "countryCode": "BY", "toponymName": "Shklow"}, "geometry": {"coordinates": [30.2877, 54.2131], "type": "Point"}, "type": "Feature"}, {"properties": {"fcl": "P", "geonameId": 8281122, "countryId": "630336", "fcode": "PPL", "name": "Malyy Staryy Shklov", "countryName": "Belarus", "population": 0, "fclName": "city, village,...", "adminName1": "Mahilyowskaya Voblasts\u02bc", "adminCode1": "06", "fcodeName": "populated place", "countryCode": "BY", "toponymName": "Malyy Staryy Shklov"}, "geometry": {"coordinates": [30.248, 54.2128], "type": "Point"}, "type": "Feature"}, {"properties": {"fcl": "P", "geonameId": 8281121, "countryId": "630336", "fcode": "PPL", "name": "Bol\u2019shoy Staryy Shklov", "countryName": "Belarus", "population": 0, "fclName": "city, village,...", "adminName1": "Mahilyowskaya Voblasts\u02bc", "adminCode1": "06", "fcodeName": "populated place", "countryCode": "BY", "toponymName": "Bol\u2019shoy Staryy Shklov"}, "geometry": {"coordinates": [30.2487, 54.2019], "type": "Point"}, "type": "Feature"}, {"properties": {"fcl": "P", "geonameId": 619127, "countryId": "630336", "fcode": "PPL", "name": "Maloye Zarechcha", "countryName": "Belarus", "population": 0, "fclName": "city, village,...", "adminName1": "Mahilyowskaya Voblasts\u02bc", "adminCode1": "06", "fcodeName": "populated place", "countryCode": "BY", "toponymName": "Maloye Zarechcha"}, "geometry": {"coordinates": [30.3195, 54.1973], "type": "Point"}, "type": "Feature"}], "type": "FeatureCollection"}