{"type": "FeatureCollection", "features": [{"type": "Feature", "geometry": {"coordinates": [41.38833, 56.84865], "type": "Point"}, "properties": {"countryCode": "RU", "countryId": "2017370", "fcodeName": "populated place", "adminName1": "Ivanovo", "fclName": "city, village,...", "fcl": "P", "countryName": "Russia", "fcode": "PPL", "geonameId": 493231, "population": 60705, "adminCode1": "21", "name": "Shuya", "toponymName": "Shuya"}}]}