{"features": [{"properties": {"hgr_source_url": "http://babel.hathitrust.org/cgi/pt?id=uc1.b4583201;view=1up;seq=129", "fcl": "P", "fclName": "city, village,...", "hgr_partof_id": 3.0, "hgr_alt_name": null, "fcodeName": "populated place", "hgr_ru_uezd": "not_in_text", "hgr_partof_prov_name": "\u0412\u043b\u0430\u0434\u0438\u043c\u0435\u0440\u0441\u043a\u043e\u0435 \u041d\u0430\u043c\u0463\u0441\u0442\u043d\u0438\u0447\u0435\u0441\u0442\u0432\u043e", "hgr_name": "\u0428\u0443\u044f", "population": 60705, "adminCode1": "21", "fcode": "PPL", "geonameId": 493231, "hgr_text": "\u0428\u0423\u042f, \u0441\u044a 1778 \u0433\u043e\u0434\u0443 \u0433\u043e\u0440\u043e\u0434\u044a \u0412\u043e\u043b\u043e\u0434\u0438\u043c\u0435\u0440\u0441\u043a\u0430\u0433\u043e \u041d\u0430\u043c\u0463\u0441\u0442\u043d\u0438\u0447\u0435\u0441\u0442\u0432\u0430. \u0417\u0434\u0463\u0441\u044c \u0431\u044b\u0432\u0430\u0435\u0442\u044a \u0433\u043e\u0434\u043e\u0432\u0430\u044f \u044f\u0440\u043c\u0430\u0440\u043a\u0430 24 \u0406\u044e\u043b\u044f , \u043d\u0430\u0437\u044b\u0432\u0430\u0435\u043c\u0430\u044f \u0411\u043e\u0440\u0438\u0441\u043e\u0433\u043b\u0463\u0431\u0441\u043a\u0430\u044f ; \u0434\u0430 \u043e\u043d\u0430\u0433\u043e \u0432\u044a \u0443\u0463\u0437\u0434\u0463 \u0432\u044a \u043e\u0442\u0447\u0438\u043d\u0463 \u041d\u0438\u043a\u043e\u043b\u0430\u0435\u0432\u0441\u043a\u0430\u0433\u043e \u0428\u0430\u0440\u0442\u043e\u043b\u044c\u0441\u043a\u0430\u0433\u043e \u043c\u043e\u043d\u0430\u0441\u0442\u044b\u0440\u044f \u0432\u044a \u0441\u0435\u043b\u0463 \u041f\u0443\u043f\u043a\u0430\u0445\u044a \u0442\u043e\u0440\u0433\u0443\u044e\u0442\u044a \u043a\u0443\u043f\u0446\u044b \u0420\u043e\u0441\u0441\u0456\u0439\u0441\u043a\u0438\u043c\u0438 \u0438 \u0438\u043d\u043e\u0441\u0442\u0440\u0430\u043d\u043d\u044b\u043c\u0438 \u0442\u043e\u0432\u0430\u0440\u0430\u043c\u0438.", "hgr_type": "\u0433\u043e\u0440\u043e\u0434\u044a", "hgr_name_modern_sp": "\u0428\u0443\u044f", "hgr_page": 130, "hgr_uezd_modern_sp": "not_\u0438n_text", "toponymName": "Shuya", "countryCode": "RU", "hgr_html_text": "\u0428\u0423\u042f, \u0441\u044a 1778 \u0433\u043e\u0434\u0443 </span><span class=\"font0\" style=\"font-style:italic;\">\u0433\u043e\u0440\u043e\u0434\u044a </span><span class=\"font0\">\u0412\u043e\u043b\u043e\u0434\u0438\u043c\u0435\u0440\u0441\u043a\u0430\u0433\u043e \u041d\u0430\u043c\u0463\u0441\u0442\u043d\u0438\u0447\u0435\u0441\u0442\u0432\u0430. \u0417\u0434\u0463\u0441\u044c \u0431\u044b\u0432\u0430\u0435\u0442\u044a \u0433\u043e\u0434\u043e\u0432\u0430\u044f \u044f\u0440\u043c\u0430\u0440\u043a\u0430 24 \u0406\u044e\u043b\u044f </span><span class=\"font0\" style=\"font-style:italic;\">,</span><span class=\"font0\"> \u043d\u0430\u0437\u044b\u0432\u0430\u0435\u043c\u0430\u044f \u0411\u043e\u0440\u0438\u0441\u043e\u0433\u043b\u0463\u0431\u0441\u043a\u0430\u044f ; \u0434\u0430 \u043e\u043d\u0430\u0433\u043e \u0432\u044a \u0443\u0463\u0437\u0434\u0463 \u0432\u044a \u043e\u0442\u0447\u0438\u043d\u0463 \u041d\u0438\u043a\u043e\u043b\u0430\u0435\u0432\u0441\u043a\u0430\u0433\u043e \u0428\u0430\u0440\u0442\u043e\u043b\u044c\u0441\u043a\u0430\u0433\u043e \u043c\u043e\u043d\u0430\u0441\u0442\u044b\u0440\u044f \u0432\u044a \u0441\u0435\u043b\u0463 \u041f\u0443\u043f\u043a\u0430\u0445\u044a \u0442\u043e\u0440\u0433\u0443\u044e\u0442\u044a \u043a\u0443\u043f\u0446\u044b \u0420\u043e\u0441\u0441\u0456\u0439\u0441\u043a\u0438\u043c\u0438 \u0438 \u0438\u043d\u043e\u0441\u0442\u0440\u0430\u043d\u043d\u044b\u043c\u0438 \u0442\u043e\u0432\u0430\u0440\u0430\u043c\u0438.</span>", "hgr_prov_stem": "\u0432\u043b\u0430\u0434\u0438\u043c\u0435\u0440\u0441\u043a", "countryName": "Russia", "hgr_uezd_stem": "\u043d\u043e\u0442_\u0438\u043d_\u0442\u0435x\u0442", "adminName1": "Ivanovo", "name": "Shuya", "hgr_admin_hierarchy": "\u0432\u043b\u0430\u0434\u0438\u043c\u0435\u0440\u0441\u043a", "hgr_prov_modern_sp": "\u0412\u043e\u043b\u043e\u0434\u0438\u043c\u0435\u0440\u0441\u043a\u043e\u0433\u043e \u041d\u0430\u043c\u0435\u0441\u0442\u043d\u0438\u0447\u0435\u0441\u0442\u0432\u0430", "hgr_admin1_partof": 3.0, "countryId": "2017370", "hgr_admin2_partof": null, "hgr_ru_prov": "\u0412\u043e\u043b\u043e\u0434\u0438\u043c\u0435\u0440\u0441\u043a\u0430\u0433\u043e \u041d\u0430\u043c\u0463\u0441\u0442\u043d\u0438\u0447\u0435\u0441\u0442\u0432\u0430"}, "type": "Feature", "geometry": {"coordinates": [41.38833, 56.84865], "type": "Point"}}], "type": "FeatureCollection"}