{"type": "FeatureCollection", "features": [{"properties": {"countryId": "2017370", "toponymName": "Shuya", "adminCode1": "21", "geonameId": 493231, "fcl": "P", "name": "Shuya", "countryName": "Russia", "fclName": "city, village,...", "fcode": "PPL", "adminName1": "Ivanovo", "countryCode": "RU", "population": 60705, "fcodeName": "populated place"}, "geometry": {"coordinates": [41.38833, 56.84865], "type": "Point"}, "type": "feature"}]}