{"type": "FeatureCollection", "features": [{"type": "Feature", "geometry": {"coordinates": [34.99434, 53.6947], "type": "Point"}, "properties": {"countryCode": "RU", "countryId": "2017370", "fcodeName": "populated place", "adminName1": "Kaluga", "fclName": "city, village,...", "fcl": "P", "countryName": "Russia", "fcode": "PPL", "geonameId": 495203, "population": 0, "adminCode1": "25", "name": "Shchigry", "toponymName": "Shchigry"}}, {"type": "Feature", "geometry": {"coordinates": [35.91997, 53.43481], "type": "Point"}, "properties": {"countryCode": "RU", "countryId": "2017370", "fcodeName": "populated place", "adminName1": "Orjol", "fclName": "city, village,...", "fcl": "P", "countryName": "Russia", "fcode": "PPL", "geonameId": 816607, "population": 0, "adminCode1": "56", "name": "Shchigry", "toponymName": "Shchigry"}}, {"type": "Feature", "geometry": {"coordinates": [34.42025, 54.01959], "type": "Point"}, "properties": {"countryCode": "RU", "countryId": "2017370", "fcodeName": "populated place", "adminName1": "Kaluga", "fclName": "city, village,...", "fcl": "P", "countryName": "Russia", "fcode": "PPL", "geonameId": 814271, "population": 0, "adminCode1": "25", "name": "Shchigry", "toponymName": "Shchigry"}}, {"type": "Feature", "geometry": {"coordinates": [36.90432, 51.87555], "type": "Point"}, "properties": {"countryCode": "RU", "countryId": "2017370", "fcodeName": "populated place", "adminName1": "Kursk", "fclName": "city, village,...", "fcl": "P", "countryName": "Russia", "fcode": "PPL", "geonameId": 495206, "population": 19198, "adminCode1": "41", "name": "Shchigry", "toponymName": "Shchigry"}}]}