{"type": "FeatureCollection", "features": [{"properties": {"countryId": "2017370", "toponymName": "Shchigry", "adminCode1": "25", "geonameId": 495203, "fcl": "P", "name": "Shchigry", "countryName": "Russia", "fclName": "city, village,...", "fcode": "PPL", "adminName1": "Kaluga", "countryCode": "RU", "population": 0, "fcodeName": "populated place"}, "geometry": {"coordinates": [34.99434, 53.6947], "type": "Point"}, "type": "feature"}, {"properties": {"countryId": "2017370", "toponymName": "Shchigry", "adminCode1": "56", "geonameId": 816607, "fcl": "P", "name": "Shchigry", "countryName": "Russia", "fclName": "city, village,...", "fcode": "PPL", "adminName1": "Orjol", "countryCode": "RU", "population": 0, "fcodeName": "populated place"}, "geometry": {"coordinates": [35.91997, 53.43481], "type": "Point"}, "type": "feature"}, {"properties": {"countryId": "2017370", "toponymName": "Shchigry", "adminCode1": "25", "geonameId": 814271, "fcl": "P", "name": "Shchigry", "countryName": "Russia", "fclName": "city, village,...", "fcode": "PPL", "adminName1": "Kaluga", "countryCode": "RU", "population": 0, "fcodeName": "populated place"}, "geometry": {"coordinates": [34.42025, 54.01959], "type": "Point"}, "type": "feature"}, {"properties": {"countryId": "2017370", "toponymName": "Shchigry", "adminCode1": "41", "geonameId": 495206, "fcl": "P", "name": "Shchigry", "countryName": "Russia", "fclName": "city, village,...", "fcode": "PPL", "adminName1": "Kursk", "countryCode": "RU", "population": 19198, "fcodeName": "populated place"}, "geometry": {"coordinates": [36.90432, 51.87555], "type": "Point"}, "type": "feature"}]}