{"type": "FeatureCollection", "features": [{"type": "Feature", "geometry": {"coordinates": [37.95634, 48.93555], "type": "Point"}, "properties": {"countryCode": "UA", "countryId": "690791", "fcodeName": "populated place", "adminName1": "Donetsk", "fclName": "city, village,...", "fcl": "P", "countryName": "Ukraine", "fcode": "PPL", "geonameId": 688505, "population": 0, "adminCode1": "05", "name": "Yampol'", "toponymName": "Yampil\u2019"}}]}