{"features": [{"properties": {"hgr_name_modern_sp": "\u042f\u043c\u043f\u043e\u043b\u044c", "countryCode": "UA", "hgr_admin_hierarchy": "\u0445\u0430\u0440\u044c\u043a\u043e\u0432\u0441\u043a|\u0438\u0437\u044e\u043c\u0441\u043a", "fcl": "P", "toponymName": "Yampil\u2019", "countryName": "Ukraine", "adminCode1": "05", "fcodeName": "populated place", "population": 0, "hgr_partof_id": 69.0, "hgr_page": 132, "hgr_html_text": "\u042f\u041c\u041f\u041e\u041b\u042c, </span><span class=\"font0\" style=\"font-style:italic;\">\u0441\u043b\u043e\u0431\u043e\u0434\u0430</span><span class=\"font0\"> \u0425\u0430\u0440\u044c\u043a\u043e\u0432\u0441\u043a\u0430\u0433\u043e \u041d\u0430\u043c\u0463\u0441\u0442\u043d\u0438\u0447\u0435\u0441\u0442\u0432\u0430 \u0432\u044a \u0418\u0437\u044e\u043c\u0441\u043a\u043e\u043c\u044a \u0443\u0463\u0437\u0434\u0463. \u0417\u0434\u0463\u0441\u044c \u0431\u044b\u0432\u0430\u044e\u0442\u044a \u0432\u044a \u0433\u043e\u0434\u0443 \u0442\u0440\u0438 \u044f\u0440\u043c\u0430\u0440\u043a\u0438: \u043f\u0435\u0440\u0432\u0430\u044f \u041c\u0430\u0456\u044f 9, \u0432\u044a \u0434\u0435\u043d\u044c \u0427\u0443\u0434\u043e\u0442\u0432\u043e\u0440\u0446\u0430 \u041d\u0438\u043a\u043e\u043b\u0430\u044f , \u0432\u0442\u043e\u0440\u0430\u044f \u041d\u043e\u044f\u0431\u0440\u044f 1, \u0432\u044a \u0434\u0435\u043d\u044c \u041a\u043e\u0437\u043c\u044b \u0438 \u0414\u0430\u043c\u0456\u0430\u043d\u0430, \u0442\u0440\u0435\u0442\u0456\u044f \u0414\u0435\u043a\u0430\u0431\u0440\u044f 6, \u0432\u044a \u0434\u0435\u043d\u044c \u0427\u0443\u0434\u043e\u0442\u0432\u043e\u0440\u0446\u0430 \u041d\u0438\u043a\u043e\u043b\u0430\u044f; \u043a\u0443\u043f\u0446\u044b \u043f\u0440\u0456\u0463\u0437\u0436\u0430\u044e\u0442\u044a \u043d\u0430 \u043e\u043d\u044b\u044f \u0438\u0437\u044a \u0440\u0430\u0437\u043d\u044b\u0445\u044a \u0433\u043e\u0440\u043e\u0434\u043e\u0432\u044a \u0441\u044a \u0448\u0435\u043b\u043a\u043e\u0432\u044b\u043c\u0438 \u0438 \u043f\u0440\u043e\u0447\u0438\u043c\u0438 \u0442\u043e\u0432\u0430\u0440\u0430\u043c\u0438.</span>", "UPDATE_SCRIPT": "python add_town_by_geoname_id.py \u042f\u043c\u043f\u043e\u043b\u044c_794.geojson 688505", "hgr_text": "\u042f\u041c\u041f\u041e\u041b\u042c, \u0441\u043b\u043e\u0431\u043e\u0434\u0430 \u0425\u0430\u0440\u044c\u043a\u043e\u0432\u0441\u043a\u0430\u0433\u043e \u041d\u0430\u043c\u0463\u0441\u0442\u043d\u0438\u0447\u0435\u0441\u0442\u0432\u0430 \u0432\u044a \u0418\u0437\u044e\u043c\u0441\u043a\u043e\u043c\u044a \u0443\u0463\u0437\u0434\u0463. \u0417\u0434\u0463\u0441\u044c \u0431\u044b\u0432\u0430\u044e\u0442\u044a \u0432\u044a \u0433\u043e\u0434\u0443 \u0442\u0440\u0438 \u044f\u0440\u043c\u0430\u0440\u043a\u0438: \u043f\u0435\u0440\u0432\u0430\u044f \u041c\u0430\u0456\u044f 9, \u0432\u044a \u0434\u0435\u043d\u044c \u0427\u0443\u0434\u043e\u0442\u0432\u043e\u0440\u0446\u0430 \u041d\u0438\u043a\u043e\u043b\u0430\u044f , \u0432\u0442\u043e\u0440\u0430\u044f \u041d\u043e\u044f\u0431\u0440\u044f 1, \u0432\u044a \u0434\u0435\u043d\u044c \u041a\u043e\u0437\u043c\u044b \u0438 \u0414\u0430\u043c\u0456\u0430\u043d\u0430, \u0442\u0440\u0435\u0442\u0456\u044f \u0414\u0435\u043a\u0430\u0431\u0440\u044f 6, \u0432\u044a \u0434\u0435\u043d\u044c \u0427\u0443\u0434\u043e\u0442\u0432\u043e\u0440\u0446\u0430 \u041d\u0438\u043a\u043e\u043b\u0430\u044f; \u043a\u0443\u043f\u0446\u044b \u043f\u0440\u0456\u0463\u0437\u0436\u0430\u044e\u0442\u044a \u043d\u0430 \u043e\u043d\u044b\u044f \u0438\u0437\u044a \u0440\u0430\u0437\u043d\u044b\u0445\u044a \u0433\u043e\u0440\u043e\u0434\u043e\u0432\u044a \u0441\u044a \u0448\u0435\u043b\u043a\u043e\u0432\u044b\u043c\u0438 \u0438 \u043f\u0440\u043e\u0447\u0438\u043c\u0438 \u0442\u043e\u0432\u0430\u0440\u0430\u043c\u0438.", "hgr_prov_modern_sp": "\u0425\u0430\u0440\u044c\u043a\u043e\u0432\u0441\u043a\u043e\u0433\u043e \u041d\u0430\u043c\u0435\u0441\u0442\u043d\u0438\u0447\u0435\u0441\u0442\u0432\u0430", "hgr_name": "\u042f\u043c\u043f\u043e\u043b\u044c", "name": "Yampol'", "hgr_ru_uezd": "\u0418\u0437\u044e\u043c\u0441\u043a\u043e\u043c\u044a \u0443\u0463\u0437\u0434\u0463", "hgr_source_url": "http://babel.hathitrust.org/cgi/pt?id=uc1.b4583201;view=1up;seq=131", "countryId": "690791", "hgr_ru_prov": "\u0425\u0430\u0440\u044c\u043a\u043e\u0432\u0441\u043a\u0430\u0433\u043e \u041d\u0430\u043c\u0463\u0441\u0442\u043d\u0438\u0447\u0435\u0441\u0442\u0432\u0430", "hgr_uezd_stem": "\u0438\u0437\u044e\u043c\u0441\u043a", "hgr_admin1_partof": 37.0, "hgr_alt_name": null, "adminName1": "Donetsk", "hgr_admin2_partof": 69.0, "fcode": "PPL", "fclName": "city, village,...", "hgr_prov_stem": "\u0445\u0430\u0440\u044c\u043a\u043e\u0432\u0441\u043a", "geonameId": 688505, "hgr_type": "\u0441\u043b\u043e\u0431\u043e\u0434\u0430", "hgr_uezd_modern_sp": "\u0418\u0437\u044e\u043c\u0441\u043a\u043e\u043c \u0443\u0435\u0437\u0434\u0435"}, "geometry": {"coordinates": [37.95634, 48.93555], "type": "Point"}, "type": "Feature"}], "type": "FeatureCollection"}