{"type": "FeatureCollection", "features": [{"properties": {"countryId": "690791", "toponymName": "Yampil\u2019", "adminCode1": "05", "geonameId": 688505, "fcl": "P", "name": "Yampol'", "countryName": "Ukraine", "fclName": "city, village,...", "fcode": "PPL", "adminName1": "Donetsk", "countryCode": "UA", "population": 0, "fcodeName": "populated place"}, "geometry": {"coordinates": [37.95634, 48.93555], "type": "Point"}, "type": "feature"}]}